Workbook
Name Afectación_Económica: '3 PROBABIL E IMPACTO INHERENTE'!$X$9:$X$14
Name AFECTACIÓN_ECONÓMICA_EXTENDIDA: '3 PROBABIL E IMPACTO INHERENTE'!$X$9:$X$14
Name Definicion_tratamiento: '11 FORMULAS'!#REF!
Name E_Relaciones_Laborales: '11 FORMULAS'!$C$12:$C$17
Name Ejecución_administración_de_procesos: Tabla2[Ejecución_administración_de_procesos]
Name Evento_externo: '11 FORMULAS'!$F$45:$F$48
Name F_Usuarios_Productos_y_Prácticas_Organizacionales: '11 FORMULAS'!$C$18:$C$23
Name Fiscal: '11 FORMULAS'!$B$32:$B$43
Name Fiscal_A: '11 FORMULAS'!#REF!
Name Fiscal_B: '11 FORMULAS'!#REF!
Name G_Daños_Activos_Físicos: '11 FORMULAS'!$C$24:$C$26
Name Gestión: '11 FORMULAS'!$A$32:$A$34
Name Gestiòn: '11 FORMULAS'!#REF!
Name Gestión_A: '11 FORMULAS'!#REF!
Name Gestión_B: '11 FORMULAS'!#REF!
Name IMPACTO_PROCESOS: '[1]LISTAS FORMULAS'!$C$3:$C$7
Name IMPACTO_PROCESOS: '[1]LISTAS FORMULAS'!$C$3:$C$7
Name IMPACTO_PROCESOS: '[1]LISTAS FORMULAS'!$C$3:$C$7
Name IMPACTO_PROCESOS: '[1]LISTAS FORMULAS'!$C$3:$C$7
Name IMPACTO_PROCESOS: '[1]LISTAS FORMULAS'!$C$3:$C$7
Name IMPACTO_PROCESOS: '[1]LISTAS FORMULAS'!$C$3:$C$7
Name Infraestructura: '11 FORMULAS'!$E$45:$E$48
Name Integridad_Pública_Corrupción: '11 FORMULAS'!$D$32:$D$43
Name Integridad_Pública_LA_FT_FP: '11 FORMULAS'!$E$32:$E$43
Name IntegridadPública_Corrupción: '11 FORMULAS'!#REF!
Name IntegridadPública_LA_FT_FP: '11 FORMULAS'!#REF!
Name IP_CANALES_LA_FT_FP: 'H1'!$D$30:$D$34
Name IP_CONTRAPARTES_LA_FT_FP: 'H1'!$D$20:$D$24
Name IP_JURISDICCION_LA_FT_FP: 'H1'!$D$35:$D$39
Name IP_PRODUCTOS__LA_FT_FP: 'H1'!$D$25:$D$29
Name NO_APLICA: 'H1'!$U$2
Name opciones: '[1]LISTAS FORMULAS'!$F$3:$F$4
Name opciones: '[1]LISTAS FORMULAS'!$F$3:$F$4
Name opciones: '[1]LISTAS FORMULAS'!$F$3:$F$4
Name opciones: '[1]LISTAS FORMULAS'!$F$3:$F$4
Name opciones: '[1]LISTAS FORMULAS'!$F$3:$F$4
Name opciones: '[1]LISTAS FORMULAS'!$F$3:$F$4
Name opciones2: '[1]LISTAS FORMULAS'!$G$3:$G$5
Name opciones2: '[1]LISTAS FORMULAS'!$G$3:$G$5
Name opciones2: '[1]LISTAS FORMULAS'!$G$3:$G$5
Name opciones2: '[1]LISTAS FORMULAS'!$G$3:$G$5
Name opciones2: '[1]LISTAS FORMULAS'!$G$3:$G$5
Name opciones2: '[1]LISTAS FORMULAS'!$G$3:$G$5
Name Plan_accion: '11 FORMULAS'!#REF!
Name Plan_acción: '11 FORMULAS'!#REF!
Name Plan_de_acción: '11 FORMULAS'!#REF!
Name Posibilidad__de_efecto_dañoso_sobre_el_interes_patrimonial: '11 FORMULAS'!#REF!
Name Posibilidad_de_pérdida_Económica: '11 FORMULAS'!#REF!
Name Quince_Cero: '[1]LISTAS FORMULAS'!$F$14:$F$15
Name Quince_Cero: '[1]LISTAS FORMULAS'!$F$14:$F$15
Name Quince_Cero: '[1]LISTAS FORMULAS'!$F$14:$F$15
Name Quince_Cero: '[1]LISTAS FORMULAS'!$F$14:$F$15
Name Quince_Cero: '[1]LISTAS FORMULAS'!$F$14:$F$15
Name Quince_Cero: '[1]LISTAS FORMULAS'!$F$14:$F$15
Name Rango_Calificacion_Ejecucion: '[1]LISTAS FORMULAS'!$H$3:$H$5
Name Rango_Calificacion_Ejecucion: '[1]LISTAS FORMULAS'!$H$3:$H$5
Name Rango_Calificacion_Ejecucion: '[1]LISTAS FORMULAS'!$H$3:$H$5
Name Rango_Calificacion_Ejecucion: '[1]LISTAS FORMULAS'!$H$3:$H$5
Name Rango_Calificacion_Ejecucion: '[1]LISTAS FORMULAS'!$H$3:$H$5
Name Rango_Calificacion_Ejecucion: '[1]LISTAS FORMULAS'!$H$3:$H$5

Sheet INSTRUCTIVO ACTIVOS
A1: INSTRUCTIVO DILIGENCIAMIENTO DE ACTIVOS DE INFORMACIÓN
A2: OBJETIVO Establecer de manera clara, detallada y paso a paso la forma correcta de diligenciar cada campo del Formato de Gestión y Clasificación de Activos de Información, permitiendo a las dependencias de la entidad identificar, clasificar, valorar y proteger sus activos de información conforme a los lineamientos del Modelo de Seguridad y Privacidad de la Información (MSPI), ISO 27001, Ley 1712 de 2014, Ley 1581 de 2012 y demás normatividad aplicable. A continuación se presenta el diligenciamiento fila por fila para facilitar el registro del formato.
A3: FASE | B3: Columna | C3: Descripción - Lineamientos para el diligenciamiento
A4: FASE 1 | B4: MACROPROCESO | C4: Seleccione el macroproceso de la lista desplegable entre: Direccionamiento Estratégico Gestión de la Información y las Comunicaciones Gestión de Servicios de Salud Gestión Educativa Convivencia Ciudadana, Seguridad y Orden Público Desarrollo Social Integral y Ambiental del Territorio Gestión Financiera Gestión Catastral Gestión Administrativa Gestión del Talento Humano Gestión Jurídica Gestión Estadística Control Interno
B5: PROCESO | C5: Seleccione el proceso relacionado con el macroproceso y con el activo de información de la lista desplegable.
B6: CÓDIGO DEL SISTEMA DE GESTIÓN DOCUMENTAL | C6: Diligencie el código documental asignado en la Tabla de Retención Documental (TDR) o instrumentos archivísticos. Si no existe, escriba “No aplica”.
B7: IDENTIFICADOR | C7: Registre un código único que permita identificar el activo. Se recomienda usar una combinación de la dependencia + número consecutivo. Por ejemplo, TIC-001
B8: TIPO | C8: Seleccione el tipo de activo de información de la lista desplegable entre: Información (Bases de datos de clientes, contratos, hojas de cálculo financieras, manuales internos, correos electrónicos, reportes de ventas) Software (Sistema ERP, antivirus, sistema operativo Windows/Linux, aplicación contable, CRM, aplicaciones móviles) Hardware (Servidores, computadores portátiles, impresoras, discos duros externos, routers, cámaras de seguridad) Servicios (Servicio de correo electrónico corporativo, hosting web, nube (AWS/Azure), internet empresarial, mesa de ayuda TI) Intangibles (Marca de la empresa, propiedad intelectual, licencias, patentes, reputación corporativa, know-how) Componentes de red (Switches, firewalls, access points Wi-Fi, cables de red, módems, balanceadores de carga) Recurso humano No aplica
B9: OFICINA | C9: Seleccione la dependencia u oficina responsable o relacionada con el activo de información de la lista desplegable entre: Despacho del Alcalde Agricultura Ambiente Asuntos Étnicos Cultura Desarrollo Social Educación Gobierno Gestión Institucional Hacienda Infraestructura Planeación Salud Turismo Vivienda General Jurídica Seguridad y Convivencia Comunicaciones Control I​nterno Control Interno y Disciplinario​ Cooperación Internacion​al​ Tecnologías de la Información y las Comunicaciones​ Progr​amas Especiales​ Posconflicto​ Equidad de Género​ Juventudes Libertad Religiosa Gestión Catastral
B10: SERIE DOCUMENTAL | C10: Ingrese la serie documental del área, dependencia o proceso donde se encuentra identificado el activo. Por ejemplo: Si el activo se encuentra en la secretaría jurírica y el activo es un PROCESO JURIDICO el número de serie 34-42
B11: SUBSERIE DOCUMENTAL | C11: Ingrese la subserie documental correspondiente a la serie donde se encuentra el activo. Por ejemplo: Para el PROCESO JURIDICO si es un proceso de cobro coactivo el número de serie sería 34-42 01
B12: NOMBRE | C12: Registre el nombre del activo de información de forma clara y específica.
B13: DESCRIPCIÓN | C13: Describa de manera resumida la función, contenido o propósito del activo.
B14: NOMBRE DEL RESPONSABLE DE LA PRODUCCIÓN DE LA INFORMACIÓN (PROPIETARIO DEL ACTIVO) | C14: Diligencie el nombre completo de la persona encargada de crear, generar o administrar funcionalmente la información.
B15: FECHA DE GENERACIÓN DE LA INFORMACIÓN | C15: Ingrese la fecha en la que el activo de información fue creado o comenzó a generarse.
B16: NOMBRE DEL RESPONSABLE DE LA INFORMACIÓN (CUSTODIO DEL ACTIVO) | C16: Ingrese el nombre completo de la persona encargada de custodiar, almacenar o mantener el activo.
... B20: IDIOMA | C20: Establezca el idioma en el que está redactado o disponible el activo.
A22: FASE 2 | B22: CONFIDENCIALIDAD | C22: Seleccione el nivel de restricción del activo de información según el acceso permitido de la lista desplegable entre: Información pública reservada: Es la información que no debe ser divulgada debido a que esto puede causar daño a intereses públicos. Solamente la Constitución o la ley pueden definir qué información es de carácter reservado. Información pública clasificada: Es la información que no debe ser divulgada debido a que se pueden vulnerar los derechos de las personas naturales o jurídicas, tales como: derecho de las personas a la intimidad, derecho a la vida, salud o seguridad y los secretos comerciales, industriales y profesionales. Información pública: Información que puede ser entregada o publicada sin restricciones a cualquier persona dentro y fuera de la entidad, sin que esto implique daños a terceros ni a las actividades y procesos de la entidad. No clasificada: Activos de Información que deben ser incluidos en el inventario y que aún no han sido clasificados, deben ser tratados como activos de INFORMACIÓN PÚBLICA RESERVADA. como: Hardware, Colaboradores de Planta o Contratistas
B23: INTEGRIDAD | C23: Seleccione el nivel de importancia relacionado con la exactitud y completitud de la información de la lista desplegable entre: Alta: Información cuya pérdida de exactitud y completitud puede conllevar un impacto negativo de índole legal o económica, retrasar sus funciones, o generar pérdidas de imagen severas de la entidad. Media: Información cuya pérdida de exactitud y completitud puede conllevar un impacto negativo de índole legal o económica, retrasar sus funciones, o generar pérdida de imagen moderada a funcionarios de la entidad. Baja: Información cuya pérdida de exactitud y completitud conlleva un impacto no significativo para la entidad o entes externos. No clasificada: Activos de Información que deben ser incluidos en el inventario y que aún no han sido clasificados, deben ser tratados como activos de información de integridad ALTA.
B24: DISPONIBILIDAD | C24: Seleccione el nivel de necesidad de acceso continuo al activo de información de la lista desplegable entre: Alta: La no disponibilidad de la información puede conllevar un impacto negativo de índole legal o económica, retrasar sus funciones, o generar pérdidas de imagen severas a entes externos. Media: La no disponibilidad de la información puede conllevar un impacto negativo de índole legal o económica, retrasar sus funciones, o generar pérdida de imagen moderada de la entidad. Baja: La no disponibilidad de la información puede afectar la operación normal de la entidad o entes externos, pero no conlleva implicaciones legales, económicas o de pérdida de imagen. No clasificada: Activos de Información que deben ser incluidos en el inventario y que aún no han sido clasificados, deben ser tratados como activos de información de disponibilidad ALTA.
B25: INFORMACIÓN PUBLICADA | C25: Seleccione el estado de publicación de la información de la lista desplegable entre: Publicada Disponible a solicitud No publicada o disponible
B26: LUGAR DE CONSULTA O UBICACIÓN | C26: Seleccione el lugar físico o digital donde se consulta o almacena el activo de la lista desplegable entre: Portal web propios Portal web de terceros Intranet Archivo físico Archivo digital Sistema de información Base de datos
A28: FASE 3 | B28: OBJETO LEGÍTIMO DE LA EXCEPCIÓN | C28: Se refiere a la justificación jurídica válida que permite reservar, clasificar o denegar el acceso a cierta información pública. Es la causal o motivo legal, como la protección de datos personales o la seguridad nacional, que autoriza a las entidades estatales a mantener documentos en reserva. (por ejemplo, por razones de seguridad, confidencialidad, o acceso restringido).
B29: FUNDAMENTO CONSTITUCIONAL O LEGAL | C29: Registrar la norma o artículo que soporta la clasificación o reserva de la información. Ejemplo: “Ley 1581 de 2012” para tipos de activo software, “Ley 1712 de 2014” para todos los demás activos“ Constitución Política Art. 15”.
B30: EXCEPCIÓN TOTAL O PARCIAL | C30: Indicar si la restricción aplica sobre toda la información o solo una parte de ella. Seleccione de la lista desplegable entre: Total Parical Sin excepción
B31: FECHA DE CLASIFICACIÓN | C31: Registrar la fecha en la cual el activo fue clasificado como reservado o clasificado. Utilizar formato DD/MM/AAAA. Ejemplo: “15/01/2026”.
B32: TIEMPO DE LA CLASIFICACIÓN | C32: Registrar el tiempo durante el cual la información permanecerá clasificada o reservada, según la normatividad aplicable. Ejemplo: “15 años”, “5 años”, “Permanente”.
A34: FASE 4 | B34: ¿CONTIENE DATOS PERSONALES? | C34: Seleccione si el activo contiene información asociada a personas naturales identificadas o identificables de la lista desplegable entre: Sí No. Por ejempolo si es de “Nómina = Sí”.
B35: ¿CONTIENE DATOS DE NIÑOS, NIÑAS O ADOLESCENTES? | C35: "Seleccione si el activo contiene información asociada a personas naturales identificadas o identificables de la lista desplegable entre: Sí No. Por ejempolo si es de “Base de datos estudiantil= Sí”."
B36: TIPOS DE DATOS PERSONALES | C36: Seleccione el tipo de dato personal contenido en el activo de la lista desplegable entre: Dato público: Información que puede ser conocida y consultada por cualquier persona sin necesidad de autorización del titular, debido a que no afecta su intimidad ni genera riesgos de discriminación. Ejemplo: nombre, estado civil, profesión u oficio, calidad de comerciante o servidor público. Dato semiprivado: Información que no tiene naturaleza íntima, reservada ni pública, y cuyo conocimiento puede interesar tanto al titular como a un grupo determinado de personas o a la sociedad. Su acceso está sujeto a ciertos controles. Ejemplo: historial crediticio, información financiera o comercial. Dato privado: Información que únicamente interesa al titular por su carácter íntimo o reservado y que no debe ser conocida públicamente sin autorización. Ejemplo: dirección de residencia, número telefónico personal, correos electrónicos personales o información laboral interna. Dato sensible: Información que puede afectar la intimidad del titular o generar discriminación en caso de ser divulgada. Requiere especial protección legal. Ejemplo: origen racial o étnico, orientación política, convicciones religiosas, datos biométricos, información de salud, orientación sexual. Dato vulnerable: Información asociada a personas que requieren protección especial debido a condiciones particulares de edad, discapacidad, situación social o dependencia. Incluye datos de menores de edad, adultos mayores, víctimas del conflicto, personas con discapacidad, entre otros. No aplica: Clasificación utilizada cuando la información evaluada no corresponde a datos personales o no contiene información relacionada con personas naturales identificadas o identificables.
B37: FINALIDAD DE LA RECOLECCIÓN DE LOS DATOS PERSONALES | C37: Registrar el propósito para el cual fueron recolectados los datos personales. Ejemplo: “Gestión de pagos salariales”, “Atención al ciudadano”, “Gestión académica”.
B38: EXISTE AUTORIZACIÓN PARA EL TRATAMIENTO DE DATOS PERSONALES | C38: Indicar si la entidad cuenta con autorización para el tratamiento de los datos personales.
A40: Nota: Si el campo no aplica al activo, escriba “No aplica” únicamente cuando el instructivo o el formato lo permitan.

Sheet ACTIVOS DE INFORMACIÓN
A8: ç | B8: FORMATO DE GESTIÓN Y CLASIFICACIÓN DE ACTIVOS DE INFORMACIÓN | AL8: Código: GIC-TEI-F-09
AL9: Fecha actualización:08/05/2026
AL10: Versión: 1
A12: IDENTIFICACIÓN DEL ACTIVO DE INFORMACIÓN ( LEY 594 DE 2000 - LEY 1712 DE 2014- DECRETO 103 DE 2015 - DECRETO 1080 DE 2015 - ISO 27001 ) | T12: CLASIFICACIÓN DEL ACTIVO DE INFORMACIÓN ( ISO 27001 ) | AC12: ÍNDICE DE INFORMACIÓN CLASIFICADA Y RESERVADA ( DECRETO 103 DE 2015) | AI12: DATOS PERSONALES ( LEY 1581 DE 2012) | AZ12: IDENTIFICACIÓN DEL ACTIVO DE INFORMACIÓN ( LEY 594 DE 2000 - LEY 1712 DE 2014- DECRETO 103 DE 2015 - DECRETO 1080 DE 2015 - ISO 27001 ) | BG12: CLASIFICACIÓN DEL ACTIVO DE INFORMACIÓN ( ISO 27001 ) | BM12: INDICE DE INFORMACIÓN CLASIFICADA O RESERVADA
A13: Proceso | B13: Subproceso | C13: Código del sistema de gestión documental | D13: Identificador | E13: Tipo | F13: Dependencia | G13: Serie documental | H13: Subserie documental | I13: Nombre | J13: Cantidad | K13: Descripción | L13: Cargo de la producción de la información ( Propietario del activo) | M13: Fecha de generación de la información | N13: Cargo de la persona encargada de la información (Custodio del activo) | O13: Fecha de ingreso del activo al archivo | P13: Soporte de registro | Q13: Medio de conservación | R13: Formato | S13: Idioma | T13: Confidencialidad | U13: C | V13: Integridad | W13: I | X13: Disponibilidad | Y13: D | Z13: Criticidad del activo | AA13: Información publicada | AB13: Lugar de consulta o ubicación | AC13: Objeto legítimo de la excepción | AD13: Fundamento constitucional o legal | AE13: Fundamento jurídico de la excepción | AF13: Excepción total o parcial | AG13: Fecha de clasificación (DD/MM/AAAA) | AH13: Tiempo de clasificación | AI13: ¿Contiene datos personales? | AJ13: ¿Contiene datos personales de niños, niñas o adolescentes? | AK13: Tipos de datos personales | AL13: Finalidad de la recolección de los datos personales | AM13: Existe la autorización para el tratamiento de los datos personales | AZ13: Tipo | BA13: Estado | BB13: Soporte de registro | BC13: Oficina | BD13: Medio de Conservación | BE13: Formato | BG13: Confidencialidad | BH13: Integridad | BI13: Disponibilidad | BJ13: Información publicada | BK13: Lugar de consulta o ubicación | BM13: Objeto legítimo de la excepción | BN13: Excepción total o parcial | BO13: Fundamento de constitución legal | BR13: ¿Contiene datos personales? | BS13: ¿Contiene datos personales de niños, niñas o adolescentes? | BT13: Tipos de datos personales | BU13: Finalidad de la recolección de los datos personales | BV13: Existe la autorización para el tratamiento de los datos personales | BX13: Direccionamiento Estratégico | BY13: Gestión de la Información y las Comunicaciones | BZ13: Gestión de Servicios de Salud | CA13: Gestión Educativa | CB13: Convivencia Ciudadana, Seguridad y Orden Público | CC13: Desarrollo Social Integral y Ambiental del Territorio | CD13: Gestión Financiera | CE13: Gestión Catastral | CF13: Gestión Administrativa | CG13: Gestión del Talento Humano | CH13: Gestión Jurídica | CI13: Gestión Estadística | CJ13: Control Interno | CL13: Macroproceso | CM13: Proceso
A14: Desarrollo Social Integral y Ambiental del Territorio | B14: Gestión Turística | E14: Software | F14: Turismo | I14: SISNET | J14: 1 | K14: Software de gestión de correspondencia. | L14: Auxiliar administrativa | M14: 46178 | N14: Profesional Atención al ciudadano. | O14: N/A | P14: Fisico | Q14: Digital | R14: Sistema de Información | T14: Información pública clasificada | U14: =IF(T14="No clasificada",5,IF(T14="Información pública clasificada",3,IF(T14="Información pública reservada",5,IF(T14="Información pública",1,)))) -> 3 | V14: Media | W14: =IF(V14="No clasificada",5,IF(V14="Baja",1,IF(V14="Media",3,IF(V14="Alta",5,)))) -> 3 | X14: Baja | Y14: =IF(X14="No clasificada",5,IF(X14="Baja",1,IF(X14="Media",3,IF(X14="Alta",5,)))) -> 1 | Z14: =IF(OR(T14=0,V14=0,X14=0),"FALTAN DATOS",IF(AND(U14=1,W14=1,Y14=1),"BAJA",(IF(OR(AND(U14=5,W14=5),AND(U14=5,Y14=5),AND(U14=5,Y14=5),AND(U14=5,W14=5,Y14=5)),"ALTA","MEDIA")))) -> MEDIA | AA14: No publicada o disponible | AB14: Portal web de terceros | AC14: Sí | AD14: =IF(AC14="Sí","Ley 1581 de 2012",IF(AC14="No","Ley 1755 de 2015","")) -> Ley 1581 de 2012 | AE14: =IF(AC14="Sí","Artículo 10 y 13",IF(AC14="No","Artículo 27","")) -> Artículo 10 y 13 | AF14: Parcial | AG14: 46167 | AH14: 1 año | AZ14: Información | BA14: Vigente | BB14: Fisico | BC14: Despacho del Alcalde | BD14: Fisico | BE14: Audio | BG14: Información pública reservada | BH14: Alta | BI14: Alta | BJ14: Publicada | BK14: Portal web propios | BM14: Sí | BN14: Total | BO14: Ley 1581 de 2012 | BP14: Artículo 10 y 13 | BR14: Sí | BS14: Sí | BT14: Dato público | BV14: Sí | BX14: Banco de Programas y Proyectos | BY14: Comunicación Pública | BZ14: Aseguramiento en Salud | CA14: Calidad Educativa | CB14: Convivencia y Cultura Ciudadana (Inspección de policía - comisaría de familia, metrología) | CC14: Gestión de Vivienda y Saneamiento Básico | CD14: Tesorería | CE14: Actualización Catastral | CF14: Atención al Ciudadano | CG14: Administración del Talento Humano | CH14: Gestión Contractual | CI14: Gestión del Sisbén | CJ14: Evaluación a la Gestión | CL14: Direccionamiento Estratégico | CM14: Banco de Programas y Proyectos
A15: Desarrollo Social Integral y Ambiental del Territorio | B15: Gestión Turística | E15: Servicios | F15: Turismo | I15: Sistema de Correo Institucional | J15: 1 | K15: Plataforma de correo electrónico institucional para comunicaciones oficiales. | L15: Secretario de despacho | M15: 46178 | N15: Técnico administrativo 1 -Oficina TIC | O15: N/A | Q15: Digital | R15: Otro | T15: Información pública clasificada | U15: =IF(T15="No clasificada",5,IF(T15="Información pública clasificada",3,IF(T15="Información pública reservada",5,IF(T15="Información pública",1,)))) -> 3 | V15: Alta | W15: =IF(V15="No clasificada",5,IF(V15="Baja",1,IF(V15="Media",3,IF(V15="Alta",5,)))) -> 5 | X15: Alta | Y15: =IF(X15="No clasificada",5,IF(X15="Baja",1,IF(X15="Media",3,IF(X15="Alta",5,)))) -> 5 | Z15: =IF(OR(T15=0,V15=0,X15=0),"FALTAN DATOS",IF(AND(U15=1,W15=1,Y15=1),"BAJA",(IF(OR(AND(U15=5,W15=5),AND(U15=5,Y15=5),AND(U15=5,Y15=5),AND(U15=5,W15=5,Y15=5)),"ALTA","MEDIA")))) -> MEDIA | AA15: No publicada o disponible | AB15: Portal web de terceros | AC15: No | AD15: =IF(AC15="Sí","Ley 1581 de 2012",IF(AC15="No","Ley 1755 de 2015","")) -> Ley 1755 de 2015 | AE15: =IF(AC15="Sí","Artículo 10 y 13",IF(AC15="No","Artículo 27","")) -> Artículo 27 | AF15: Parcial | AG15: 46167 | AH15: 1 año | AZ15: Software | BA15: Obsoleto | BB15: Digital | BC15: Agricultura | BD15: Digital | BE15: Documento de texto | BG15: Información pública clasificada | BH15: Media | BI15: Media | BJ15: Disponible a solicitud | BK15: Portal web de terceros | BM15: No | BN15: Parcial | BO15: Ley 1755 de 2015 | BP15: Artículo 27 | BR15: No | BS15: No | BT15: Dato semiprivado | BV15: No | BX15: Gestión para el Mejoramiento Institucional | BY15: Tecnologías de la Información | BZ15: Salud Pública | CA15: Cobertura Educativa | CB15: Gestión de Riesgo de Desastres | CC15: Gestión Cultural | CD15: Fiscalización | CE15: Conservación Catastral | CF15: Gestión Documental (Archivo - Ventanilla Única) | CG15: Seguridad y Salud en el Trabajo | CH15: Defensa Judicial | CI15: Información Estadística | CL15: Gestión de la Información y las Comunicaciones | CM15: Gestión para el Mejoramiento Institucional
A16: Desarrollo Social Integral y Ambiental del Territorio | B16: Gestión Turística | E16: Software | F16: Turismo | I16: Repositorio Archivo digital de correspondecia | J16: 1 | K16: Base de datos en Drive de la correspondencia fisica escaneada y digital | L16: Secretario de despacho | M16: 46178 | N16: Técnico administrativo 1 -Oficina TIC | O16: N/A | Q16: Digital | R16: Sistema de Información | T16: Información pública reservada | U16: =IF(T16="No clasificada",5,IF(T16="Información pública clasificada",3,IF(T16="Información pública reservada",5,IF(T16="Información pública",1,)))) -> 5 | V16: Alta | W16: =IF(V16="No clasificada",5,IF(V16="Baja",1,IF(V16="Media",3,IF(V16="Alta",5,)))) -> 5 | X16: Alta | Y16: =IF(X16="No clasificada",5,IF(X16="Baja",1,IF(X16="Media",3,IF(X16="Alta",5,)))) -> 5 | Z16: =IF(OR(T16=0,V16=0,X16=0),"FALTAN DATOS",IF(AND(U16=1,W16=1,Y16=1),"BAJA",(IF(OR(AND(U16=5,W16=5),AND(U16=5,Y16=5),AND(U16=5,Y16=5),AND(U16=5,W16=5,Y16=5)),"ALTA","MEDIA")))) -> ALTA | AA16: No publicada o disponible | AB16: Portal web de terceros | AC16: Sí | AD16: =IF(AC16="Sí","Ley 1581 de 2012",IF(AC16="No","Ley 1755 de 2015","")) -> Ley 1581 de 2012 | AF16: Total | AG16: 46177 | AH16: 1 año | AZ16: Hardware | BA16: Otro | BB16: Electronico | BC16: Ambiente | BD16: No aplica | BE16: Documento PDF | BG16: Información pública | BH16: Baja | BI16: Baja | BJ16: No publicada o disponible | BK16: Intranet | BM16: No aplica | BN16: Sin excepción | BT16: Dato privado | BX16: Ordenamiento Territorial | BZ16: Salud Ambiental | CA16: Inspección y Vigilancia Educativa | CB16: Víctimas | CC16: Gestión Turística | CD16: Contabilidad General | CF16: Administración Plaza de Mercado | CG16: Control Disciplinario | CH16: Juzgamiento Disciplinario | CL16: Gestión de Servicios de Salud | CM16: Ordenamiento Territorial
A17: Desarrollo Social Integral y Ambiental del Territorio | B17: Gestión Turística | E17: Servicios | F17: Turismo | I17: GECO | J17: 1 | K17: Plataforma de gestión contractual | L17: Secretario de despacho | M17: 46178 | N17: Secretaría Jurídica | O17: N/A | P17: Digital | Q17: Sistema de Información | R17: Sistema de Información | T17: Información pública reservada | U17: =IF(T17="No clasificada",5,IF(T17="Información pública clasificada",3,IF(T17="Información pública reservada",5,IF(T17="Información pública",1,)))) -> 5 | V17: Alta | W17: =IF(V17="No clasificada",5,IF(V17="Baja",1,IF(V17="Media",3,IF(V17="Alta",5,)))) -> 5 | X17: Baja | Y17: =IF(X17="No clasificada",5,IF(X17="Baja",1,IF(X17="Media",3,IF(X17="Alta",5,)))) -> 1 | Z17: =IF(OR(T17=0,V17=0,X17=0),"FALTAN DATOS",IF(AND(U17=1,W17=1,Y17=1),"BAJA",(IF(OR(AND(U17=5,W17=5),AND(U17=5,Y17=5),AND(U17=5,Y17=5),AND(U17=5,W17=5,Y17=5)),"ALTA","MEDIA")))) -> ALTA | AA17: No publicada o disponible | AB17: Base de datos | AC17: No aplica | AD17: =IF(AC17="Sí","Ley 1581 de 2012",IF(AC17="No","Ley 1755 de 2015","")) | AE17: =IF(AC17="Sí","Artículo 10 y 13",IF(AC17="No","Artículo 27","")) | AF17: Sin excepción | AG17: 46177 | AH17: 1 año | AZ17: Servicios | BA17: No aplica | BB17: No aplica | BC17: Asuntos Étnicos | BE17: Presentación | BG17: No clasificada | BH17: No clasificada | BI17: No clasificada | BK17: Archivo físico | BT17: Dato sensible | BX17: Cooperación Internacional | BZ17: Defensa de los Derechos de los Ciudadanos | CB17: Gestión de Movilidad y Seguridad Vial | CC17: Gestión para las Comunidades Étnicas | CD17: Gestión Presupuestal | CF17: Gestión de Inventarios de Bienes Muebles e Inmuebles | CL17: Gestión Educativa | CM17: Cooperación Internacional
A18: Desarrollo Social Integral y Ambiental del Territorio | B18: Gestión Turística | E18: Hardware | F18: Turismo | I18: Portal web | J18: 1 | K18: Vivejamundi.com, es la plataforma digital oficial que promociona la oferta turística del Municipio. (Directorio oficial de operadores turísticos de Jamundí) | L18: Secretario de Despacho | M18: 46178 | N18: Jefe de Oficina Comunicaciones | O18: N/A | P18: Digital | Q18: Digital | R18: Otro | T18: Información pública | U18: =IF(T18="No clasificada",5,IF(T18="Información pública clasificada",3,IF(T18="Información pública reservada",5,IF(T18="Información pública",1,)))) -> 1 | V18: Media | W18: =IF(V18="No clasificada",5,IF(V18="Baja",1,IF(V18="Media",3,IF(V18="Alta",5,)))) -> 3 | X18: Alta | Y18: =IF(X18="No clasificada",5,IF(X18="Baja",1,IF(X18="Media",3,IF(X18="Alta",5,)))) -> 5 | Z18: =IF(OR(T18=0,V18=0,X18=0),"FALTAN DATOS",IF(AND(U18=1,W18=1,Y18=1),"BAJA",(IF(OR(AND(U18=5,W18=5),AND(U18=5,Y18=5),AND(U18=5,Y18=5),AND(U18=5,W18=5,Y18=5)),"ALTA","MEDIA")))) -> MEDIA | AA18: Publicada | AB18: Portal web propios | AC18: No aplica | AD18: =IF(AC18="Sí","Ley 1581 de 2012",IF(AC18="No","Ley 1755 de 2015","")) | AE18: =IF(AC18="Sí","Artículo 10 y 13",IF(AC18="No","Artículo 27","")) | AF18: Sin excepción | AG18: 46177 | AH18: 1 año | AZ18: Intangibles | BC18: Cultura | BE18: Hoja de calculo | BK18: Archivo digital | BT18: Dato vulnerable | BX18: Gestión Presupuestal | CC18: Mantenimiento Espacios de Uso Público e Infraestructura Vial | CL18: Convivencia Ciudadana, Seguridad y Orden Público | CM18: Gestión Presupuestal
U19: =IF(T19="No clasificada",5,IF(T19="Información pública clasificada",3,IF(T19="Información pública reservada",5,IF(T19="Información pública",1,)))) -> 0 | W19: =IF(V19="No clasificada",5,IF(V19="Baja",1,IF(V19="Media",3,IF(V19="Alta",5,)))) -> 0 | Y19: =IF(X19="No clasificada",5,IF(X19="Baja",1,IF(X19="Media",3,IF(X19="Alta",5,)))) -> 0 | Z19: =IF(OR(T19=0,V19=0,X19=0),"FALTAN DATOS",IF(AND(U19=1,W19=1,Y19=1),"BAJA",(IF(OR(AND(U19=5,W19=5),AND(U19=5,Y19=5),AND(U19=5,Y19=5),AND(U19=5,W19=5,Y19=5)),"ALTA","MEDIA")))) -> FALTAN DATOS | AD19: =IF(AC19="Sí","Ley 1581 de 2012",IF(AC19="No","Ley 1755 de 2015","")) | AE19: =IF(AC19="Sí","Artículo 10 y 13",IF(AC19="No","Artículo 27","")) | AZ19: Componentes de red | BC19: Desarrollo Social | BE19: Imagen | BK19: Sistema de información | BT19: No aplica | CC19: Sostenibilidad Ambiental y Minera | CL19: Desarrollo Social Integral y Ambiental del Territorio | CM19: Comunicación Pública
U20: =IF(T20="No clasificada",5,IF(T20="Información pública clasificada",3,IF(T20="Información pública reservada",5,IF(T20="Información pública",1,)))) -> 0 | W20: =IF(V20="No clasificada",5,IF(V20="Baja",1,IF(V20="Media",3,IF(V20="Alta",5,)))) -> 0 | Y20: =IF(X20="No clasificada",5,IF(X20="Baja",1,IF(X20="Media",3,IF(X20="Alta",5,)))) -> 0 | Z20: =IF(OR(T20=0,V20=0,X20=0),"FALTAN DATOS",IF(AND(U20=1,W20=1,Y20=1),"BAJA",(IF(OR(AND(U20=5,W20=5),AND(U20=5,Y20=5),AND(U20=5,Y20=5),AND(U20=5,W20=5,Y20=5)),"ALTA","MEDIA")))) -> FALTAN DATOS | AD20: =IF(AC20="Sí","Ley 1581 de 2012",IF(AC20="No","Ley 1755 de 2015","")) | AE20: =IF(AC20="Sí","Artículo 10 y 13",IF(AC20="No","Artículo 27","")) | AZ20: Recurso humano | BC20: Educación | BE20: Video | BK20: Base de datos | CC20: Atención Social y Participación Ciudadana | CL20: Gestión Financiera | CM20: Tecnologías de la Información
U21: =IF(T21="No clasificada",5,IF(T21="Información pública clasificada",3,IF(T21="Información pública reservada",5,IF(T21="Información pública",1,)))) -> 0 | W21: =IF(V21="No clasificada",5,IF(V21="Baja",1,IF(V21="Media",3,IF(V21="Alta",5,)))) -> 0 | Y21: =IF(X21="No clasificada",5,IF(X21="Baja",1,IF(X21="Media",3,IF(X21="Alta",5,)))) -> 0 | Z21: =IF(OR(T21=0,V21=0,X21=0),"FALTAN DATOS",IF(AND(U21=1,W21=1,Y21=1),"BAJA",(IF(OR(AND(U21=5,W21=5),AND(U21=5,Y21=5),AND(U21=5,Y21=5),AND(U21=5,W21=5,Y21=5)),"ALTA","MEDIA")))) -> FALTAN DATOS | AD21: =IF(AC21="Sí","Ley 1581 de 2012",IF(AC21="No","Ley 1755 de 2015","")) | AE21: =IF(AC21="Sí","Artículo 10 y 13",IF(AC21="No","Artículo 27","")) | AZ21: No aplica | BC21: Gobierno | BE21: Base de datos | CC21: Desarrollo Agropecuario | CL21: Gestión Catastral | CM21: Aseguramiento en Salud
U22: =IF(T22="No clasificada",5,IF(T22="Información pública clasificada",3,IF(T22="Información pública reservada",5,IF(T22="Información pública",1,)))) -> 0 | W22: =IF(V22="No clasificada",5,IF(V22="Baja",1,IF(V22="Media",3,IF(V22="Alta",5,)))) -> 0 | Y22: =IF(X22="No clasificada",5,IF(X22="Baja",1,IF(X22="Media",3,IF(X22="Alta",5,)))) -> 0 | Z22: =IF(OR(T22=0,V22=0,X22=0),"FALTAN DATOS",IF(AND(U22=1,W22=1,Y22=1),"BAJA",(IF(OR(AND(U22=5,W22=5),AND(U22=5,Y22=5),AND(U22=5,Y22=5),AND(U22=5,W22=5,Y22=5)),"ALTA","MEDIA")))) -> FALTAN DATOS | AD22: =IF(AC22="Sí","Ley 1581 de 2012",IF(AC22="No","Ley 1755 de 2015","")) | AE22: =IF(AC22="Sí","Artículo 10 y 13",IF(AC22="No","Artículo 27","")) | BC22: Gestión Institucional | BE22: Otro | CC22: Gestión para el Posconflicto | CL22: Gestión Administrativa | CM22: Salud Pública
U23: =IF(T23="No clasificada",5,IF(T23="Información pública clasificada",3,IF(T23="Información pública reservada",5,IF(T23="Información pública",1,)))) -> 0 | W23: =IF(V23="No clasificada",5,IF(V23="Baja",1,IF(V23="Media",3,IF(V23="Alta",5,)))) -> 0 | Y23: =IF(X23="No clasificada",5,IF(X23="Baja",1,IF(X23="Media",3,IF(X23="Alta",5,)))) -> 0 | Z23: =IF(OR(T23=0,V23=0,X23=0),"FALTAN DATOS",IF(AND(U23=1,W23=1,Y23=1),"BAJA",(IF(OR(AND(U23=5,W23=5),AND(U23=5,Y23=5),AND(U23=5,Y23=5),AND(U23=5,W23=5,Y23=5)),"ALTA","MEDIA")))) -> FALTAN DATOS | AD23: =IF(AC23="Sí","Ley 1581 de 2012",IF(AC23="No","Ley 1755 de 2015","")) | AE23: =IF(AC23="Sí","Artículo 10 y 13",IF(AC23="No","Artículo 27","")) | BC23: Hacienda | BE23: No aplica | CL23: Gestión del Talento Humano | CM23: Salud Ambiental
U24: =IF(T24="No clasificada",5,IF(T24="Información pública clasificada",3,IF(T24="Información pública reservada",5,IF(T24="Información pública",1,)))) -> 0 | W24: =IF(V24="No clasificada",5,IF(V24="Baja",1,IF(V24="Media",3,IF(V24="Alta",5,)))) -> 0 | Y24: =IF(X24="No clasificada",5,IF(X24="Baja",1,IF(X24="Media",3,IF(X24="Alta",5,)))) -> 0 | Z24: =IF(OR(T24=0,V24=0,X24=0),"FALTAN DATOS",IF(AND(U24=1,W24=1,Y24=1),"BAJA",(IF(OR(AND(U24=5,W24=5),AND(U24=5,Y24=5),AND(U24=5,Y24=5),AND(U24=5,W24=5,Y24=5)),"ALTA","MEDIA")))) -> FALTAN DATOS | AD24: =IF(AC24="Sí","Ley 1581 de 2012",IF(AC24="No","Ley 1755 de 2015","")) | AE24: =IF(AC24="Sí","Artículo 10 y 13",IF(AC24="No","Artículo 27","")) | BC24: Infraestructura | CL24: Gestión Jurídica | CM24: Defensa de los Derechos de los Ciudadanos
U25: =IF(T25="No clasificada",5,IF(T25="Información pública clasificada",3,IF(T25="Información pública reservada",5,IF(T25="Información pública",1,)))) -> 0 | W25: =IF(V25="No clasificada",5,IF(V25="Baja",1,IF(V25="Media",3,IF(V25="Alta",5,)))) -> 0 | Y25: =IF(X25="No clasificada",5,IF(X25="Baja",1,IF(X25="Media",3,IF(X25="Alta",5,)))) -> 0 | Z25: =IF(OR(T25=0,V25=0,X25=0),"FALTAN DATOS",IF(AND(U25=1,W25=1,Y25=1),"BAJA",(IF(OR(AND(U25=5,W25=5),AND(U25=5,Y25=5),AND(U25=5,Y25=5),AND(U25=5,W25=5,Y25=5)),"ALTA","MEDIA")))) -> FALTAN DATOS | AD25: =IF(AC25="Sí","Ley 1581 de 2012",IF(AC25="No","Ley 1755 de 2015","")) | AE25: =IF(AC25="Sí","Artículo 10 y 13",IF(AC25="No","Artículo 27","")) | BC25: Planeación | CL25: Gestión Estadística | CM25: Calidad Educativa
U26: =IF(T26="No clasificada",5,IF(T26="Información pública clasificada",3,IF(T26="Información pública reservada",5,IF(T26="Información pública",1,)))) -> 0 | W26: =IF(V26="No clasificada",5,IF(V26="Baja",1,IF(V26="Media",3,IF(V26="Alta",5,)))) -> 0 | Y26: =IF(X26="No clasificada",5,IF(X26="Baja",1,IF(X26="Media",3,IF(X26="Alta",5,)))) -> 0 | Z26: =IF(OR(T26=0,V26=0,X26=0),"FALTAN DATOS",IF(AND(U26=1,W26=1,Y26=1),"BAJA",(IF(OR(AND(U26=5,W26=5),AND(U26=5,Y26=5),AND(U26=5,Y26=5),AND(U26=5,W26=5,Y26=5)),"ALTA","MEDIA")))) -> FALTAN DATOS | AD26: =IF(AC26="Sí","Ley 1581 de 2012",IF(AC26="No","Ley 1755 de 2015","")) | AE26: =IF(AC26="Sí","Artículo 10 y 13",IF(AC26="No","Artículo 27","")) | BC26: Salud | CL26: Control Interno | CM26: Cobertura Educativa
U27: =IF(T27="No clasificada",5,IF(T27="Información pública clasificada",3,IF(T27="Información pública reservada",5,IF(T27="Información pública",1,)))) -> 0 | W27: =IF(V27="No clasificada",5,IF(V27="Baja",1,IF(V27="Media",3,IF(V27="Alta",5,)))) -> 0 | Y27: =IF(X27="No clasificada",5,IF(X27="Baja",1,IF(X27="Media",3,IF(X27="Alta",5,)))) -> 0 | Z27: =IF(OR(T27=0,V27=0,X27=0),"FALTAN DATOS",IF(AND(U27=1,W27=1,Y27=1),"BAJA",(IF(OR(AND(U27=5,W27=5),AND(U27=5,Y27=5),AND(U27=5,Y27=5),AND(U27=5,W27=5,Y27=5)),"ALTA","MEDIA")))) -> FALTAN DATOS | AD27: =IF(AC27="Sí","Ley 1581 de 2012",IF(AC27="No","Ley 1755 de 2015","")) | AE27: =IF(AC27="Sí","Artículo 10 y 13",IF(AC27="No","Artículo 27","")) | BC27: Turismo | CM27: Inspección y Vigilancia Educativa
U28: =IF(T28="No clasificada",5,IF(T28="Información pública clasificada",3,IF(T28="Información pública reservada",5,IF(T28="Información pública",1,)))) -> 0 | W28: =IF(V28="No clasificada",5,IF(V28="Baja",1,IF(V28="Media",3,IF(V28="Alta",5,)))) -> 0 | Y28: =IF(X28="No clasificada",5,IF(X28="Baja",1,IF(X28="Media",3,IF(X28="Alta",5,)))) -> 0 | Z28: =IF(OR(T28=0,V28=0,X28=0),"FALTAN DATOS",IF(AND(U28=1,W28=1,Y28=1),"BAJA",(IF(OR(AND(U28=5,W28=5),AND(U28=5,Y28=5),AND(U28=5,Y28=5),AND(U28=5,W28=5,Y28=5)),"ALTA","MEDIA")))) -> FALTAN DATOS | AD28: =IF(AC28="Sí","Ley 1581 de 2012",IF(AC28="No","Ley 1755 de 2015","")) | AE28: =IF(AC28="Sí","Artículo 10 y 13",IF(AC28="No","Artículo 27","")) | BC28: Vivienda | CM28: Convivencia y Cultura Ciudadana (Inspección de policía - comisaría de familia, metrología)
U29: =IF(T29="No clasificada",5,IF(T29="Información pública clasificada",3,IF(T29="Información pública reservada",5,IF(T29="Información pública",1,)))) -> 0 | W29: =IF(V29="No clasificada",5,IF(V29="Baja",1,IF(V29="Media",3,IF(V29="Alta",5,)))) -> 0 | Y29: =IF(X29="No clasificada",5,IF(X29="Baja",1,IF(X29="Media",3,IF(X29="Alta",5,)))) -> 0 | Z29: =IF(OR(T29=0,V29=0,X29=0),"FALTAN DATOS",IF(AND(U29=1,W29=1,Y29=1),"BAJA",(IF(OR(AND(U29=5,W29=5),AND(U29=5,Y29=5),AND(U29=5,Y29=5),AND(U29=5,W29=5,Y29=5)),"ALTA","MEDIA")))) -> FALTAN DATOS | AD29: =IF(AC29="Sí","Ley 1581 de 2012",IF(AC29="No","Ley 1755 de 2015","")) | AE29: =IF(AC29="Sí","Artículo 10 y 13",IF(AC29="No","Artículo 27","")) | BC29: General | CM29: Gestión de Riesgo de Desastres
U30: =IF(T30="No clasificada",5,IF(T30="Información pública clasificada",3,IF(T30="Información pública reservada",5,IF(T30="Información pública",1,)))) -> 0 | W30: =IF(V30="No clasificada",5,IF(V30="Baja",1,IF(V30="Media",3,IF(V30="Alta",5,)))) -> 0 | Y30: =IF(X30="No clasificada",5,IF(X30="Baja",1,IF(X30="Media",3,IF(X30="Alta",5,)))) -> 0 | Z30: =IF(OR(T30=0,V30=0,X30=0),"FALTAN DATOS",IF(AND(U30=1,W30=1,Y30=1),"BAJA",(IF(OR(AND(U30=5,W30=5),AND(U30=5,Y30=5),AND(U30=5,Y30=5),AND(U30=5,W30=5,Y30=5)),"ALTA","MEDIA")))) -> FALTAN DATOS | AD30: =IF(AC30="Sí","Ley 1581 de 2012",IF(AC30="No","Ley 1755 de 2015","")) | AE30: =IF(AC30="Sí","Artículo 10 y 13",IF(AC30="No","Artículo 27","")) | BC30: Jurídica | CM30: Víctimas
U31: =IF(T31="No clasificada",5,IF(T31="Información pública clasificada",3,IF(T31="Información pública reservada",5,IF(T31="Información pública",1,)))) -> 0 | W31: =IF(V31="No clasificada",5,IF(V31="Baja",1,IF(V31="Media",3,IF(V31="Alta",5,)))) -> 0 | Y31: =IF(X31="No clasificada",5,IF(X31="Baja",1,IF(X31="Media",3,IF(X31="Alta",5,)))) -> 0 | Z31: =IF(OR(T31=0,V31=0,X31=0),"FALTAN DATOS",IF(AND(U31=1,W31=1,Y31=1),"BAJA",(IF(OR(AND(U31=5,W31=5),AND(U31=5,Y31=5),AND(U31=5,Y31=5),AND(U31=5,W31=5,Y31=5)),"ALTA","MEDIA")))) -> FALTAN DATOS | AD31: =IF(AC31="Sí","Ley 1581 de 2012",IF(AC31="No","Ley 1755 de 2015","")) | AE31: =IF(AC31="Sí","Artículo 10 y 13",IF(AC31="No","Artículo 27","")) | BC31: Seguridad y Convivencia | CM31: Gestión de Movilidad y Seguridad Vial
U32: =IF(T32="No clasificada",5,IF(T32="Información pública clasificada",3,IF(T32="Información pública reservada",5,IF(T32="Información pública",1,)))) -> 0 | W32: =IF(V32="No clasificada",5,IF(V32="Baja",1,IF(V32="Media",3,IF(V32="Alta",5,)))) -> 0 | Y32: =IF(X32="No clasificada",5,IF(X32="Baja",1,IF(X32="Media",3,IF(X32="Alta",5,)))) -> 0 | Z32: =IF(OR(T32=0,V32=0,X32=0),"FALTAN DATOS",IF(AND(U32=1,W32=1,Y32=1),"BAJA",(IF(OR(AND(U32=5,W32=5),AND(U32=5,Y32=5),AND(U32=5,Y32=5),AND(U32=5,W32=5,Y32=5)),"ALTA","MEDIA")))) -> FALTAN DATOS | AD32: =IF(AC32="Sí","Ley 1581 de 2012",IF(AC32="No","Ley 1755 de 2015","")) | AE32: =IF(AC32="Sí","Artículo 10 y 13",IF(AC32="No","Artículo 27","")) | BC32: Comunicaciones | CM32: Gestión de Vivienda y Saneamiento Básico
U33: =IF(T33="No clasificada",5,IF(T33="Información pública clasificada",3,IF(T33="Información pública reservada",5,IF(T33="Información pública",1,)))) -> 0 | W33: =IF(V33="No clasificada",5,IF(V33="Baja",1,IF(V33="Media",3,IF(V33="Alta",5,)))) -> 0 | Y33: =IF(X33="No clasificada",5,IF(X33="Baja",1,IF(X33="Media",3,IF(X33="Alta",5,)))) -> 0 | Z33: =IF(OR(T33=0,V33=0,X33=0),"FALTAN DATOS",IF(AND(U33=1,W33=1,Y33=1),"BAJA",(IF(OR(AND(U33=5,W33=5),AND(U33=5,Y33=5),AND(U33=5,Y33=5),AND(U33=5,W33=5,Y33=5)),"ALTA","MEDIA")))) -> FALTAN DATOS | AD33: =IF(AC33="Sí","Ley 1581 de 2012",IF(AC33="No","Ley 1755 de 2015","")) | AE33: =IF(AC33="Sí","Artículo 10 y 13",IF(AC33="No","Artículo 27","")) | BC33: Control I​nterno | CM33: Gestión Cultural
U34: =IF(T34="No clasificada",5,IF(T34="Información pública clasificada",3,IF(T34="Información pública reservada",5,IF(T34="Información pública",1,)))) -> 0 | W34: =IF(V34="No clasificada",5,IF(V34="Baja",1,IF(V34="Media",3,IF(V34="Alta",5,)))) -> 0 | Y34: =IF(X34="No clasificada",5,IF(X34="Baja",1,IF(X34="Media",3,IF(X34="Alta",5,)))) -> 0 | Z34: =IF(OR(T34=0,V34=0,X34=0),"FALTAN DATOS",IF(AND(U34=1,W34=1,Y34=1),"BAJA",(IF(OR(AND(U34=5,W34=5),AND(U34=5,Y34=5),AND(U34=5,Y34=5),AND(U34=5,W34=5,Y34=5)),"ALTA","MEDIA")))) -> FALTAN DATOS | AD34: =IF(AC34="Sí","Ley 1581 de 2012",IF(AC34="No","Ley 1755 de 2015","")) | AE34: =IF(AC34="Sí","Artículo 10 y 13",IF(AC34="No","Artículo 27","")) | BC34: Control Interno y Disciplinario​ | CM34: Gestión Turística
U35: =IF(T35="No clasificada",5,IF(T35="Información pública clasificada",3,IF(T35="Información pública reservada",5,IF(T35="Información pública",1,)))) -> 0 | W35: =IF(V35="No clasificada",5,IF(V35="Baja",1,IF(V35="Media",3,IF(V35="Alta",5,)))) -> 0 | Y35: =IF(X35="No clasificada",5,IF(X35="Baja",1,IF(X35="Media",3,IF(X35="Alta",5,)))) -> 0 | Z35: =IF(OR(T35=0,V35=0,X35=0),"FALTAN DATOS",IF(AND(U35=1,W35=1,Y35=1),"BAJA",(IF(OR(AND(U35=5,W35=5),AND(U35=5,Y35=5),AND(U35=5,Y35=5),AND(U35=5,W35=5,Y35=5)),"ALTA","MEDIA")))) -> FALTAN DATOS | AD35: =IF(AC35="Sí","Ley 1581 de 2012",IF(AC35="No","Ley 1755 de 2015","")) | AE35: =IF(AC35="Sí","Artículo 10 y 13",IF(AC35="No","Artículo 27","")) | BC35: Cooperación Internacion​al​ | CM35: Gestión para las Comunidades Étnicas
U36: =IF(T36="No clasificada",5,IF(T36="Información pública clasificada",3,IF(T36="Información pública reservada",5,IF(T36="Información pública",1,)))) -> 0 | W36: =IF(V36="No clasificada",5,IF(V36="Baja",1,IF(V36="Media",3,IF(V36="Alta",5,)))) -> 0 | Y36: =IF(X36="No clasificada",5,IF(X36="Baja",1,IF(X36="Media",3,IF(X36="Alta",5,)))) -> 0 | Z36: =IF(OR(T36=0,V36=0,X36=0),"FALTAN DATOS",IF(AND(U36=1,W36=1,Y36=1),"BAJA",(IF(OR(AND(U36=5,W36=5),AND(U36=5,Y36=5),AND(U36=5,Y36=5),AND(U36=5,W36=5,Y36=5)),"ALTA","MEDIA")))) -> FALTAN DATOS | AD36: =IF(AC36="Sí","Ley 1581 de 2012",IF(AC36="No","Ley 1755 de 2015","")) | AE36: =IF(AC36="Sí","Artículo 10 y 13",IF(AC36="No","Artículo 27","")) | BC36: Tecnologías de la Información y las Comunicaciones​ | CM36: Mantenimiento Espacios de Uso Público e Infraestructura Vial
U37: =IF(T37="No clasificada",5,IF(T37="Información pública clasificada",3,IF(T37="Información pública reservada",5,IF(T37="Información pública",1,)))) -> 0 | W37: =IF(V37="No clasificada",5,IF(V37="Baja",1,IF(V37="Media",3,IF(V37="Alta",5,)))) -> 0 | Y37: =IF(X37="No clasificada",5,IF(X37="Baja",1,IF(X37="Media",3,IF(X37="Alta",5,)))) -> 0 | Z37: =IF(OR(T37=0,V37=0,X37=0),"FALTAN DATOS",IF(AND(U37=1,W37=1,Y37=1),"BAJA",(IF(OR(AND(U37=5,W37=5),AND(U37=5,Y37=5),AND(U37=5,Y37=5),AND(U37=5,W37=5,Y37=5)),"ALTA","MEDIA")))) -> FALTAN DATOS | AD37: =IF(AC37="Sí","Ley 1581 de 2012",IF(AC37="No","Ley 1755 de 2015","")) | AE37: =IF(AC37="Sí","Artículo 10 y 13",IF(AC37="No","Artículo 27","")) | BC37: Progr​amas Especiales​ | CM37: Sostenibilidad Ambiental y Minera
U38: =IF(T38="No clasificada",5,IF(T38="Información pública clasificada",3,IF(T38="Información pública reservada",5,IF(T38="Información pública",1,)))) -> 0 | W38: =IF(V38="No clasificada",5,IF(V38="Baja",1,IF(V38="Media",3,IF(V38="Alta",5,)))) -> 0 | Y38: =IF(X38="No clasificada",5,IF(X38="Baja",1,IF(X38="Media",3,IF(X38="Alta",5,)))) -> 0 | Z38: =IF(OR(T38=0,V38=0,X38=0),"FALTAN DATOS",IF(AND(U38=1,W38=1,Y38=1),"BAJA",(IF(OR(AND(U38=5,W38=5),AND(U38=5,Y38=5),AND(U38=5,Y38=5),AND(U38=5,W38=5,Y38=5)),"ALTA","MEDIA")))) -> FALTAN DATOS | AD38: =IF(AC38="Sí","Ley 1581 de 2012",IF(AC38="No","Ley 1755 de 2015","")) | AE38: =IF(AC38="Sí","Artículo 10 y 13",IF(AC38="No","Artículo 27","")) | BC38: Posconflicto​ | CM38: Atención Social y Participación Ciudadana
... U42: =IF(T42="No clasificada",5,IF(T42="Información pública clasificada",3,IF(T42="Información pública reservada",5,IF(T42="Información pública",1,)))) -> 0 | W42: =IF(V42="No clasificada",5,IF(V42="Baja",1,IF(V42="Media",3,IF(V42="Alta",5,)))) -> 0 | Y42: =IF(X42="No clasificada",5,IF(X42="Baja",1,IF(X42="Media",3,IF(X42="Alta",5,)))) -> 0 | Z42: =IF(OR(T42=0,V42=0,X42=0),"FALTAN DATOS",IF(AND(U42=1,W42=1,Y42=1),"BAJA",(IF(OR(AND(U42=5,W42=5),AND(U42=5,Y42=5),AND(U42=5,Y42=5),AND(U42=5,W42=5,Y42=5)),"ALTA","MEDIA")))) -> FALTAN DATOS | AD42: =IF(AC42="Sí","Ley 1581 de 2012",IF(AC42="No","Ley 1755 de 2015","")) | AE42: =IF(AC42="Sí","Artículo 10 y 13",IF(AC42="No","Artículo 27","")) | BC42: Gestión Catastral | CM42: Fiscalización
U43: =IF(T43="No clasificada",5,IF(T43="Información pública clasificada",3,IF(T43="Información pública reservada",5,IF(T43="Información pública",1,)))) -> 0 | W43: =IF(V43="No clasificada",5,IF(V43="Baja",1,IF(V43="Media",3,IF(V43="Alta",5,)))) -> 0 | Y43: =IF(X43="No clasificada",5,IF(X43="Baja",1,IF(X43="Media",3,IF(X43="Alta",5,)))) -> 0 | Z43: =IF(OR(T43=0,V43=0,X43=0),"FALTAN DATOS",IF(AND(U43=1,W43=1,Y43=1),"BAJA",(IF(OR(AND(U43=5,W43=5),AND(U43=5,Y43=5),AND(U43=5,Y43=5),AND(U43=5,W43=5,Y43=5)),"ALTA","MEDIA")))) -> FALTAN DATOS | AD43: =IF(AC43="Sí","Ley 1581 de 2012",IF(AC43="No","Ley 1755 de 2015","")) | AE43: =IF(AC43="Sí","Artículo 10 y 13",IF(AC43="No","Artículo 27","")) | CM43: Contabilidad General
U44: =IF(T44="No clasificada",5,IF(T44="Información pública clasificada",3,IF(T44="Información pública reservada",5,IF(T44="Información pública",1,)))) -> 0 | W44: =IF(V44="No clasificada",5,IF(V44="Baja",1,IF(V44="Media",3,IF(V44="Alta",5,)))) -> 0 | Y44: =IF(X44="No clasificada",5,IF(X44="Baja",1,IF(X44="Media",3,IF(X44="Alta",5,)))) -> 0 | Z44: =IF(OR(T44=0,V44=0,X44=0),"FALTAN DATOS",IF(AND(U44=1,W44=1,Y44=1),"BAJA",(IF(OR(AND(U44=5,W44=5),AND(U44=5,Y44=5),AND(U44=5,Y44=5),AND(U44=5,W44=5,Y44=5)),"ALTA","MEDIA")))) -> FALTAN DATOS | AD44: =IF(AC44="Sí","Ley 1581 de 2012",IF(AC44="No","Ley 1755 de 2015","")) | AE44: =IF(AC44="Sí","Artículo 10 y 13",IF(AC44="No","Artículo 27","")) | CM44: Gestión Presupuestal
U45: =IF(T45="No clasificada",5,IF(T45="Información pública clasificada",3,IF(T45="Información pública reservada",5,IF(T45="Información pública",1,)))) -> 0 | W45: =IF(V45="No clasificada",5,IF(V45="Baja",1,IF(V45="Media",3,IF(V45="Alta",5,)))) -> 0 | Y45: =IF(X45="No clasificada",5,IF(X45="Baja",1,IF(X45="Media",3,IF(X45="Alta",5,)))) -> 0 | Z45: =IF(OR(T45=0,V45=0,X45=0),"FALTAN DATOS",IF(AND(U45=1,W45=1,Y45=1),"BAJA",(IF(OR(AND(U45=5,W45=5),AND(U45=5,Y45=5),AND(U45=5,Y45=5),AND(U45=5,W45=5,Y45=5)),"ALTA","MEDIA")))) -> FALTAN DATOS | AD45: =IF(AC45="Sí","Ley 1581 de 2012",IF(AC45="No","Ley 1755 de 2015","")) | AE45: =IF(AC45="Sí","Artículo 10 y 13",IF(AC45="No","Artículo 27","")) | CM45: Actualización Catastral
U46: =IF(T46="No clasificada",5,IF(T46="Información pública clasificada",3,IF(T46="Información pública reservada",5,IF(T46="Información pública",1,)))) -> 0 | W46: =IF(V46="No clasificada",5,IF(V46="Baja",1,IF(V46="Media",3,IF(V46="Alta",5,)))) -> 0 | Y46: =IF(X46="No clasificada",5,IF(X46="Baja",1,IF(X46="Media",3,IF(X46="Alta",5,)))) -> 0 | Z46: =IF(OR(T46=0,V46=0,X46=0),"FALTAN DATOS",IF(AND(U46=1,W46=1,Y46=1),"BAJA",(IF(OR(AND(U46=5,W46=5),AND(U46=5,Y46=5),AND(U46=5,Y46=5),AND(U46=5,W46=5,Y46=5)),"ALTA","MEDIA")))) -> FALTAN DATOS | AD46: =IF(AC46="Sí","Ley 1581 de 2012",IF(AC46="No","Ley 1755 de 2015","")) | AE46: =IF(AC46="Sí","Artículo 10 y 13",IF(AC46="No","Artículo 27","")) | CM46: Conservación Catastral
U47: =IF(T47="No clasificada",5,IF(T47="Información pública clasificada",3,IF(T47="Información pública reservada",5,IF(T47="Información pública",1,)))) -> 0 | W47: =IF(V47="No clasificada",5,IF(V47="Baja",1,IF(V47="Media",3,IF(V47="Alta",5,)))) -> 0 | Y47: =IF(X47="No clasificada",5,IF(X47="Baja",1,IF(X47="Media",3,IF(X47="Alta",5,)))) -> 0 | Z47: =IF(OR(T47=0,V47=0,X47=0),"FALTAN DATOS",IF(AND(U47=1,W47=1,Y47=1),"BAJA",(IF(OR(AND(U47=5,W47=5),AND(U47=5,Y47=5),AND(U47=5,Y47=5),AND(U47=5,W47=5,Y47=5)),"ALTA","MEDIA")))) -> FALTAN DATOS | AD47: =IF(AC47="Sí","Ley 1581 de 2012",IF(AC47="No","Ley 1755 de 2015","")) | AE47: =IF(AC47="Sí","Artículo 10 y 13",IF(AC47="No","Artículo 27","")) | CM47: Atención al Ciudadano
U48: =IF(T48="No clasificada",5,IF(T48="Información pública clasificada",3,IF(T48="Información pública reservada",5,IF(T48="Información pública",1,)))) -> 0 | W48: =IF(V48="No clasificada",5,IF(V48="Baja",1,IF(V48="Media",3,IF(V48="Alta",5,)))) -> 0 | Y48: =IF(X48="No clasificada",5,IF(X48="Baja",1,IF(X48="Media",3,IF(X48="Alta",5,)))) -> 0 | Z48: =IF(OR(T48=0,V48=0,X48=0),"FALTAN DATOS",IF(AND(U48=1,W48=1,Y48=1),"BAJA",(IF(OR(AND(U48=5,W48=5),AND(U48=5,Y48=5),AND(U48=5,Y48=5),AND(U48=5,W48=5,Y48=5)),"ALTA","MEDIA")))) -> FALTAN DATOS | AD48: =IF(AC48="Sí","Ley 1581 de 2012",IF(AC48="No","Ley 1755 de 2015","")) | AE48: =IF(AC48="Sí","Artículo 10 y 13",IF(AC48="No","Artículo 27","")) | CM48: Gestión Documental (Archivo - Ventanilla Única)
U49: =IF(T49="No clasificada",5,IF(T49="Información pública clasificada",3,IF(T49="Información pública reservada",5,IF(T49="Información pública",1,)))) -> 0 | W49: =IF(V49="No clasificada",5,IF(V49="Baja",1,IF(V49="Media",3,IF(V49="Alta",5,)))) -> 0 | Y49: =IF(X49="No clasificada",5,IF(X49="Baja",1,IF(X49="Media",3,IF(X49="Alta",5,)))) -> 0 | Z49: =IF(OR(T49=0,V49=0,X49=0),"FALTAN DATOS",IF(AND(U49=1,W49=1,Y49=1),"BAJA",(IF(OR(AND(U49=5,W49=5),AND(U49=5,Y49=5),AND(U49=5,Y49=5),AND(U49=5,W49=5,Y49=5)),"ALTA","MEDIA")))) -> FALTAN DATOS | AD49: =IF(AC49="Sí","Ley 1581 de 2012",IF(AC49="No","Ley 1755 de 2015","")) | AE49: =IF(AC49="Sí","Artículo 10 y 13",IF(AC49="No","Artículo 27","")) | CM49: Administración Plaza de Mercado
U50: =IF(T50="No clasificada",5,IF(T50="Información pública clasificada",3,IF(T50="Información pública reservada",5,IF(T50="Información pública",1,)))) -> 0 | W50: =IF(V50="No clasificada",5,IF(V50="Baja",1,IF(V50="Media",3,IF(V50="Alta",5,)))) -> 0 | Y50: =IF(X50="No clasificada",5,IF(X50="Baja",1,IF(X50="Media",3,IF(X50="Alta",5,)))) -> 0 | Z50: =IF(OR(T50=0,V50=0,X50=0),"FALTAN DATOS",IF(AND(U50=1,W50=1,Y50=1),"BAJA",(IF(OR(AND(U50=5,W50=5),AND(U50=5,Y50=5),AND(U50=5,Y50=5),AND(U50=5,W50=5,Y50=5)),"ALTA","MEDIA")))) -> FALTAN DATOS | AD50: =IF(AC50="Sí","Ley 1581 de 2012",IF(AC50="No","Ley 1755 de 2015","")) | AE50: =IF(AC50="Sí","Artículo 10 y 13",IF(AC50="No","Artículo 27","")) | CM50: Gestión de Inventarios de Bienes Muebles e Inmuebles
U51: =IF(T51="No clasificada",5,IF(T51="Información pública clasificada",3,IF(T51="Información pública reservada",5,IF(T51="Información pública",1,)))) -> 0 | W51: =IF(V51="No clasificada",5,IF(V51="Baja",1,IF(V51="Media",3,IF(V51="Alta",5,)))) -> 0 | Y51: =IF(X51="No clasificada",5,IF(X51="Baja",1,IF(X51="Media",3,IF(X51="Alta",5,)))) -> 0 | Z51: =IF(OR(T51=0,V51=0,X51=0),"FALTAN DATOS",IF(AND(U51=1,W51=1,Y51=1),"BAJA",(IF(OR(AND(U51=5,W51=5),AND(U51=5,Y51=5),AND(U51=5,Y51=5),AND(U51=5,W51=5,Y51=5)),"ALTA","MEDIA")))) -> FALTAN DATOS | AD51: =IF(AC51="Sí","Ley 1581 de 2012",IF(AC51="No","Ley 1755 de 2015","")) | AE51: =IF(AC51="Sí","Artículo 10 y 13",IF(AC51="No","Artículo 27","")) | CM51: Administración del Talento Humano
U52: =IF(T52="No clasificada",5,IF(T52="Información pública clasificada",3,IF(T52="Información pública reservada",5,IF(T52="Información pública",1,)))) -> 0 | W52: =IF(V52="No clasificada",5,IF(V52="Baja",1,IF(V52="Media",3,IF(V52="Alta",5,)))) -> 0 | Y52: =IF(X52="No clasificada",5,IF(X52="Baja",1,IF(X52="Media",3,IF(X52="Alta",5,)))) -> 0 | Z52: =IF(OR(T52=0,V52=0,X52=0),"FALTAN DATOS",IF(AND(U52=1,W52=1,Y52=1),"BAJA",(IF(OR(AND(U52=5,W52=5),AND(U52=5,Y52=5),AND(U52=5,Y52=5),AND(U52=5,W52=5,Y52=5)),"ALTA","MEDIA")))) -> FALTAN DATOS | AD52: =IF(AC52="Sí","Ley 1581 de 2012",IF(AC52="No","Ley 1755 de 2015","")) | AE52: =IF(AC52="Sí","Artículo 10 y 13",IF(AC52="No","Artículo 27","")) | CM52: Seguridad y Salud en el Trabajo
U53: =IF(T53="No clasificada",5,IF(T53="Información pública clasificada",3,IF(T53="Información pública reservada",5,IF(T53="Información pública",1,)))) -> 0 | W53: =IF(V53="No clasificada",5,IF(V53="Baja",1,IF(V53="Media",3,IF(V53="Alta",5,)))) -> 0 | Y53: =IF(X53="No clasificada",5,IF(X53="Baja",1,IF(X53="Media",3,IF(X53="Alta",5,)))) -> 0 | Z53: =IF(OR(T53=0,V53=0,X53=0),"FALTAN DATOS",IF(AND(U53=1,W53=1,Y53=1),"BAJA",(IF(OR(AND(U53=5,W53=5),AND(U53=5,Y53=5),AND(U53=5,Y53=5),AND(U53=5,W53=5,Y53=5)),"ALTA","MEDIA")))) -> FALTAN DATOS | AD53: =IF(AC53="Sí","Ley 1581 de 2012",IF(AC53="No","Ley 1755 de 2015","")) | AE53: =IF(AC53="Sí","Artículo 10 y 13",IF(AC53="No","Artículo 27","")) | CM53: Control Disciplinario
U54: =IF(T54="No clasificada",5,IF(T54="Información pública clasificada",3,IF(T54="Información pública reservada",5,IF(T54="Información pública",1,)))) -> 0 | W54: =IF(V54="No clasificada",5,IF(V54="Baja",1,IF(V54="Media",3,IF(V54="Alta",5,)))) -> 0 | Y54: =IF(X54="No clasificada",5,IF(X54="Baja",1,IF(X54="Media",3,IF(X54="Alta",5,)))) -> 0 | Z54: =IF(OR(T54=0,V54=0,X54=0),"FALTAN DATOS",IF(AND(U54=1,W54=1,Y54=1),"BAJA",(IF(OR(AND(U54=5,W54=5),AND(U54=5,Y54=5),AND(U54=5,Y54=5),AND(U54=5,W54=5,Y54=5)),"ALTA","MEDIA")))) -> FALTAN DATOS | AD54: =IF(AC54="Sí","Ley 1581 de 2012",IF(AC54="No","Ley 1755 de 2015","")) | AE54: =IF(AC54="Sí","Artículo 10 y 13",IF(AC54="No","Artículo 27","")) | CM54: Gestión Contractual
... U59: =IF(T59="No clasificada",5,IF(T59="Información pública clasificada",3,IF(T59="Información pública reservada",5,IF(T59="Información pública",1,)))) -> 0 | W59: =IF(V59="No clasificada",5,IF(V59="Baja",1,IF(V59="Media",3,IF(V59="Alta",5,)))) -> 0 | Y59: =IF(X59="No clasificada",5,IF(X59="Baja",1,IF(X59="Media",3,IF(X59="Alta",5,)))) -> 0 | Z59: =IF(OR(T59=0,V59=0,X59=0),"FALTAN DATOS",IF(AND(U59=1,W59=1,Y59=1),"BAJA",(IF(OR(AND(U59=5,W59=5),AND(U59=5,Y59=5),AND(U59=5,Y59=5),AND(U59=5,W59=5,Y59=5)),"ALTA","MEDIA")))) -> FALTAN DATOS | AD59: =IF(AC59="Sí","Ley 1581 de 2012",IF(AC59="No","Ley 1755 de 2015","")) | AE59: =IF(AC59="Sí","Artículo 10 y 13",IF(AC59="No","Artículo 27","")) | CM59: Evaluación a la Gestión
U60: =IF(T60="No clasificada",5,IF(T60="Información pública clasificada",3,IF(T60="Información pública reservada",5,IF(T60="Información pública",1,)))) -> 0 | W60: =IF(V60="No clasificada",5,IF(V60="Baja",1,IF(V60="Media",3,IF(V60="Alta",5,)))) -> 0 | Y60: =IF(X60="No clasificada",5,IF(X60="Baja",1,IF(X60="Media",3,IF(X60="Alta",5,)))) -> 0 | Z60: =IF(OR(T60=0,V60=0,X60=0),"FALTAN DATOS",IF(AND(U60=1,W60=1,Y60=1),"BAJA",(IF(OR(AND(U60=5,W60=5),AND(U60=5,Y60=5),AND(U60=5,Y60=5),AND(U60=5,W60=5,Y60=5)),"ALTA","MEDIA")))) -> FALTAN DATOS | AD60: =IF(AC60="Sí","Ley 1581 de 2012",IF(AC60="No","Ley 1755 de 2015","")) | AE60: =IF(AC60="Sí","Artículo 10 y 13",IF(AC60="No","Artículo 27",""))
U61: =IF(T61="No clasificada",5,IF(T61="Información pública clasificada",3,IF(T61="Información pública reservada",5,IF(T61="Información pública",1,)))) -> 0 | W61: =IF(V61="No clasificada",5,IF(V61="Baja",1,IF(V61="Media",3,IF(V61="Alta",5,)))) -> 0 | Y61: =IF(X61="No clasificada",5,IF(X61="Baja",1,IF(X61="Media",3,IF(X61="Alta",5,)))) -> 0 | Z61: =IF(OR(T61=0,V61=0,X61=0),"FALTAN DATOS",IF(AND(U61=1,W61=1,Y61=1),"BAJA",(IF(OR(AND(U61=5,W61=5),AND(U61=5,Y61=5),AND(U61=5,Y61=5),AND(U61=5,W61=5,Y61=5)),"ALTA","MEDIA")))) -> FALTAN DATOS | AD61: =IF(AC61="Sí","Ley 1581 de 2012",IF(AC61="No","Ley 1755 de 2015","")) | AE61: =IF(AC61="Sí","Artículo 10 y 13",IF(AC61="No","Artículo 27",""))
U62: =IF(T62="No clasificada",5,IF(T62="Información pública clasificada",3,IF(T62="Información pública reservada",5,IF(T62="Información pública",1,)))) -> 0 | W62: =IF(V62="No clasificada",5,IF(V62="Baja",1,IF(V62="Media",3,IF(V62="Alta",5,)))) -> 0 | Y62: =IF(X62="No clasificada",5,IF(X62="Baja",1,IF(X62="Media",3,IF(X62="Alta",5,)))) -> 0 | Z62: =IF(OR(T62=0,V62=0,X62=0),"FALTAN DATOS",IF(AND(U62=1,W62=1,Y62=1),"BAJA",(IF(OR(AND(U62=5,W62=5),AND(U62=5,Y62=5),AND(U62=5,Y62=5),AND(U62=5,W62=5,Y62=5)),"ALTA","MEDIA")))) -> FALTAN DATOS | AD62: =IF(AC62="Sí","Ley 1581 de 2012",IF(AC62="No","Ley 1755 de 2015","")) | AE62: =IF(AC62="Sí","Artículo 10 y 13",IF(AC62="No","Artículo 27",""))
U63: =IF(T63="No clasificada",5,IF(T63="Información pública clasificada",3,IF(T63="Información pública reservada",5,IF(T63="Información pública",1,)))) -> 0 | W63: =IF(V63="No clasificada",5,IF(V63="Baja",1,IF(V63="Media",3,IF(V63="Alta",5,)))) -> 0 | Y63: =IF(X63="No clasificada",5,IF(X63="Baja",1,IF(X63="Media",3,IF(X63="Alta",5,)))) -> 0 | Z63: =IF(OR(T63=0,V63=0,X63=0),"FALTAN DATOS",IF(AND(U63=1,W63=1,Y63=1),"BAJA",(IF(OR(AND(U63=5,W63=5),AND(U63=5,Y63=5),AND(U63=5,Y63=5),AND(U63=5,W63=5,Y63=5)),"ALTA","MEDIA")))) -> FALTAN DATOS | AD63: =IF(AC63="Sí","Ley 1581 de 2012",IF(AC63="No","Ley 1755 de 2015","")) | AE63: =IF(AC63="Sí","Artículo 10 y 13",IF(AC63="No","Artículo 27",""))
U64: =IF(T64="No clasificada",5,IF(T64="Información pública clasificada",3,IF(T64="Información pública reservada",5,IF(T64="Información pública",1,)))) -> 0 | W64: =IF(V64="No clasificada",5,IF(V64="Baja",1,IF(V64="Media",3,IF(V64="Alta",5,)))) -> 0 | Y64: =IF(X64="No clasificada",5,IF(X64="Baja",1,IF(X64="Media",3,IF(X64="Alta",5,)))) -> 0 | Z64: =IF(OR(T64=0,V64=0,X64=0),"FALTAN DATOS",IF(AND(U64=1,W64=1,Y64=1),"BAJA",(IF(OR(AND(U64=5,W64=5),AND(U64=5,Y64=5),AND(U64=5,Y64=5),AND(U64=5,W64=5,Y64=5)),"ALTA","MEDIA")))) -> FALTAN DATOS | AD64: =IF(AC64="Sí","Ley 1581 de 2012",IF(AC64="No","Ley 1755 de 2015","")) | AE64: =IF(AC64="Sí","Artículo 10 y 13",IF(AC64="No","Artículo 27",""))
U65: =IF(T65="No clasificada",5,IF(T65="Información pública clasificada",3,IF(T65="Información pública reservada",5,IF(T65="Información pública",1,)))) -> 0 | W65: =IF(V65="No clasificada",5,IF(V65="Baja",1,IF(V65="Media",3,IF(V65="Alta",5,)))) -> 0 | Y65: =IF(X65="No clasificada",5,IF(X65="Baja",1,IF(X65="Media",3,IF(X65="Alta",5,)))) -> 0 | Z65: =IF(OR(T65=0,V65=0,X65=0),"FALTAN DATOS",IF(AND(U65=1,W65=1,Y65=1),"BAJA",(IF(OR(AND(U65=5,W65=5),AND(U65=5,Y65=5),AND(U65=5,Y65=5),AND(U65=5,W65=5,Y65=5)),"ALTA","MEDIA")))) -> FALTAN DATOS | AD65: =IF(AC65="Sí","Ley 1581 de 2012",IF(AC65="No","Ley 1755 de 2015","")) | AE65: =IF(AC65="Sí","Artículo 10 y 13",IF(AC65="No","Artículo 27",""))
U66: =IF(T66="No clasificada",5,IF(T66="Información pública clasificada",3,IF(T66="Información pública reservada",5,IF(T66="Información pública",1,)))) -> 0 | W66: =IF(V66="No clasificada",5,IF(V66="Baja",1,IF(V66="Media",3,IF(V66="Alta",5,)))) -> 0 | Y66: =IF(X66="No clasificada",5,IF(X66="Baja",1,IF(X66="Media",3,IF(X66="Alta",5,)))) -> 0 | Z66: =IF(OR(T66=0,V66=0,X66=0),"FALTAN DATOS",IF(AND(U66=1,W66=1,Y66=1),"BAJA",(IF(OR(AND(U66=5,W66=5),AND(U66=5,Y66=5),AND(U66=5,Y66=5),AND(U66=5,W66=5,Y66=5)),"ALTA","MEDIA")))) -> FALTAN DATOS | AD66: =IF(AC66="Sí","Ley 1581 de 2012",IF(AC66="No","Ley 1755 de 2015","")) | AE66: =IF(AC66="Sí","Artículo 10 y 13",IF(AC66="No","Artículo 27",""))
U67: =IF(T67="No clasificada",5,IF(T67="Información pública clasificada",3,IF(T67="Información pública reservada",5,IF(T67="Información pública",1,)))) -> 0 | W67: =IF(V67="No clasificada",5,IF(V67="Baja",1,IF(V67="Media",3,IF(V67="Alta",5,)))) -> 0 | Y67: =IF(X67="No clasificada",5,IF(X67="Baja",1,IF(X67="Media",3,IF(X67="Alta",5,)))) -> 0 | Z67: =IF(OR(T67=0,V67=0,X67=0),"FALTAN DATOS",IF(AND(U67=1,W67=1,Y67=1),"BAJA",(IF(OR(AND(U67=5,W67=5),AND(U67=5,Y67=5),AND(U67=5,Y67=5),AND(U67=5,W67=5,Y67=5)),"ALTA","MEDIA")))) -> FALTAN DATOS | AD67: =IF(AC67="Sí","Ley 1581 de 2012",IF(AC67="No","Ley 1755 de 2015","")) | AE67: =IF(AC67="Sí","Artículo 10 y 13",IF(AC67="No","Artículo 27",""))
U68: =IF(T68="No clasificada",5,IF(T68="Información pública clasificada",3,IF(T68="Información pública reservada",5,IF(T68="Información pública",1,)))) -> 0 | W68: =IF(V68="No clasificada",5,IF(V68="Baja",1,IF(V68="Media",3,IF(V68="Alta",5,)))) -> 0 | Y68: =IF(X68="No clasificada",5,IF(X68="Baja",1,IF(X68="Media",3,IF(X68="Alta",5,)))) -> 0 | Z68: =IF(OR(T68=0,V68=0,X68=0),"FALTAN DATOS",IF(AND(U68=1,W68=1,Y68=1),"BAJA",(IF(OR(AND(U68=5,W68=5),AND(U68=5,Y68=5),AND(U68=5,Y68=5),AND(U68=5,W68=5,Y68=5)),"ALTA","MEDIA")))) -> FALTAN DATOS | AD68: =IF(AC68="Sí","Ley 1581 de 2012",IF(AC68="No","Ley 1755 de 2015","")) | AE68: =IF(AC68="Sí","Artículo 10 y 13",IF(AC68="No","Artículo 27",""))
U69: =IF(T69="No clasificada",5,IF(T69="Información pública clasificada",3,IF(T69="Información pública reservada",5,IF(T69="Información pública",1,)))) -> 0 | W69: =IF(V69="No clasificada",5,IF(V69="Baja",1,IF(V69="Media",3,IF(V69="Alta",5,)))) -> 0 | Y69: =IF(X69="No clasificada",5,IF(X69="Baja",1,IF(X69="Media",3,IF(X69="Alta",5,)))) -> 0 | Z69: =IF(OR(T69=0,V69=0,X69=0),"FALTAN DATOS",IF(AND(U69=1,W69=1,Y69=1),"BAJA",(IF(OR(AND(U69=5,W69=5),AND(U69=5,Y69=5),AND(U69=5,Y69=5),AND(U69=5,W69=5,Y69=5)),"ALTA","MEDIA")))) -> FALTAN DATOS | AD69: =IF(AC69="Sí","Ley 1581 de 2012",IF(AC69="No","Ley 1755 de 2015","")) | AE69: =IF(AC69="Sí","Artículo 10 y 13",IF(AC69="No","Artículo 27",""))
U70: =IF(T70="No clasificada",5,IF(T70="Información pública clasificada",3,IF(T70="Información pública reservada",5,IF(T70="Información pública",1,)))) -> 0 | W70: =IF(V70="No clasificada",5,IF(V70="Baja",1,IF(V70="Media",3,IF(V70="Alta",5,)))) -> 0 | Y70: =IF(X70="No clasificada",5,IF(X70="Baja",1,IF(X70="Media",3,IF(X70="Alta",5,)))) -> 0 | Z70: =IF(OR(T70=0,V70=0,X70=0),"FALTAN DATOS",IF(AND(U70=1,W70=1,Y70=1),"BAJA",(IF(OR(AND(U70=5,W70=5),AND(U70=5,Y70=5),AND(U70=5,Y70=5),AND(U70=5,W70=5,Y70=5)),"ALTA","MEDIA")))) -> FALTAN DATOS | AD70: =IF(AC70="Sí","Ley 1581 de 2012",IF(AC70="No","Ley 1755 de 2015","")) | AE70: =IF(AC70="Sí","Artículo 10 y 13",IF(AC70="No","Artículo 27",""))
U71: =IF(T71="No clasificada",5,IF(T71="Información pública clasificada",3,IF(T71="Información pública reservada",5,IF(T71="Información pública",1,)))) -> 0 | W71: =IF(V71="No clasificada",5,IF(V71="Baja",1,IF(V71="Media",3,IF(V71="Alta",5,)))) -> 0 | Y71: =IF(X71="No clasificada",5,IF(X71="Baja",1,IF(X71="Media",3,IF(X71="Alta",5,)))) -> 0 | Z71: =IF(OR(T71=0,V71=0,X71=0),"FALTAN DATOS",IF(AND(U71=1,W71=1,Y71=1),"BAJA",(IF(OR(AND(U71=5,W71=5),AND(U71=5,Y71=5),AND(U71=5,Y71=5),AND(U71=5,W71=5,Y71=5)),"ALTA","MEDIA")))) -> FALTAN DATOS | AD71: =IF(AC71="Sí","Ley 1581 de 2012",IF(AC71="No","Ley 1755 de 2015","")) | AE71: =IF(AC71="Sí","Artículo 10 y 13",IF(AC71="No","Artículo 27",""))
... U88: =IF(T88="No clasificada",5,IF(T88="Información pública clasificada",3,IF(T88="Información pública reservada",5,IF(T88="Información pública",1,)))) -> 0 | W88: =IF(V88="No clasificada",5,IF(V88="Baja",1,IF(V88="Media",3,IF(V88="Alta",5,)))) -> 0 | Y88: =IF(X88="No clasificada",5,IF(X88="Baja",1,IF(X88="Media",3,IF(X88="Alta",5,)))) -> 0 | Z88: =IF(OR(T88=0,V88=0,X88=0),"FALTAN DATOS",IF(AND(U88=1,W88=1,Y88=1),"BAJA",(IF(OR(AND(U88=5,W88=5),AND(U88=5,Y88=5),AND(U88=5,Y88=5),AND(U88=5,W88=5,Y88=5)),"ALTA","MEDIA")))) -> FALTAN DATOS | AD88: =IF(AC88="Sí","Ley 1581 de 2012",IF(AC88="No","Ley 1755 de 2015","")) | AE88: =IF(AC88="Sí","Artículo 10 y 13",IF(AC88="No","Artículo 27",""))
AP119: R

Sheet  1 INSTRUCTIVO
B2: Matriz Mapa de Riesgos | J2: INSTRUCTIVO DILIGENCIAMIENTO DE ACTIVOS DE INFORMACIÓN
J3: OBJETIVO Establecer de manera clara, detallada y paso a paso la forma correcta de diligenciar cada campo del Formato de Gestión y Clasificación de Activos de Información, permitiendo a las dependencias de la entidad identificar, clasificar, valorar y proteger sus activos de información conforme a los lineamientos del Modelo de Seguridad y Privacidad de la Información (MSPI), ISO 27001, Ley 1712 de 2014, Ley 1581 de 2012 y demás normatividad aplicable. A continuación se presenta el diligenciamiento fila por fila para facilitar el registro del formato.
B4: Con la expedición del Decreto 1499 de 2017 “Por medio del cual se modifica el Decreto 1083 de 2015, Decreto Único Reglamentario del Sector Función Pública, en lo relacionado con el Sistema de Gestión establecido en el artículo 133 de la Ley 1753 de 2015”, se crea un solo Sistema de Gestión y se alinea con el Sistema de Control Interno, hoy todas las entidades públicas requieren actualizar y/o implementar el Modelo Integrado de Planeación y Gestión MIPG, modelo que incorpora el Modelo Estándar de Control Interno MECI a través de la 7a dimensión del mismo. En este marco general, el proceso de administración del riesgo es un esfuerzo conjunto entre la Alta Dirección y los servidores en todos sus niveles, ejercicio que inicia con la formulación de la política de Administración del Riesgo, la cual incluye los niveles de responsabilidad frente al seguimiento y evaluación, aspectos que deberán definirse acorde con el Esquema de Líneas de Defensa vinculado a la Dimensión 7. Teniendo en cuenta lo anterior y dada la necesidad de las entidades frente a la estructuración de los mapas de riesgos, como herramienta fundamental frente a la gestión del riesgo, el presente formato desarrolla un esquema completo acorde con los contenidos metodológicos de la Guía para la Administración del Riesgo y el diseño de controles V5. El formato cuenta con celdas parametrizadas y permite contar con los respectivos mapas de calor para riesgo inherente y riesgo residual. | J4: FASE | K4: Columna | L4: Descripción - Lineamientos para el diligenciamiento
J5: FASE 1 | K5: MACROPROCESO | L5: Seleccione el macroproceso de la lista desplegable entre: Direccionamiento Estratégico Gestión de la Información y las Comunicaciones Gestión de Servicios de Salud Gestión Educativa Convivencia Ciudadana, Seguridad y Orden Público Desarrollo Social Integral y Ambiental del Territorio Gestión Financiera Gestión Catastral Gestión Administrativa Gestión del Talento Humano Gestión Jurídica Gestión Estadística Control Interno
B6: Orientaciones Generales | K6: PROCESO | L6: Seleccione el proceso relacionado con el macroproceso y con el activo de información de la lista desplegable.
B7: Antes de iniciar con el diligenciamiento de la información en la matriz, se requiere haber avanzado en el análisis del proceso, su objetivo, alcance, actividades clave, considere los lineamientos establecidos en el Paso 2: identificación del riesgo, donde se explica ampliamente las bases para adelantar este análisis. Así mismo, considere en el Paso 3: valoración del riesgo los lineamientos para definir el No. de veces que se hace la actividad con la cual se relaciona el riesgo y su impacto en términos económicos o reputacionales. En este mismo paso se analizan los controles que deben responder a los atributos de eficiencia e informativos. | K7: CÓDIGO DEL SISTEMA DE GESTIÓN DOCUMENTAL | L7: Diligencie el código documental asignado en la Tabla de Retención Documental (TDR) o instrumentos archivísticos. Si no existe, escriba “No aplica”.
K8: IDENTIFICADOR | L8: Registre un código único que permita identificar el activo. Se recomienda usar una combinación de la dependencia + número consecutivo. Por ejemplo, TIC-001
B9: Las hojas se encuentran protegidas para evidar dañar las formulas, para desprotegerlas no se requiere contraseña | K9: TIPO | L9: Seleccione el tipo de activo de información de la lista desplegable entre: Información (Bases de datos de clientes, contratos, hojas de cálculo financieras, manuales internos, correos electrónicos, reportes de ventas) Software (Sistema ERP, antivirus, sistema operativo Windows/Linux, aplicación contable, CRM, aplicaciones móviles) Hardware (Servidores, computadores portátiles, impresoras, discos duros externos, routers, cámaras de seguridad) Servicios (Servicio de correo electrónico corporativo, hosting web, nube (AWS/Azure), internet empresarial, mesa de ayuda TI) Intangibles (Marca de la empresa, propiedad intelectual, licencias, patentes, reputación corporativa, know-how) Componentes de red (Switches, firewalls, access points Wi-Fi, cables de red, módems, balanceadores de carga) Recurso humano No aplica
K10: OFICINA | L10: Seleccione la dependencia u oficina responsable o relacionada con el activo de información de la lista desplegable entre: Despacho del Alcalde Agricultura Ambiente Asuntos Étnicos Cultura Desarrollo Social Educación Gobierno Gestión Institucional Hacienda Infraestructura Planeación Salud Turismo Vivienda General Jurídica Seguridad y Convivencia Comunicaciones Control I​nterno Control Interno y Disciplinario​ Cooperación Internacion​al​ Tecnologías de la Información y las Comunicaciones​ Progr​amas Especiales​ Posconflicto​ Equidad de Género​ Juventudes Libertad Religiosa Gestión Catastral
B11: Se debe ingresar información solo en las celdas identificadas con color NARANJA CLARO, las demás contienen formulas de autollenado | K11: SERIE DOCUMENTAL | L11: Ingrese la serie documental del área, dependencia o proceso donde se encuentra identificado el activo. Por ejemplo: Si el activo se encuentra en la secretaría jurírica y el activo es un PROCESO JURIDICO el número de serie 34-42
K12: SUBSERIE DOCUMENTAL | L12: Ingrese la subserie documental correspondiente a la serie donde se encuentra el activo. Por ejemplo: Para el PROCESO JURIDICO si es un proceso de cobro coactivo el número de serie sería 34-42 01
B13: El formato de fecha es: DD/MM/AAAA | K13: NOMBRE | L13: Registre el nombre del activo de información de forma clara y específica.
K14: DESCRIPCIÓN | L14: Describa de manera resumida la función, contenido o propósito del activo.
B15: El archivo contiene las siguientes hojas: | K15: NOMBRE DEL RESPONSABLE DE LA PRODUCCIÓN DE LA INFORMACIÓN (PROPIETARIO DEL ACTIVO) | L15: Diligencie el nombre completo de la persona encargada de crear, generar o administrar funcionalmente la información.
K16: FECHA DE GENERACIÓN DE LA INFORMACIÓN | L16: Ingrese la fecha en la que el activo de información fue creado o comenzó a generarse.
B17: 1 INSTRUCTIVO: Identifica el contenido del archivo y su funcionalidad | K17: NOMBRE DEL RESPONSABLE DE LA INFORMACIÓN (CUSTODIO DEL ACTIVO) | L17: Ingrese el nombre completo de la persona encargada de custodiar, almacenar o mantener el activo.
K18: FECHA DE INGRESO DEL ACTIVO AL ARCHIVO | L18: Ingrese la fecha en la que el activo fue archivado o incorporado al sistema de gestión documental, formato (DD/MM/AAAA)
B19: 2 CONTEXTO E IDENTIFICACIÓN: Se establece el Número, Descripción y Factor del riesgo | K19: MEDIO DE CONSERVACIÓN | L19: Seleccione el medio de conservación del activo (físico, formato, contenedor o soporte tecnológico) de la lista desplegable entre: Fisico Digital No aplica
K20: FORMATO | L20: Seleccione el tipo de formato en el que se presenta o consulta el activo de la lista desplegable entre: Formato Audio Documento de texto Documento PDF Presentación Hoja de calculo Imagen Video Base de datos Otro No aplica
C21: Columna | E21: Descripción - Lineamientos para el diligenciamiento | K21: IDIOMA | L21: Establezca el idioma en el que está redactado o disponible el activo.
C22: Proceso | E22: Diligencie el nombre del proceso al cual se le identificarán y valorarán los riesgos.
C23: Objetivo del Proceso | E23: Diligencie el objetivo del proceso. | J23: FASE 2 | K23: CONFIDENCIALIDAD | L23: Seleccione el nivel de restricción del activo de información según el acceso permitido de la lista desplegable entre: Información pública reservada: Es la información que no debe ser divulgada debido a que esto puede causar daño a intereses públicos. Solamente la Constitución o la ley pueden definir qué información es de carácter reservado. Información pública clasificada: Es la información que no debe ser divulgada debido a que se pueden vulnerar los derechos de las personas naturales o jurídicas, tales como: derecho de las personas a la intimidad, derecho a la vida, salud o seguridad y los secretos comerciales, industriales y profesionales. Información pública: Información que puede ser entregada o publicada sin restricciones a cualquier persona dentro y fuera de la entidad, sin que esto implique daños a terceros ni a las actividades y procesos de la entidad. No clasificada: Activos de Información que deben ser incluidos en el inventario y que aún no han sido clasificados, deben ser tratados como activos de INFORMACIÓN PÚBLICA RESERVADA. como: Hardware, Colaboradores de Planta o Contratistas
C24: Elaboración o Actualización: | E24: Fecha en la que realiza el diligenciamiento o actualización del mapa de riesgos, formato (DD/MM/AAAA) | K24: INTEGRIDAD | L24: Seleccione el nivel de importancia relacionado con la exactitud y completitud de la información de la lista desplegable entre: Alta: Información cuya pérdida de exactitud y completitud puede conllevar un impacto negativo de índole legal o económica, retrasar sus funciones, o generar pérdidas de imagen severas de la entidad. Media: Información cuya pérdida de exactitud y completitud puede conllevar un impacto negativo de índole legal o económica, retrasar sus funciones, o generar pérdida de imagen moderada a funcionarios de la entidad. Baja: Información cuya pérdida de exactitud y completitud conlleva un impacto no significativo para la entidad o entes externos. No clasificada: Activos de Información que deben ser incluidos en el inventario y que aún no han sido clasificados, deben ser tratados como activos de información de integridad ALTA.
C25: Vigencia: | E25: Vigencia que tiene el mapa de riesgos fecha inicio fecha final, formato (DD/MM/AAAA) | K25: DISPONIBILIDAD | L25: Seleccione el nivel de necesidad de acceso continuo al activo de información de la lista desplegable entre: Alta: La no disponibilidad de la información puede conllevar un impacto negativo de índole legal o económica, retrasar sus funciones, o generar pérdidas de imagen severas a entes externos. Media: La no disponibilidad de la información puede conllevar un impacto negativo de índole legal o económica, retrasar sus funciones, o generar pérdida de imagen moderada de la entidad. Baja: La no disponibilidad de la información puede afectar la operación normal de la entidad o entes externos, pero no conlleva implicaciones legales, económicas o de pérdida de imagen. No clasificada: Activos de Información que deben ser incluidos en el inventario y que aún no han sido clasificados, deben ser tratados como activos de información de disponibilidad ALTA.
C26: No. de Riesgo | E26: Permite definir unl consecutivo de riesgos. Una entidad puede ir en el riesgo 150, pero tener 70 riesgos, lo que permite llevar una traza de los riesgos. Esta información la debe administrar la oficina asesora de planeación o gerencia de riesgos. Cuando un el riesgo salga del mapa no existirá otro riesgo con el mismo número. | K26: INFORMACIÓN PUBLICADA | L26: Seleccione el estado de publicación de la información de la lista desplegable entre: Publicada Disponible a solicitud No publicada o disponible
C27: ¿QUÉ? IMPACTO | E27: Analice las consecuencias que puede ocasionar a la organización la materialización del riesgo, Seleccione de la lista desplegable entre: Posibilidad de pérdida Económica Posibilidad de pérdida Reputacional Posibilidad de pérdida Económica y Reputacional | K27: LUGAR DE CONSULTA O UBICACIÓN | L27: Seleccione el lugar físico o digital donde se consulta o almacena el activo de la lista desplegable entre: Portal web propios Portal web de terceros Intranet Archivo físico Archivo digital Sistema de información Base de datos
C28: ¿CÓMO? CAUSA INMEDIATA | E28: Circunstancias bajo las cuales se presenta el riesgo, es la situación más evidente frente al riesgo, redacte de la forma más concreta posible. (Iniciar con la palabra por)
C29: ¿PORQUÉ? CAUSA RAÍZ | E29: Causa principal o básica, corresponde a las razones por la cuales se puede presentar el riesgo, redacte de la forma más concreta posible. (Iniciar con debido a) | J29: FASE 3 | K29: OBJETO LEGÍTIMO DE LA EXCEPCIÓN | L29: Se refiere a la justificación jurídica válida que permite reservar, clasificar o denegar el acceso a cierta información pública. Es la causal o motivo legal, como la protección de datos personales o la seguridad nacional, que autoriza a las entidades estatales a mantener documentos en reserva. (por ejemplo, por razones de seguridad, confidencialidad, o acceso restringido).
C30: DESCRIPCIÓN DEL RIESGO | E30: Consolida o resume los análisis sobre impacto + causa inmediata + causa raíz, permitiendo contar con una redacción clara y concreta del riesgo indentificado. Tenga en cuenta la estructura de alto nivel establecida en al guía, inicia con POSIBILIDAD DE + Impacto para la entidad (Qué) + Causa Inmediata (Cómo) + Causa Raíz (Por qué) (Se genera automáticamente) | K30: FUNDAMENTO CONSTITUCIONAL O LEGAL | L30: Registrar la norma o artículo que soporta la clasificación o reserva de la información. Ejemplo: “Ley 1581 de 2012” para tipos de activo software, “Ley 1712 de 2014” para todos los demás activos“ Constitución Política Art. 15”.
C31: FACTOR DEL RIESGO / TIPO | E31: Seleccione de la lista desplegable entre las opiciones: A_Ejecución_y_Administración_de_procesos B_Infraestructura D_Evento externo E_Talento_Humano F_Transacción_u_Operación_aplica_para_LA_FT_FP G_Tecnología | K31: EXCEPCIÓN TOTAL O PARCIAL | L31: Indicar si la restricción aplica sobre toda la información o solo una parte de ella. Seleccione de la lista desplegable entre: Total Parical Sin excepción
C32: FACTOR DEL RIESGO / SELECCIONE FUENTE GENERADORA DEL EVENTO | E32: Seleccione de la lista desplegable entre las opiciones: A_Ejecución_y_Administración_de_procesos: - Falta de aplicación de los procedimientos - Falta segregación de funciones - Errores de grabación, autorización - Errores en cálculos para pagos internos y externos - Falta de supervisión o interventoría - Alta rotación o insuficiencia de personal - Acciones contrarias a las leyes o acuerdos de empleo, salud o seguridad en el trabajo - Acciones contrarias a las leyes o acuerdos contractuales - Falta de capacitación y otros temas relacionados con el personal | K32: FECHA DE CLASIFICACIÓN | L32: Registrar la fecha en la cual el activo fue clasificado como reservado o clasificado. Utilizar formato DD/MM/AAAA. Ejemplo: “15/01/2026”.
E33: B_Infraestructura: - Derrumbes - Incendios - Inundaciones - Daños a activos fijos | K33: TIEMPO DE LA CLASIFICACIÓN | L33: Registrar el tiempo durante el cual la información permanecerá clasificada o reservada, según la normatividad aplicable. Ejemplo: “15 años”, “5 años”, “Permanente”.
E34: D_Evento externo: - Fraude Externo - Suplantación de identidad - Asalto a la oficina - Atentados, vandalismo, orden público
E35: E_Talento_Humano: - Fraude interno - Soborno - Gestión inadecuada de conflicto de Intereses - Corrupción - Hurto de activos | J35: FASE 4 | K35: ¿CONTIENE DATOS PERSONALES? | L35: Seleccione si el activo contiene información asociada a personas naturales identificadas o identificables de la lista desplegable entre: Sí No. Por ejempolo si es de “Nómina = Sí”.
E36: F_Transacción_u_Operación_aplica_para_LA_FT_FP - Contrapartes de la entidad (naturales o jurídicas) - Productos (bienes o servicios) que oferta/requiere - Canales utilizados para la operación - Jurisdicciones (nacional o territorial) | K36: ¿CONTIENE DATOS DE NIÑOS, NIÑAS O ADOLESCENTES? | L36: "Seleccione si el activo contiene información asociada a personas naturales identificadas o identificables de la lista desplegable entre: Sí No. Por ejempolo si es de “Base de datos estudiantil= Sí”."
E37: G_Tecnología - Daño de equipos - Caída de sistemas de información y aplicaciones - Caída de redes - Errores en hardware o software - Errores en programas | K37: TIPOS DE DATOS PERSONALES | L37: Seleccione el tipo de dato personal contenido en el activo de la lista desplegable entre: Dato público: Información que puede ser conocida y consultada por cualquier persona sin necesidad de autorización del titular, debido a que no afecta su intimidad ni genera riesgos de discriminación. Ejemplo: nombre, estado civil, profesión u oficio, calidad de comerciante o servidor público. Dato semiprivado: Información que no tiene naturaleza íntima, reservada ni pública, y cuyo conocimiento puede interesar tanto al titular como a un grupo determinado de personas o a la sociedad. Su acceso está sujeto a ciertos controles. Ejemplo: historial crediticio, información financiera o comercial. Dato privado: Información que únicamente interesa al titular por su carácter íntimo o reservado y que no debe ser conocida públicamente sin autorización. Ejemplo: dirección de residencia, número telefónico personal, correos electrónicos personales o información laboral interna. Dato sensible: Información que puede afectar la intimidad del titular o generar discriminación en caso de ser divulgada. Requiere especial protección legal. Ejemplo: origen racial o étnico, orientación política, convicciones religiosas, datos biométricos, información de salud, orientación sexual. Dato vulnerable: Información asociada a personas que requieren protección especial debido a condiciones particulares de edad, discapacidad, situación social o dependencia. Incluye datos de menores de edad, adultos mayores, víctimas del conflicto, personas con discapacidad, entre otros. No aplica: Clasificación utilizada cuando la información evaluada no corresponde a datos personales o no contiene información relacionada con personas naturales identificadas o identificables.
C38: RESULTADO FUENTE GENERADORA DEL EVENTO | E38: Se rellena automáticamente según lo seleccinado de FACTOR DEL RIESGO | K38: FINALIDAD DE LA RECOLECCIÓN DE LOS DATOS PERSONALES | L38: Registrar el propósito para el cual fueron recolectados los datos personales. Ejemplo: “Gestión de pagos salariales”, “Atención al ciudadano”, “Gestión académica”.
K39: EXISTE AUTORIZACIÓN PARA EL TRATAMIENTO DE DATOS PERSONALES | L39: Indicar si la entidad cuenta con autorización para el tratamiento de los datos personales.
B40: 3 PROBABIL E IMPACTO INHERENTE:
J41: Nota: Si el campo no aplica al activo, escriba “No aplica” únicamente cuando el instructivo o el formato lo permitan.
C42: Columna | E42: Descripción - Lineamientos para el diligenciamiento
C43: No. veces que realiza la actividad al año | E43: Defina el número de veces que se ejecuta la actividad durante el año, (Recuerde la probabilidad e ocurrencia del riesgo se define como el No. de veces que se pasa por el punto de riesgo en el periodo de 1 año). La matriz automáticamente hará el cálculo para el nivel de probabilidad inherente. La matriz calcula automáticamente: Frecuencia de la Actividad % Probabilidad Nivel Probabilidad
C44: Afectación Económica | E44: Selecciona de la lista desplegable el rango de afectación económica y la matriz calcula: % Nivel
C45: Reputacional | E45: Selecciona de la lista desplegable el rango de afectación reputacional y la matriz calcula: % Nivel
C46: Resultado / Porcentaje de Impacto / Nivel de Impacto | E46: Se calcula automáticamente según la información de afectación económica y reputacional
B48: 4 MAPA CALOR INHERENTE: Representación gráfica de la ubicación de cada riesgo inherente en el mapa de calor (En esta hoja no se ingresan datos)
B50: 5 VALORACIÓN DEL CONTROL: Se realiza la descripción y atributos del control, calcula automáticamente el Valor Total del Control, Probabilidad residual e Impacto Residual
C52: Columna | E52: Descripción - Lineamientos para el diligenciamiento
C53: Descripción del Control | E53: Recuerde que el control se define como la medida que permite reducir o mitigar un riesgo. Defina el control (es) que atacan la causa raíz del riesgo, considere la estructura explicada en la guía: Responsable de ejecutar el control + Acción + Complemento
C54: Tipo de control | E54: Debe seleccionar de lista desplegable entre: Preventivo Detectivo Correctivo
C55: Peso del Control | E55: Se calcula automáticamente según lo seleccionado en Tipo de Control Preventivo: 25 % Detectivo: 15 % Correctivo: 10 %
C56: Afectación o Desplazamiento en la Matriz | E56: Se calcula automáticamente según lo seleccionado en Tipo de Control Preventivo: 25 % Detectivo: 15 % Correctivo: 10 %
C57: Implementación | E57: Debe seleccionar de lista desplegable entre: Automático: 25 % Manual: 15 %
C58: Peso de la implementación | E58: Se calcula automáticamente según lo seleccionado en Implementación Manual Automático
C59: Informativos | E59: Debe seleccionar de listas desplegables Documentación: Documentado - Sin Documentar Frecuencia: Continua - Aleatoria Evidencia: Con registro - Sin registro
C60: Valor Total del Control | E60: Se calcula automáticamente: Peso del Control + Peso de la implementación
C61: Probabilidad residual | E61: Se calcula automáticamente: % Probabilidad Riesgo Inherente-(% Probabilidad Riesgo Inherente*Valor Total del Control)
C62: Impacto Residual | E62: % Impacto Riesgo Inherente-(% Impacto Riesgo Inherente*Valor Total del Control)
B64: 6 MAPA CALOR RESIDUAL: Representación gráfica de la ubicación de cada riesgo residual en el mapa de calor (En esta hoja no se ingresan datos)
B66: 7 MAPA CALOR INHEREN Y RESIDUAL: Comparación gráfica de la ubicación de cada riesgo inherente y residual en el mapa de calor (En esta hoja no se ingresan dados)
B68: 8 MAPA RIESGOS: Establece el Tratamiento, Plan de Acción, Seguimientos por parte del Líder del Proceso, Verificación por parte de segunda línea de defensa o quien haga sus veces, Verificación por parte de la Oficina de Control Interno o quien haga sus veces y el estado de la acción.
C70: Columna | E70: Descripción - Lineamientos para el diligenciamiento
C71: SEVERIDAD (NIVEL DE RIESGO) | E71: Se calcula automáticamente según CALIFICACIÓN RIESGO RESIDUAL / PROBABILIDAD E IMPACTO
C72: Tratamiento | E72: Se calcula automáticamente según SEVERIDAD (NIVEL DE RIESGO): Extremo, Alto, Moderado: Reducir, mitigar, Transferir, Evitar Bajo: Aceptar
C73: ¿Requiere Plan de Acción? | E73: Se calcula automáticamente según Tratamiento Reducir, mitigar, Transferir, Evitar: Requiere plan de acción Aceptar: No requiere plan de acción
C74: Plan de Acción Descripción de la Acción, basado en el análisis de causas Responsable (Cargo) Fecha de Inicio Fecha de Finalización | E74: Esta casilla dependerá del tratamiento establecido, si es Aceptar no se requieren acciones adicionales, en caso de escoger Reducir (mitigar) se deben diligenciar las acciones que se adelantarán como complemento a los controles establecidos, no necesariamente son controles adicionales. Para Reducir (compartir), es viable diligenciar la acción que deriva de esta (ejemplo póliza seguros, terceración), indicando información relevante.
C75: Seguimientos por parte del Líder del Proceso | E75: Realizar descripción de los seguimientos por parte del proceso
C76: Verificación por parte de segunda línea de defensa o quien haga sus veces (Fecha y Descripción) | E76: Realizar descripción de las verificaciones de la segunda línea de defensa
C77: Verificación por parte de la Oficina de Control Interno o quien haga sus veces (Fecha y Descripción) | E77: Realizar descripción de las verificaciones que realiza Control Interno o quien haga sus veces.
C78: Estado | E78: Utilice la lista de despligue que se encuentra parametrizada, le aparecerán las opciones: Sin Iniciar, En proceso, Cerrado, la selección en este caso dependerá de las acciones del plan que se hayan establecido en cada caso.
B80: 9 RIESGO DEL PROCESO: Calcula el nivel de riesgo del proceso (En esta hoja no se ingresan datos)
B82: 10 CONTROL DE CAMBIOS: En ella se debe registrar los cambios al formato y al contenido del mismo
B84: 11 FORMULAS: La información que contiene se utiliza para realizar operaciones en las demás hojas (En esta hoja no se ingresan datos)
B87: Lista de datos de la matriz:
B90: Hoja | C90: Columna | E90: Descripción - Lineamientos para el diligenciamiento
B91: 2 | C91: Proceso | E91: Diligencie el nombre del proceso al cual se le identificarán y valorarán los riesgos.
B92: 2 | C92: Objetivo del Proceso | E92: Diligencie el objetivo del proceso.
B93: 2 | C93: Elaboración o Actualización: | E93: Fecha en la que realiza el diligenciamiento o actualización del mapa de riesgos, formato (DD/MM/AAAA)
B94: 2 | C94: Vigencia: | E94: Vigencia que tiene el mapa de riesgos fecha inicio fecha final, formato (DD/MM/AAAA)
B95: 2 | C95: No. de Riesgo | E95: Permite definir unl consecutivo de riesgos. Una entidad puede ir en el riesgo 150, pero tener 70 riesgos, lo que permite llevar una traza de los riesgos. Esta información la debe administrar la oficina asesora de planeación o gerencia de riesgos. Cuando un el riesgo salga del mapa no existirá otro riesgo con el mismo número.
B96: 2 | C96: ¿QUÉ? IMPACTO | E96: Analice las consecuencias que puede ocasionar a la organización la materialización del riesgo, Seleccione de la lista desplegable entre: Posibilidad de pérdida Económica Posibilidad de pérdida Reputacional Posibilidad de pérdida Económica y Reputacional
B97: 2 | C97: ¿CÓMO? CAUSA INMEDIATA | E97: Circunstancias bajo las cuales se presenta el riesgo, es la situación más evidente frente al riesgo, redacte de la forma más concreta posible. (Iniciar con la palabra por)
B98: 2 | C98: ¿PORQUÉ? CAUSA RAÍZ | E98: Causa principal o básica, corresponde a las razones por la cuales se puede presentar el riesgo, redacte de la forma más concreta posible. (Iniciar con debido a)
B99: 2 | C99: DESCRIPCIÓN DEL RIESGO | E99: Consolida o resume los análisis sobre impacto + causa inmediata + causa raíz, permitiendo contar con una redacción clara y concreta del riesgo indentificado. Tenga en cuenta la estructura de alto nivel establecida en al guía, inicia con POSIBILIDAD DE + Impacto para la entidad (Qué) + Causa Inmediata (Cómo) + Causa Raíz (Por qué) (Se genera automáticamente)
B100: 2 | C100: FACTOR DEL RIESGO / TIPO | E100: Seleccione de la lista desplegable entre las opiciones: A_Ejecución_y_Administración_de_procesos B_Fraude_Externo C_Fraude_Interno D_Fallas_Tecnológicas E_Relaciones_Laborales F_Usuarios_Productos_y_Prácticas_Organizacionales G_Daños_Activos_Físicos
B101: 2 | C101: FACTOR DEL RIESGO / SELECCIONE FUENTE GENERADORA DEL EVENTO PARA TIPO E,F,G | E101: Si en TIPO seleccioneó las opiciones: E_Relaciones_Laborales F_Usuarios_Productos_y_Prácticas_Organizacionales G_Daños_Activos_Físicos Debe definir la fuente generadora de la lista desplegable
B102: 2 | C102: RESULTADO FUENTE GENERADORA DEL EVENTO | E102: Se rellena automáticamente según lo seleccinado de FACTOR DEL RIESGO
... B124: 8 | C124: Estado | E124: Utilice la lista de despligue que se encuentra parametrizada, le aparecerán las opciones: Sin Iniciar, En proceso, Cerrado, la selección en este caso dependerá de las acciones del plan que se hayan establecido en cada caso.
B131: Archivo creado por:

Sheet 2 CONTEXTO E IDENTIFICACIÓN
A1: MAPA DE RIESGOS
A2: VERSIÓN: | B2: 1
A4: ENTIDAD: | E4: PROCESO: Control Interno | J4: Elaboración o Actualización: | K4: 45991
A5: PROCESO: | E5: Vigencia: | G5: Del | H5: 46023 | J5: Al | K5: 46387
A7: No. de Riesgo (Mismo consecutivo para toda la entidad) | B7: FACTOR DEL RIESGO
B8: FACTOR DE RIESGO | C8: SELECCIONE FUENTE GENERADORA DEL EVENTO PARA TIPO E,F,G | D8: VALIDACIÓN FUENTE GENERADORA DEL EVENTO PARA TIPO A,B,C,D | E8: DESCRIPCIÓN DEL TIPO DE FACTOR DE RIESGO | F8: TIPOLOGÍA | G8: ACTIVO DE INFORMACION (Diligenciar solo si Tipologia es Seguridad_Información) | H8: ¿QUÉ? IMPACTO | I8: ¿CÓMO? CAUSA INMEDIATA (Iniciar con la palabra por) | J8: ¿PORQUÉ? CAUSA RAÍZ (Iniciar con debido a/a causa de) | K8: DESCRIPCIÓN DEL RIESGO | L8: SUB CAUSAS (Si aplica)
A9: R1 | B9: Integridad_Pública_LA_FT_FP | C9: Contrapartes de la entidad (naturales o jurídicas) | D9: =+IF(B9='11 FORMULAS'!$B$4,'11 FORMULAS'!$C$4,IF(B9='11 FORMULAS'!$B$6,'11 FORMULAS'!$C$6,IF(B9='11 FORMULAS'!$B$8,'11 FORMULAS'!$C$8,IF(B9='11 FORMULAS'!$B$10,'11 FORMULAS'!$C$10,"")))) | E9: =+IFERROR(VLOOKUP(B9,Tabla3[],2,0),"") -> Eventos relacionados con transacciones y Operaciones realizadas por un cliente o usuario, que accede o entrega un bien o servicio a la entidad, a través de los canales dispuestos y en una jurisdicción específica. | F9: Seguridad_Información | G9: SISNET | H9: Posibilidad de perdida de Disponibilidad, confidencialidad e integridad de la información | I9: por fallas en el sistema | J9: debido a deficiencias en la infraestructura tecnológica, ausencia o insuficiencia de mantenimiento preventivo y correctivo | K9: =(CONCATENATE(Tabla1[[#This Row],[¿QUÉ? IMPACTO]]," ",Tabla1[[#This Row],[¿CÓMO? CAUSA INMEDIATA (Iniciar con la palabra por)]]," "," ",Tabla1[[#This Row],[¿PORQUÉ? CAUSA RAÍZ (Iniciar con debido a/a causa de)]])) -> Posibilidad de perdida de Disponibilidad, confidencialidad e integridad de la información por fallas en el sistema debido a deficiencias en la infraestructura tecnológica, ausencia o insuficiencia de mantenimiento preventivo y correctivo
A10: R2 | D10: =+IF(B10='11 FORMULAS'!$B$4,'11 FORMULAS'!$C$4,IF(B10='11 FORMULAS'!$B$6,'11 FORMULAS'!$C$6,IF(B10='11 FORMULAS'!$B$8,'11 FORMULAS'!$C$8,IF(B10='11 FORMULAS'!$B$10,'11 FORMULAS'!$C$10,"")))) | E10: =+IFERROR(VLOOKUP(B10,Tabla3[],2,0),"") | F10: Seguridad_Información | G10: Sistema de Correo Institucional | H10: Posibilidad de perdida de Disponibilidad, confidencialidad e integridad de la información | I10: por accesos no autorizados, hackeos o fallas en el servicio | J10: debido a controles de seguridad y autenticación de usuarios, falta de actualización o monitoreo de la plataforma | K10: =(CONCATENATE(Tabla1[[#This Row],[¿QUÉ? IMPACTO]]," ",Tabla1[[#This Row],[¿CÓMO? CAUSA INMEDIATA (Iniciar con la palabra por)]]," "," ",Tabla1[[#This Row],[¿PORQUÉ? CAUSA RAÍZ (Iniciar con debido a/a causa de)]])) -> Posibilidad de perdida de Disponibilidad, confidencialidad e integridad de la información por accesos no autorizados, hackeos o fallas en el servicio debido a controles de seguridad y autenticación de usuarios, falta de actualización o monitoreo de la plataforma
A11: R3 | D11: =+IF(B11='11 FORMULAS'!$B$4,'11 FORMULAS'!$C$4,IF(B11='11 FORMULAS'!$B$6,'11 FORMULAS'!$C$6,IF(B11='11 FORMULAS'!$B$8,'11 FORMULAS'!$C$8,IF(B11='11 FORMULAS'!$B$10,'11 FORMULAS'!$C$10,"")))) | E11: =+IFERROR(VLOOKUP(B11,Tabla3[],2,0),"") | F11: Seguridad_Información | G11: Repositorio Archivo digital de correspondecia | H11: Posibilidad de perdida de Disponibilidad, confidencialidad e integridad de la información | I11: por eliminación accidental de archivos, fallas en el sistema o accesos no autorizados | J11: a causa de deficiencias en copias de seguridad, controles de accesos o ausencia de politicas de preservación digital | K11: =(CONCATENATE(Tabla1[[#This Row],[¿QUÉ? IMPACTO]]," ",Tabla1[[#This Row],[¿CÓMO? CAUSA INMEDIATA (Iniciar con la palabra por)]]," "," ",Tabla1[[#This Row],[¿PORQUÉ? CAUSA RAÍZ (Iniciar con debido a/a causa de)]])) -> Posibilidad de perdida de Disponibilidad, confidencialidad e integridad de la información por eliminación accidental de archivos, fallas en el sistema o accesos no autorizados a causa de deficiencias en copias de seguridad, controles de accesos o ausencia de politicas de preservación digital
A12: R4 | D12: =+IF(B12='11 FORMULAS'!$B$4,'11 FORMULAS'!$C$4,IF(B12='11 FORMULAS'!$B$6,'11 FORMULAS'!$C$6,IF(B12='11 FORMULAS'!$B$8,'11 FORMULAS'!$C$8,IF(B12='11 FORMULAS'!$B$10,'11 FORMULAS'!$C$10,"")))) | E12: =+IFERROR(VLOOKUP(B12,Tabla3[],2,0),"") | F12: Seguridad_Información | G12: GECO | H12: Posibilidad de perdida de Disponibilidad, confidencialidad e integridad de la información | I12: por fallas tecnológicas y manipulación indebida de la información o interrupciones del servicio | J12: debido a falta de actualización tecnólogica, vulnerabilidades en la administración de la plataforma o controles de seguridad avanzados | K12: =(CONCATENATE(Tabla1[[#This Row],[¿QUÉ? IMPACTO]]," ",Tabla1[[#This Row],[¿CÓMO? CAUSA INMEDIATA (Iniciar con la palabra por)]]," "," ",Tabla1[[#This Row],[¿PORQUÉ? CAUSA RAÍZ (Iniciar con debido a/a causa de)]])) -> Posibilidad de perdida de Disponibilidad, confidencialidad e integridad de la información por fallas tecnológicas y manipulación indebida de la información o interrupciones del servicio debido a falta de actualización tecnólogica, vulnerabilidades en la administración de la plataforma o controles de seguridad avanzados
A13: R5 | D13: =+IF(B13='11 FORMULAS'!$B$4,'11 FORMULAS'!$C$4,IF(B13='11 FORMULAS'!$B$6,'11 FORMULAS'!$C$6,IF(B13='11 FORMULAS'!$B$8,'11 FORMULAS'!$C$8,IF(B13='11 FORMULAS'!$B$10,'11 FORMULAS'!$C$10,"")))) | E13: =+IFERROR(VLOOKUP(B13,Tabla3[],2,0),"") | F13: Seguridad_Información | G13: Portal web | H13: Posibilidad de perdida de disponibilidad e integridad de la información | I13: por ataques cibernéticos, modificaciones no autorizadas o fallas del servidor | J13: debido a ausencia de monitoreo permanente y mantenimiento de la plataforma o deficiencias en la implementación de controles de seguridad | K13: =(CONCATENATE(Tabla1[[#This Row],[¿QUÉ? IMPACTO]]," ",Tabla1[[#This Row],[¿CÓMO? CAUSA INMEDIATA (Iniciar con la palabra por)]]," "," ",Tabla1[[#This Row],[¿PORQUÉ? CAUSA RAÍZ (Iniciar con debido a/a causa de)]])) -> Posibilidad de perdida de disponibilidad e integridad de la información por ataques cibernéticos, modificaciones no autorizadas o fallas del servidor debido a ausencia de monitoreo permanente y mantenimiento de la plataforma o deficiencias en la implementación de controles de seguridad
A14: R6 | D14: =+IF(B14='11 FORMULAS'!$B$4,'11 FORMULAS'!$C$4,IF(B14='11 FORMULAS'!$B$6,'11 FORMULAS'!$C$6,IF(B14='11 FORMULAS'!$B$8,'11 FORMULAS'!$C$8,IF(B14='11 FORMULAS'!$B$10,'11 FORMULAS'!$C$10,"")))) | E14: =+IFERROR(VLOOKUP(B14,Tabla3[],2,0),"") | K14: =(CONCATENATE(Tabla1[[#This Row],[¿QUÉ? IMPACTO]]," ",Tabla1[[#This Row],[¿CÓMO? CAUSA INMEDIATA (Iniciar con la palabra por)]]," "," ",Tabla1[[#This Row],[¿PORQUÉ? CAUSA RAÍZ (Iniciar con debido a/a causa de)]]))
A15: R7 | D15: =+IF(B15='11 FORMULAS'!$B$4,'11 FORMULAS'!$C$4,IF(B15='11 FORMULAS'!$B$6,'11 FORMULAS'!$C$6,IF(B15='11 FORMULAS'!$B$8,'11 FORMULAS'!$C$8,IF(B15='11 FORMULAS'!$B$10,'11 FORMULAS'!$C$10,"")))) | E15: =+IFERROR(VLOOKUP(B15,Tabla3[],2,0),"") | K15: =(CONCATENATE(Tabla1[[#This Row],[¿QUÉ? IMPACTO]]," ",Tabla1[[#This Row],[¿CÓMO? CAUSA INMEDIATA (Iniciar con la palabra por)]]," "," ",Tabla1[[#This Row],[¿PORQUÉ? CAUSA RAÍZ (Iniciar con debido a/a causa de)]]))
A16: R8 | D16: =+IF(B16='11 FORMULAS'!$B$4,'11 FORMULAS'!$C$4,IF(B16='11 FORMULAS'!$B$6,'11 FORMULAS'!$C$6,IF(B16='11 FORMULAS'!$B$8,'11 FORMULAS'!$C$8,IF(B16='11 FORMULAS'!$B$10,'11 FORMULAS'!$C$10,"")))) | E16: =+IFERROR(VLOOKUP(B16,Tabla3[],2,0),"") | K16: =(CONCATENATE(Tabla1[[#This Row],[¿QUÉ? IMPACTO]]," ",Tabla1[[#This Row],[¿CÓMO? CAUSA INMEDIATA (Iniciar con la palabra por)]]," "," ",Tabla1[[#This Row],[¿PORQUÉ? CAUSA RAÍZ (Iniciar con debido a/a causa de)]]))
A17: R9 | D17: =+IF(B17='11 FORMULAS'!$B$4,'11 FORMULAS'!$C$4,IF(B17='11 FORMULAS'!$B$6,'11 FORMULAS'!$C$6,IF(B17='11 FORMULAS'!$B$8,'11 FORMULAS'!$C$8,IF(B17='11 FORMULAS'!$B$10,'11 FORMULAS'!$C$10,"")))) | E17: =+IFERROR(VLOOKUP(B17,Tabla3[],2,0),"") | K17: =(CONCATENATE(Tabla1[[#This Row],[¿QUÉ? IMPACTO]]," ",Tabla1[[#This Row],[¿CÓMO? CAUSA INMEDIATA (Iniciar con la palabra por)]]," "," ",Tabla1[[#This Row],[¿PORQUÉ? CAUSA RAÍZ (Iniciar con debido a/a causa de)]]))
A18: R10 | D18: =+IF(B18='11 FORMULAS'!$B$4,'11 FORMULAS'!$C$4,IF(B18='11 FORMULAS'!$B$6,'11 FORMULAS'!$C$6,IF(B18='11 FORMULAS'!$B$8,'11 FORMULAS'!$C$8,IF(B18='11 FORMULAS'!$B$10,'11 FORMULAS'!$C$10,"")))) | E18: =+IFERROR(VLOOKUP(B18,Tabla3[],2,0),"") | K18: =(CONCATENATE(Tabla1[[#This Row],[¿QUÉ? IMPACTO]]," ",Tabla1[[#This Row],[¿CÓMO? CAUSA INMEDIATA (Iniciar con la palabra por)]]," "," ",Tabla1[[#This Row],[¿PORQUÉ? CAUSA RAÍZ (Iniciar con debido a/a causa de)]]))
A19: R11 | D19: =+IF(B19='11 FORMULAS'!$B$4,'11 FORMULAS'!$C$4,IF(B19='11 FORMULAS'!$B$6,'11 FORMULAS'!$C$6,IF(B19='11 FORMULAS'!$B$8,'11 FORMULAS'!$C$8,IF(B19='11 FORMULAS'!$B$10,'11 FORMULAS'!$C$10,"")))) | E19: =+IFERROR(VLOOKUP(B19,Tabla3[],2,0),"") | K19: =(CONCATENATE(Tabla1[[#This Row],[¿QUÉ? IMPACTO]]," ",Tabla1[[#This Row],[¿CÓMO? CAUSA INMEDIATA (Iniciar con la palabra por)]]," "," ",Tabla1[[#This Row],[¿PORQUÉ? CAUSA RAÍZ (Iniciar con debido a/a causa de)]]))
A20: R12 | D20: =+IF(B20='11 FORMULAS'!$B$4,'11 FORMULAS'!$C$4,IF(B20='11 FORMULAS'!$B$6,'11 FORMULAS'!$C$6,IF(B20='11 FORMULAS'!$B$8,'11 FORMULAS'!$C$8,IF(B20='11 FORMULAS'!$B$10,'11 FORMULAS'!$C$10,"")))) | E20: =+IFERROR(VLOOKUP(B20,Tabla3[],2,0),"") | K20: =(CONCATENATE(Tabla1[[#This Row],[¿QUÉ? IMPACTO]]," ",Tabla1[[#This Row],[¿CÓMO? CAUSA INMEDIATA (Iniciar con la palabra por)]]," "," ",Tabla1[[#This Row],[¿PORQUÉ? CAUSA RAÍZ (Iniciar con debido a/a causa de)]]))
A21: R13 | D21: =+IF(B21='11 FORMULAS'!$B$4,'11 FORMULAS'!$C$4,IF(B21='11 FORMULAS'!$B$6,'11 FORMULAS'!$C$6,IF(B21='11 FORMULAS'!$B$8,'11 FORMULAS'!$C$8,IF(B21='11 FORMULAS'!$B$10,'11 FORMULAS'!$C$10,"")))) | E21: =+IFERROR(VLOOKUP(B21,Tabla3[],2,0),"") | K21: =(CONCATENATE(Tabla1[[#This Row],[¿QUÉ? IMPACTO]]," ",Tabla1[[#This Row],[¿CÓMO? CAUSA INMEDIATA (Iniciar con la palabra por)]]," "," ",Tabla1[[#This Row],[¿PORQUÉ? CAUSA RAÍZ (Iniciar con debido a/a causa de)]]))
A22: R14 | D22: =+IF(B22='11 FORMULAS'!$B$4,'11 FORMULAS'!$C$4,IF(B22='11 FORMULAS'!$B$6,'11 FORMULAS'!$C$6,IF(B22='11 FORMULAS'!$B$8,'11 FORMULAS'!$C$8,IF(B22='11 FORMULAS'!$B$10,'11 FORMULAS'!$C$10,"")))) | E22: =+IFERROR(VLOOKUP(B22,Tabla3[],2,0),"") | K22: =(CONCATENATE(Tabla1[[#This Row],[¿QUÉ? IMPACTO]]," ",Tabla1[[#This Row],[¿CÓMO? CAUSA INMEDIATA (Iniciar con la palabra por)]]," "," ",Tabla1[[#This Row],[¿PORQUÉ? CAUSA RAÍZ (Iniciar con debido a/a causa de)]]))
A23: R15 | D23: =+IF(B23='11 FORMULAS'!$B$4,'11 FORMULAS'!$C$4,IF(B23='11 FORMULAS'!$B$6,'11 FORMULAS'!$C$6,IF(B23='11 FORMULAS'!$B$8,'11 FORMULAS'!$C$8,IF(B23='11 FORMULAS'!$B$10,'11 FORMULAS'!$C$10,"")))) | E23: =+IFERROR(VLOOKUP(B23,Tabla3[],2,0),"") | K23: =(CONCATENATE(Tabla1[[#This Row],[¿QUÉ? IMPACTO]]," ",Tabla1[[#This Row],[¿CÓMO? CAUSA INMEDIATA (Iniciar con la palabra por)]]," "," ",Tabla1[[#This Row],[¿PORQUÉ? CAUSA RAÍZ (Iniciar con debido a/a causa de)]]))
A24: R16 | D24: =+IF(B24='11 FORMULAS'!$B$4,'11 FORMULAS'!$C$4,IF(B24='11 FORMULAS'!$B$6,'11 FORMULAS'!$C$6,IF(B24='11 FORMULAS'!$B$8,'11 FORMULAS'!$C$8,IF(B24='11 FORMULAS'!$B$10,'11 FORMULAS'!$C$10,"")))) | E24: =+IFERROR(VLOOKUP(B24,Tabla3[],2,0),"") | K24: =(CONCATENATE(Tabla1[[#This Row],[¿QUÉ? IMPACTO]]," ",Tabla1[[#This Row],[¿CÓMO? CAUSA INMEDIATA (Iniciar con la palabra por)]]," "," ",Tabla1[[#This Row],[¿PORQUÉ? CAUSA RAÍZ (Iniciar con debido a/a causa de)]]))
A25: R17 | D25: =+IF(B25='11 FORMULAS'!$B$4,'11 FORMULAS'!$C$4,IF(B25='11 FORMULAS'!$B$6,'11 FORMULAS'!$C$6,IF(B25='11 FORMULAS'!$B$8,'11 FORMULAS'!$C$8,IF(B25='11 FORMULAS'!$B$10,'11 FORMULAS'!$C$10,"")))) | E25: =+IFERROR(VLOOKUP(B25,Tabla3[],2,0),"") | K25: =(CONCATENATE(Tabla1[[#This Row],[¿QUÉ? IMPACTO]]," ",Tabla1[[#This Row],[¿CÓMO? CAUSA INMEDIATA (Iniciar con la palabra por)]]," "," ",Tabla1[[#This Row],[¿PORQUÉ? CAUSA RAÍZ (Iniciar con debido a/a causa de)]]))
... A28: R20 | D28: =+IF(B28='11 FORMULAS'!$B$4,'11 FORMULAS'!$C$4,IF(B28='11 FORMULAS'!$B$6,'11 FORMULAS'!$C$6,IF(B28='11 FORMULAS'!$B$8,'11 FORMULAS'!$C$8,IF(B28='11 FORMULAS'!$B$10,'11 FORMULAS'!$C$10,"")))) | E28: =+IFERROR(VLOOKUP(B28,Tabla3[],2,0),"") | K28: =(CONCATENATE(Tabla1[[#This Row],[¿QUÉ? IMPACTO]]," ",Tabla1[[#This Row],[¿CÓMO? CAUSA INMEDIATA (Iniciar con la palabra por)]]," "," ",Tabla1[[#This Row],[¿PORQUÉ? CAUSA RAÍZ (Iniciar con debido a/a causa de)]]))

Sheet H1
A1: FACTOR | B1: FUENTE GENERADORA | C1: TIPOLOGÍA | D1: ¿QUÉ IMPACTO | E1: CONCATENAR PARA CALIFICAR ECONOMICO/REPUTACIONAL | F1: CONCATENAR PARA DETERMINAR LA LISTA DE IMPACTOS | G1: PARA LA LISTA DE IMPACTO | H1: Economico | I1: Reputacional | J1: Niveles | O1: FACTOR DE RIESGO | P1: SELECCIONE FUENTE GENERADORA DEL EVENTO PARA TIPO E,F,G | Q1: TIPOLOGÍA seleccionado en la hoja 2 Contexto | R1: ¿QUÉ? IMPACTO seleccionado en la hoja 2 Contexto | S1: concatenar lo que viene de la hoja 2 CONTEXTO para calificar economica / reputacional | T1: CONCATENAR PARA LA LISTA DE IMPACTO
A2: Talento_humano | B2: Fraude interno | C2: Integridad_Pública_Corrupción | D2: Posibilidad de pérdida económica | E2: =CONCATENATE(A2,C2,D2) -> Talento_humanoIntegridad_Pública_CorrupciónPosibilidad de pérdida económica | F2: =CONCATENATE(A2,C2) -> Talento_humanoIntegridad_Pública_Corrupción | G2: TH_FI_CORRUPCION | H2: Afectación_Económica | I2: Reputacional | J2: Todos los niveles / De medio a Catastrófico | L2: RIESGO 1 | M2: =IFERROR(VLOOKUP($T2,$F$2:$F$193,1,0),0) -> 0 | N2: =IFERROR(VLOOKUP($S2,$E$2:$E$193,1,0),0) -> 0 | O2: ='2 CONTEXTO E IDENTIFICACIÓN'!B9 -> Integridad_Pública_LA_FT_FP | P2: ='2 CONTEXTO E IDENTIFICACIÓN'!C9 -> Contrapartes de la entidad (naturales o jurídicas) | Q2: ='2 CONTEXTO E IDENTIFICACIÓN'!F9 -> Seguridad_Información | R2: ='2 CONTEXTO E IDENTIFICACIÓN'!H9 -> Posibilidad de perdida de Disponibilidad, confidencialidad e integridad de la información | S2: =CONCATENATE(O2,Q2,R2) -> Integridad_Pública_LA_FT_FPSeguridad_InformaciónPosibilidad de perdida de Disponibilidad, confidencialidad e integridad de la información | T2: =CONCATENATE(O2,Q2) -> Integridad_Pública_LA_FT_FPSeguridad_Información | U2: N/A | V2: Posibilidad de efecto dañoso sobre bienes de uso fiscal
A3: Talento_humano | B3: Fraude interno | C3: Integridad_Pública_Corrupción | D3: Posibilidad de pérdida reputacional | E3: =CONCATENATE(A3,C3,D3) -> Talento_humanoIntegridad_Pública_CorrupciónPosibilidad de pérdida reputacional | F3: =CONCATENATE(A3,C3) -> Talento_humanoIntegridad_Pública_Corrupción | G3: TH_FI_CORRUPCION | H3: NO_APLICA | I3: Reputacional | J3: De medio a Catastrófico | L3: RIESGO 2 | M3: =IFERROR(VLOOKUP($T3,$F$2:$F$193,1,0),0) -> 0 | N3: =IFERROR(VLOOKUP($S3,$E$2:$E$193,1,0),0) -> 0 | O3: ='2 CONTEXTO E IDENTIFICACIÓN'!B10 -> 0 | P3: ='2 CONTEXTO E IDENTIFICACIÓN'!C10 -> 0 | Q3: ='2 CONTEXTO E IDENTIFICACIÓN'!F10 -> Seguridad_Información | R3: ='2 CONTEXTO E IDENTIFICACIÓN'!H10 -> Posibilidad de perdida de Disponibilidad, confidencialidad e integridad de la información | S3: =CONCATENATE(O3,Q3,R3) -> 0Seguridad_InformaciónPosibilidad de perdida de Disponibilidad, confidencialidad e integridad de la información | T3: =CONCATENATE(O3,Q3) -> 0Seguridad_Información
A4: Talento_humano | B4: Fraude interno | C4: Integridad_Pública_Corrupción | D4: Posibilidad de pérdida económica y reputacional | E4: =CONCATENATE(A4,C4,D4) -> Talento_humanoIntegridad_Pública_CorrupciónPosibilidad de pérdida económica y reputacional | F4: =CONCATENATE(A4,C4) -> Talento_humanoIntegridad_Pública_Corrupción | G4: TH_FI_CORRUPCION | H4: Afectación_Económica | I4: Reputacional | J4: Todos los niveles / De medio a Catastrófico | L4: RIESGO 3 | M4: =IFERROR(VLOOKUP($T4,$F$2:$F$193,1,0),0) -> 0 | N4: =IFERROR(VLOOKUP($S4,$E$2:$E$193,1,0),0) -> 0 | O4: ='2 CONTEXTO E IDENTIFICACIÓN'!B11 -> 0 | P4: ='2 CONTEXTO E IDENTIFICACIÓN'!C11 -> 0 | Q4: ='2 CONTEXTO E IDENTIFICACIÓN'!F11 -> Seguridad_Información | R4: ='2 CONTEXTO E IDENTIFICACIÓN'!H11 -> Posibilidad de perdida de Disponibilidad, confidencialidad e integridad de la información | S4: =CONCATENATE(O4,Q4,R4) -> 0Seguridad_InformaciónPosibilidad de perdida de Disponibilidad, confidencialidad e integridad de la información | T4: =CONCATENATE(O4,Q4) -> 0Seguridad_Información
A5: Talento_humano | B5: Soborno entrante | C5: Integridad_Pública_Corrupción | D5: Afectación económica por Soborno Entrante | E5: =CONCATENATE(A5,C5,D5) -> Talento_humanoIntegridad_Pública_CorrupciónAfectación económica por Soborno Entrante | F5: =CONCATENATE(A5,C5) -> Talento_humanoIntegridad_Pública_Corrupción | G5: TH_SE_CORRUPCION | H5: Afectación_Económica | I5: Reputacional | J5: Todos los niveles / De medio a Catastrófico | L5: RIESGO 4 | M5: =IFERROR(VLOOKUP($T5,$F$2:$F$193,1,0),0) -> 0 | N5: =IFERROR(VLOOKUP($S5,$E$2:$E$193,1,0),0) -> 0 | O5: ='2 CONTEXTO E IDENTIFICACIÓN'!B12 -> 0 | P5: ='2 CONTEXTO E IDENTIFICACIÓN'!C12 -> 0 | Q5: ='2 CONTEXTO E IDENTIFICACIÓN'!F12 -> Seguridad_Información | R5: ='2 CONTEXTO E IDENTIFICACIÓN'!H12 -> Posibilidad de perdida de Disponibilidad, confidencialidad e integridad de la información | S5: =CONCATENATE(O5,Q5,R5) -> 0Seguridad_InformaciónPosibilidad de perdida de Disponibilidad, confidencialidad e integridad de la información | T5: =CONCATENATE(O5,Q5) -> 0Seguridad_Información
A6: Talento_humano | B6: Soborno entrante | C6: Integridad_Pública_Corrupción | D6: Afectación reputacional por Soborno Entrante | E6: =CONCATENATE(A6,C6,D6) -> Talento_humanoIntegridad_Pública_CorrupciónAfectación reputacional por Soborno Entrante | F6: =CONCATENATE(A6,C6) -> Talento_humanoIntegridad_Pública_Corrupción | G6: TH_SE_CORRUPCION | H6: NO_APLICA | I6: Reputacional | J6: De medio a Catastrófico | L6: RIESGO 5 | M6: =IFERROR(VLOOKUP($T6,$F$2:$F$193,1,0),0) -> 0 | N6: =IFERROR(VLOOKUP($S6,$E$2:$E$193,1,0),0) -> 0 | O6: ='2 CONTEXTO E IDENTIFICACIÓN'!B13 -> 0 | P6: ='2 CONTEXTO E IDENTIFICACIÓN'!C13 -> 0 | Q6: ='2 CONTEXTO E IDENTIFICACIÓN'!F13 -> Seguridad_Información | R6: ='2 CONTEXTO E IDENTIFICACIÓN'!H13 -> Posibilidad de perdida de disponibilidad e integridad de la información | S6: =CONCATENATE(O6,Q6,R6) -> 0Seguridad_InformaciónPosibilidad de perdida de disponibilidad e integridad de la información | T6: =CONCATENATE(O6,Q6) -> 0Seguridad_Información
A7: Talento_humano | B7: Soborno entrante | C7: Integridad_Pública_Corrupción | D7: Afectación económica y reputacional por Soborno Entrante | E7: =CONCATENATE(A7,C7,D7) -> Talento_humanoIntegridad_Pública_CorrupciónAfectación económica y reputacional por Soborno Entrante | F7: =CONCATENATE(A7,C7) -> Talento_humanoIntegridad_Pública_Corrupción | G7: TH_SE_CORRUPCION | H7: Afectación_Económica | I7: Reputacional | J7: Todos los niveles / De medio a Catastrófico | L7: RIESGO 6 | M7: =IFERROR(VLOOKUP($T7,$F$2:$F$193,1,0),0) -> 0 | N7: =IFERROR(VLOOKUP($S7,$E$2:$E$193,1,0),0) -> 0 | O7: ='2 CONTEXTO E IDENTIFICACIÓN'!B14 -> 0 | P7: ='2 CONTEXTO E IDENTIFICACIÓN'!C14 -> 0 | Q7: ='2 CONTEXTO E IDENTIFICACIÓN'!F14 -> 0 | R7: ='2 CONTEXTO E IDENTIFICACIÓN'!H14 -> 0 | S7: =CONCATENATE(O7,Q7,R7) -> 000 | T7: =CONCATENATE(O7,Q7) -> 00
A8: Talento_humano | B8: Soborno saliente | C8: Integridad_Pública_Corrupción | D8: Afectación económica por Soborno Saliente | E8: =CONCATENATE(A8,C8,D8) -> Talento_humanoIntegridad_Pública_CorrupciónAfectación económica por Soborno Saliente | F8: =CONCATENATE(A8,C8) -> Talento_humanoIntegridad_Pública_Corrupción | G8: TH_SS_CORRUPCION | H8: Afectación_Económica | I8: Reputacional | J8: Todos los niveles / De medio a Catastrófico | L8: RIESGO 7 | M8: =IFERROR(VLOOKUP($T8,$F$2:$F$193,1,0),0) -> 0 | N8: =IFERROR(VLOOKUP($S8,$E$2:$E$193,1,0),0) -> 0 | O8: ='2 CONTEXTO E IDENTIFICACIÓN'!B15 -> 0 | P8: ='2 CONTEXTO E IDENTIFICACIÓN'!C15 -> 0 | Q8: ='2 CONTEXTO E IDENTIFICACIÓN'!F15 -> 0 | R8: ='2 CONTEXTO E IDENTIFICACIÓN'!H15 -> 0 | S8: =CONCATENATE(O8,Q8,R8) -> 000 | T8: =CONCATENATE(O8,Q8) -> 00
A9: Talento_humano | B9: Soborno saliente | C9: Integridad_Pública_Corrupción | D9: Afectación reputacional por Soborno Saliente | E9: =CONCATENATE(A9,C9,D9) -> Talento_humanoIntegridad_Pública_CorrupciónAfectación reputacional por Soborno Saliente | F9: =CONCATENATE(A9,C9) -> Talento_humanoIntegridad_Pública_Corrupción | G9: TH_SS_CORRUPCION | H9: NO_APLICA | I9: Reputacional | J9: De medio a Catastrófico | L9: RIESGO 8 | M9: =IFERROR(VLOOKUP($T9,$F$2:$F$193,1,0),0) -> 0 | N9: =IFERROR(VLOOKUP($S9,$E$2:$E$193,1,0),0) -> 0 | O9: ='2 CONTEXTO E IDENTIFICACIÓN'!B16 -> 0 | P9: ='2 CONTEXTO E IDENTIFICACIÓN'!C16 -> 0 | Q9: ='2 CONTEXTO E IDENTIFICACIÓN'!F16 -> 0 | R9: ='2 CONTEXTO E IDENTIFICACIÓN'!H16 -> 0 | S9: =CONCATENATE(O9,Q9,R9) -> 000 | T9: =CONCATENATE(O9,Q9) -> 00
A10: Talento_humano | B10: Soborno saliente | C10: Integridad_Pública_Corrupción | D10: Afectación económica y reputacional por Soborno Saliente | E10: =CONCATENATE(A10,C10,D10) -> Talento_humanoIntegridad_Pública_CorrupciónAfectación económica y reputacional por Soborno Saliente | F10: =CONCATENATE(A10,C10) -> Talento_humanoIntegridad_Pública_Corrupción | G10: TH_SS_CORRUPCION | H10: Afectación_Económica | I10: Reputacional | J10: Todos los niveles / De medio a Catastrófico | L10: RIESGO 9 | M10: =IFERROR(VLOOKUP($T10,$F$2:$F$193,1,0),0) -> 0 | N10: =IFERROR(VLOOKUP($S10,$E$2:$E$193,1,0),0) -> 0 | O10: ='2 CONTEXTO E IDENTIFICACIÓN'!B17 -> 0 | P10: ='2 CONTEXTO E IDENTIFICACIÓN'!C17 -> 0 | Q10: ='2 CONTEXTO E IDENTIFICACIÓN'!F17 -> 0 | R10: ='2 CONTEXTO E IDENTIFICACIÓN'!H17 -> 0 | S10: =CONCATENATE(O10,Q10,R10) -> 000 | T10: =CONCATENATE(O10,Q10) -> 00
A11: Talento_humano | B11: Gestión inadecuada de conflicto de Intereses | C11: Integridad_Pública_Corrupción | D11: Afectación económica por Conflicto de interés | E11: =CONCATENATE(A11,C11,D11) -> Talento_humanoIntegridad_Pública_CorrupciónAfectación económica por Conflicto de interés | F11: =CONCATENATE(A11,C11) -> Talento_humanoIntegridad_Pública_Corrupción | G11: TH_CI_CORRUPCION | H11: Afectación_Económica | I11: Reputacional | J11: Todos los niveles / De medio a Catastrófico | L11: RIESGO 10 | M11: =IFERROR(VLOOKUP($T11,$F$2:$F$193,1,0),0) -> 0 | N11: =IFERROR(VLOOKUP($S11,$E$2:$E$193,1,0),0) -> 0 | O11: ='2 CONTEXTO E IDENTIFICACIÓN'!B18 -> 0 | P11: ='2 CONTEXTO E IDENTIFICACIÓN'!C18 -> 0 | Q11: ='2 CONTEXTO E IDENTIFICACIÓN'!F18 -> 0 | R11: ='2 CONTEXTO E IDENTIFICACIÓN'!H18 -> 0 | S11: =CONCATENATE(O11,Q11,R11) -> 000 | T11: =CONCATENATE(O11,Q11) -> 00
A12: Talento_humano | B12: Gestión inadecuada de conflicto de Intereses | C12: Integridad_Pública_Corrupción | D12: Afectación reputacional por Conflicto de interés | E12: =CONCATENATE(A12,C12,D12) -> Talento_humanoIntegridad_Pública_CorrupciónAfectación reputacional por Conflicto de interés | F12: =CONCATENATE(A12,C12) -> Talento_humanoIntegridad_Pública_Corrupción | G12: TH_CI_CORRUPCION | H12: NO_APLICA | I12: Reputacional | J12: De medio a Catastrófico | L12: RIESGO 11 | M12: =IFERROR(VLOOKUP($T12,$F$2:$F$193,1,0),0) -> 0 | N12: =IFERROR(VLOOKUP($S12,$E$2:$E$193,1,0),0) -> 0 | O12: ='2 CONTEXTO E IDENTIFICACIÓN'!B19 -> 0 | P12: ='2 CONTEXTO E IDENTIFICACIÓN'!C19 -> 0 | Q12: ='2 CONTEXTO E IDENTIFICACIÓN'!F19 -> 0 | R12: ='2 CONTEXTO E IDENTIFICACIÓN'!H19 -> 0 | S12: =CONCATENATE(O12,Q12,R12) -> 000 | T12: =CONCATENATE(O12,Q12) -> 00
A13: Talento_humano | B13: Gestión inadecuada de conflicto de Intereses | C13: Integridad_Pública_Corrupción | D13: Afectación económica y reputacional por Conflicto de interés | E13: =CONCATENATE(A13,C13,D13) -> Talento_humanoIntegridad_Pública_CorrupciónAfectación económica y reputacional por Conflicto de interés | F13: =CONCATENATE(A13,C13) -> Talento_humanoIntegridad_Pública_Corrupción | G13: TH_CI_CORRUPCION | H13: Afectación_Económica | I13: Reputacional | J13: Todos los niveles / De medio a Catastrófico | L13: RIESGO 12 | M13: =IFERROR(VLOOKUP($T13,$F$2:$F$193,1,0),0) -> 0 | N13: =IFERROR(VLOOKUP($S13,$E$2:$E$193,1,0),0) -> 0 | O13: ='2 CONTEXTO E IDENTIFICACIÓN'!B20 -> 0 | P13: ='2 CONTEXTO E IDENTIFICACIÓN'!C20 -> 0 | Q13: ='2 CONTEXTO E IDENTIFICACIÓN'!F20 -> 0 | R13: ='2 CONTEXTO E IDENTIFICACIÓN'!H20 -> 0 | S13: =CONCATENATE(O13,Q13,R13) -> 000 | T13: =CONCATENATE(O13,Q13) -> 00
A14: Talento_humano | B14: Corrupción | C14: Integridad_Pública_Corrupción | D14: Afectación económica por Corrupción | E14: =CONCATENATE(A14,C14,D14) -> Talento_humanoIntegridad_Pública_CorrupciónAfectación económica por Corrupción | F14: =CONCATENATE(A14,C14) -> Talento_humanoIntegridad_Pública_Corrupción | G14: TH_C_CORRUPCION | H14: Afectación_Económica | I14: Reputacional | J14: Todos los niveles / De medio a Catastrófico | L14: RIESGO 13 | M14: =IFERROR(VLOOKUP($T14,$F$2:$F$193,1,0),0) -> 0 | N14: =IFERROR(VLOOKUP($S14,$E$2:$E$193,1,0),0) -> 0 | O14: ='2 CONTEXTO E IDENTIFICACIÓN'!B21 -> 0 | P14: ='2 CONTEXTO E IDENTIFICACIÓN'!C21 -> 0 | Q14: ='2 CONTEXTO E IDENTIFICACIÓN'!F21 -> 0 | R14: ='2 CONTEXTO E IDENTIFICACIÓN'!H21 -> 0 | S14: =CONCATENATE(O14,Q14,R14) -> 000 | T14: =CONCATENATE(O14,Q14) -> 00
... A21: Integridad_Pública_LA_FT_FP | B21: Contrapartes de la entidad (naturales o jurídicas) | C21: Integridad_Pública_LA_FT_FP | D21: Afectación económica por consecuencias legales | E21: =CONCATENATE(A21,C21,D21) -> Integridad_Pública_LA_FT_FPIntegridad_Pública_LA_FT_FPAfectación económica por consecuencias legales | F21: =CONCATENATE(A21,C21) -> Integridad_Pública_LA_FT_FPIntegridad_Pública_LA_FT_FP | G21: IP_CONTRAPARTES_LA_FT_FP | H21: Afectación_Económica | I21: Reputacional | J21: Todos los niveles / De medio a Catastrófico | L21: RIESGO 20 | M21: =IFERROR(VLOOKUP($T21,$F$2:$F$193,1,0),0) -> 0 | N21: =IFERROR(VLOOKUP($S21,$E$2:$E$193,1,0),0) -> 0 | O21: ='2 CONTEXTO E IDENTIFICACIÓN'!B28 -> 0 | P21: ='2 CONTEXTO E IDENTIFICACIÓN'!C28 -> 0 | Q21: ='2 CONTEXTO E IDENTIFICACIÓN'!F28 -> 0 | R21: ='2 CONTEXTO E IDENTIFICACIÓN'!H28 -> 0 | S21: =CONCATENATE(O21,Q21,R21) -> 000 | T21: =CONCATENATE(O21,Q21) -> 00
A22: Integridad_Pública_LA_FT_FP | B22: Contrapartes de la entidad (naturales o jurídicas) | C22: Integridad_Pública_LA_FT_FP | D22: Afectación económica operativa o de contagio | E22: =CONCATENATE(A22,C22,D22) -> Integridad_Pública_LA_FT_FPIntegridad_Pública_LA_FT_FPAfectación económica operativa o de contagio | F22: =CONCATENATE(A22,C22) -> Integridad_Pública_LA_FT_FPIntegridad_Pública_LA_FT_FP | G22: IP_CONTRAPARTES_LA_FT_FP | H22: Afectación_Económica | I22: Reputacional | J22: Todos los niveles / De medio a Catastrófico
A23: Integridad_Pública_LA_FT_FP | B23: Contrapartes de la entidad (naturales o jurídicas) | C23: Integridad_Pública_LA_FT_FP | D23: Afectación reputacional | E23: =CONCATENATE(A23,C23,D23) -> Integridad_Pública_LA_FT_FPIntegridad_Pública_LA_FT_FPAfectación reputacional | F23: =CONCATENATE(A23,C23) -> Integridad_Pública_LA_FT_FPIntegridad_Pública_LA_FT_FP | G23: IP_CONTRAPARTES_LA_FT_FP | H23: NO_APLICA | I23: Reputacional | J23: De medio a Catastrófico | O23: =VLOOKUP('H1'!$T4,'H1'!$F$1:$G$193,2,0) -> #N/A
A24: Integridad_Pública_LA_FT_FP | B24: Contrapartes de la entidad (naturales o jurídicas) | C24: Integridad_Pública_LA_FT_FP | D24: Afectación económica y reputacional por Corrupción | E24: =CONCATENATE(A24,C24,D24) -> Integridad_Pública_LA_FT_FPIntegridad_Pública_LA_FT_FPAfectación económica y reputacional por Corrupción | F24: =CONCATENATE(A24,C24) -> Integridad_Pública_LA_FT_FPIntegridad_Pública_LA_FT_FP | G24: IP_CONTRAPARTES_LA_FT_FP | H24: Afectación_Económica | I24: Reputacional | J24: Todos los niveles / De medio a Catastrófico
A25: Integridad_Pública_LA_FT_FP | B25: Productos (bienes o servicios) que oferta/requiere | C25: Integridad_Pública_LA_FT_FP | D25: Afectación económica | E25: =CONCATENATE(A25,C25,D25) -> Integridad_Pública_LA_FT_FPIntegridad_Pública_LA_FT_FPAfectación económica | F25: =CONCATENATE(A25,C25) -> Integridad_Pública_LA_FT_FPIntegridad_Pública_LA_FT_FP | G25: IP_PRODUCTOS__LA_FT_FP | H25: Afectación_Económica | I25: Reputacional | J25: Todos los niveles / De medio a Catastrófico
A26: Integridad_Pública_LA_FT_FP | B26: Productos (bienes o servicios) que oferta/requiere | C26: Integridad_Pública_LA_FT_FP | D26: Afectación económica por consecuencias legales | E26: =CONCATENATE(A26,C26,D26) -> Integridad_Pública_LA_FT_FPIntegridad_Pública_LA_FT_FPAfectación económica por consecuencias legales | F26: =CONCATENATE(A26,C26) -> Integridad_Pública_LA_FT_FPIntegridad_Pública_LA_FT_FP | G26: IP_PRODUCTOS__LA_FT_FP | H26: Afectación_Económica | I26: Reputacional | J26: Todos los niveles / De medio a Catastrófico
A27: Integridad_Pública_LA_FT_FP | B27: Productos (bienes o servicios) que oferta/requiere | C27: Integridad_Pública_LA_FT_FP | D27: Afectación económica operativa o de contagio | E27: =CONCATENATE(A27,C27,D27) -> Integridad_Pública_LA_FT_FPIntegridad_Pública_LA_FT_FPAfectación económica operativa o de contagio | F27: =CONCATENATE(A27,C27) -> Integridad_Pública_LA_FT_FPIntegridad_Pública_LA_FT_FP | G27: IP_PRODUCTOS__LA_FT_FP | H27: Afectación_Económica | I27: Reputacional | J27: Todos los niveles / De medio a Catastrófico
A28: Integridad_Pública_LA_FT_FP | B28: Productos (bienes o servicios) que oferta/requiere | C28: Integridad_Pública_LA_FT_FP | D28: Afectación reputacional | E28: =CONCATENATE(A28,C28,D28) -> Integridad_Pública_LA_FT_FPIntegridad_Pública_LA_FT_FPAfectación reputacional | F28: =CONCATENATE(A28,C28) -> Integridad_Pública_LA_FT_FPIntegridad_Pública_LA_FT_FP | G28: IP_PRODUCTOS__LA_FT_FP | H28: NO_APLICA | I28: Reputacional | J28: De medio a Catastrófico
A29: Integridad_Pública_LA_FT_FP | B29: Productos (bienes o servicios) que oferta/requiere | C29: Integridad_Pública_LA_FT_FP | D29: Afectación económica y reputacional por Corrupción | E29: =CONCATENATE(A29,C29,D29) -> Integridad_Pública_LA_FT_FPIntegridad_Pública_LA_FT_FPAfectación económica y reputacional por Corrupción | F29: =CONCATENATE(A29,C29) -> Integridad_Pública_LA_FT_FPIntegridad_Pública_LA_FT_FP | G29: IP_PRODUCTOS__LA_FT_FP | H29: Afectación_Económica | I29: Reputacional | J29: Todos los niveles / De medio a Catastrófico
A30: Integridad_Pública_LA_FT_FP | B30: Canales utilizados para la operación | C30: Integridad_Pública_LA_FT_FP | D30: Afectación económica | E30: =CONCATENATE(A30,C30,D30) -> Integridad_Pública_LA_FT_FPIntegridad_Pública_LA_FT_FPAfectación económica | F30: =CONCATENATE(A30,C30) -> Integridad_Pública_LA_FT_FPIntegridad_Pública_LA_FT_FP | G30: IP_CANALES_LA_FT_FP | H30: Afectación_Económica | I30: Reputacional | J30: Todos los niveles / De medio a Catastrófico
A31: Integridad_Pública_LA_FT_FP | B31: Canales utilizados para la operación | C31: Integridad_Pública_LA_FT_FP | D31: Afectación económica por consecuencias legales | E31: =CONCATENATE(A31,C31,D31) -> Integridad_Pública_LA_FT_FPIntegridad_Pública_LA_FT_FPAfectación económica por consecuencias legales | F31: =CONCATENATE(A31,C31) -> Integridad_Pública_LA_FT_FPIntegridad_Pública_LA_FT_FP | G31: IP_CANALES_LA_FT_FP | H31: Afectación_Económica | I31: Reputacional | J31: Todos los niveles / De medio a Catastrófico
A32: Integridad_Pública_LA_FT_FP | B32: Canales utilizados para la operación | C32: Integridad_Pública_LA_FT_FP | D32: Afectación económica operativa o de contagio | E32: =CONCATENATE(A32,C32,D32) -> Integridad_Pública_LA_FT_FPIntegridad_Pública_LA_FT_FPAfectación económica operativa o de contagio | F32: =CONCATENATE(A32,C32) -> Integridad_Pública_LA_FT_FPIntegridad_Pública_LA_FT_FP | G32: IP_CANALES_LA_FT_FP | H32: Afectación_Económica | I32: Reputacional | J32: Todos los niveles / De medio a Catastrófico
A33: Integridad_Pública_LA_FT_FP | B33: Canales utilizados para la operación | C33: Integridad_Pública_LA_FT_FP | D33: Afectación reputacional | E33: =CONCATENATE(A33,C33,D33) -> Integridad_Pública_LA_FT_FPIntegridad_Pública_LA_FT_FPAfectación reputacional | F33: =CONCATENATE(A33,C33) -> Integridad_Pública_LA_FT_FPIntegridad_Pública_LA_FT_FP | G33: IP_CANALES_LA_FT_FP | H33: NO_APLICA | I33: Reputacional | J33: De medio a Catastrófico
A34: Integridad_Pública_LA_FT_FP | B34: Canales utilizados para la operación | C34: Integridad_Pública_LA_FT_FP | D34: Afectación económica y reputacional por Corrupción | E34: =CONCATENATE(A34,C34,D34) -> Integridad_Pública_LA_FT_FPIntegridad_Pública_LA_FT_FPAfectación económica y reputacional por Corrupción | F34: =CONCATENATE(A34,C34) -> Integridad_Pública_LA_FT_FPIntegridad_Pública_LA_FT_FP | G34: IP_CANALES_LA_FT_FP | H34: Afectación_Económica | I34: Reputacional | J34: Todos los niveles / De medio a Catastrófico
A35: Integridad_Pública_LA_FT_FP | B35: Jurisdicciones (nacional o territorial) | C35: Integridad_Pública_LA_FT_FP | D35: Afectación económica | E35: =CONCATENATE(A35,C35,D35) -> Integridad_Pública_LA_FT_FPIntegridad_Pública_LA_FT_FPAfectación económica | F35: =CONCATENATE(A35,C35) -> Integridad_Pública_LA_FT_FPIntegridad_Pública_LA_FT_FP | G35: IP_JURISDICCION_LA_FT_FP | H35: Afectación_Económica | I35: Reputacional | J35: Todos los niveles / De medio a Catastrófico
... A39: Integridad_Pública_LA_FT_FP | B39: Jurisdicciones (nacional o territorial) | C39: Integridad_Pública_LA_FT_FP | D39: Afectación económica y reputacional por Corrupción | E39: =CONCATENATE(A39,C39,D39) -> Integridad_Pública_LA_FT_FPIntegridad_Pública_LA_FT_FPAfectación económica y reputacional por Corrupción | F39: =CONCATENATE(A39,C39) -> Integridad_Pública_LA_FT_FPIntegridad_Pública_LA_FT_FP | G39: IP_JURISDICCION_LA_FT_FP | H39: Afectación_Económica | I39: Reputacional | J39: Todos los niveles / De medio a Catastrófico
A40: Ejecución_administración_de_procesos | B40: Falta de aplicación de los procedimientos | C40: Gestión | D40: Posibilidad de afectación económica | E40: =CONCATENATE(A40,C40,D40) -> Ejecución_administración_de_procesosGestiónPosibilidad de afectación económica | F40: =CONCATENATE(A40,C40) -> Ejecución_administración_de_procesosGestión | G40: Gestión | H40: Afectación_Económica | I40: NO_APLICA | J40: Todos los niveles | O40: =EXACT(M40,$T$2) -> FALSE
A41: Ejecución_administración_de_procesos | B41: Falta de aplicación de los procedimientos | C41: Gestión | D41: Posibilidad de afectación reputacional | E41: =CONCATENATE(A41,C41,D41) -> Ejecución_administración_de_procesosGestiónPosibilidad de afectación reputacional | F41: =CONCATENATE(A41,C41) -> Ejecución_administración_de_procesosGestión | G41: Gestión | H41: NO_APLICA | I41: REPUTACIONAL_EXTENDIDA | J41: Todos los niveles | O41: =EXACT(M41,$T$2) -> FALSE
A42: Ejecución_administración_de_procesos | B42: Falta de aplicación de los procedimientos | C42: Gestión | D42: Posibilidad de afectación económica y reputacional | E42: =CONCATENATE(A42,C42,D42) -> Ejecución_administración_de_procesosGestiónPosibilidad de afectación económica y reputacional | F42: =CONCATENATE(A42,C42) -> Ejecución_administración_de_procesosGestión | G42: Gestión | H42: Afectación_Económica | I42: REPUTACIONAL_EXTENDIDA | J42: Todos los niveles / Todos los niveles | O42: =EXACT(M42,$T$2) -> FALSE
A43: Ejecución_administración_de_procesos | B43: Falta de aplicación de los procedimientos | C43: Fiscal | D43: Posibilidad de efecto dañoso sobre el recurso público | E43: =CONCATENATE(A43,C43,D43) -> Ejecución_administración_de_procesosFiscalPosibilidad de efecto dañoso sobre el recurso público | F43: =CONCATENATE(A43,C43) -> Ejecución_administración_de_procesosFiscal | G43: Fiscal | H43: Afectación_Económica | I43: Reputacional | J43: Todos los niveles / De medio a Catastrófico
A44: Ejecución_administración_de_procesos | B44: Falta de aplicación de los procedimientos | C44: Fiscal | D44: Posibilidad de efecto dañoso sobre bienes de uso público | E44: =CONCATENATE(A44,C44,D44) -> Ejecución_administración_de_procesosFiscalPosibilidad de efecto dañoso sobre bienes de uso público | F44: =CONCATENATE(A44,C44) -> Ejecución_administración_de_procesosFiscal | G44: Fiscal | H44: Afectación_Económica | I44: Reputacional | J44: Todos los niveles / De medio a Catastrófico
A45: Ejecución_administración_de_procesos | B45: Falta de aplicación de los procedimientos | C45: Fiscal | D45: Posibilidad de efecto dañoso sobre bienes de uso fiscal | E45: =CONCATENATE(A45,C45,D45) -> Ejecución_administración_de_procesosFiscalPosibilidad de efecto dañoso sobre bienes de uso fiscal | F45: =CONCATENATE(A45,C45) -> Ejecución_administración_de_procesosFiscal | G45: Fiscal | H45: Afectación_Económica | I45: Reputacional | J45: Todos los niveles / De medio a Catastrófico
A46: Ejecución_administración_de_procesos | B46: Falta de aplicación de los procedimientos | C46: Fiscal | D46: Posibilidad de efecto dañoso sobre el interes patrimonial | E46: =CONCATENATE(A46,C46,D46) -> Ejecución_administración_de_procesosFiscalPosibilidad de efecto dañoso sobre el interes patrimonial | F46: =CONCATENATE(A46,C46) -> Ejecución_administración_de_procesosFiscal | G46: Fiscal | H46: Afectación_Económica | I46: Reputacional | J46: Todos los niveles / De medio a Catastrófico
A47: Ejecución_administración_de_procesos | B47: Falta segregación de funciones | C47: Gestión | D47: Posibilidad de afectación económica | E47: =CONCATENATE(A47,C47,D47) -> Ejecución_administración_de_procesosGestiónPosibilidad de afectación económica | F47: =CONCATENATE(A47,C47) -> Ejecución_administración_de_procesosGestión | G47: Gestión | H47: Afectación_Económica | I47: NO_APLICA | J47: Todos los niveles
A48: Ejecución_administración_de_procesos | B48: Falta segregación de funciones | C48: Gestión | D48: Posibilidad de afectación reputacional | E48: =CONCATENATE(A48,C48,D48) -> Ejecución_administración_de_procesosGestiónPosibilidad de afectación reputacional | F48: =CONCATENATE(A48,C48) -> Ejecución_administración_de_procesosGestión | G48: Gestión | H48: NO_APLICA | I48: REPUTACIONAL_EXTENDIDA | J48: Todos los niveles
A49: Ejecución_administración_de_procesos | B49: Falta segregación de funciones | C49: Gestión | D49: Posibilidad de afectación económica y reputacional | E49: =CONCATENATE(A49,C49,D49) -> Ejecución_administración_de_procesosGestiónPosibilidad de afectación económica y reputacional | F49: =CONCATENATE(A49,C49) -> Ejecución_administración_de_procesosGestión | G49: Gestión | H49: Afectación_Económica | I49: REPUTACIONAL_EXTENDIDA | J49: Todos los niveles / Todos los niveles
A50: Ejecución_administración_de_procesos | B50: Falta segregación de funciones | C50: Fiscal | D50: Posibilidad de efecto dañoso sobre el recurso público | E50: =CONCATENATE(A50,C50,D50) -> Ejecución_administración_de_procesosFiscalPosibilidad de efecto dañoso sobre el recurso público | F50: =CONCATENATE(A50,C50) -> Ejecución_administración_de_procesosFiscal | G50: Fiscal | H50: Afectación_Económica | I50: Reputacional | J50: Todos los niveles / De medio a Catastrófico
A51: Ejecución_administración_de_procesos | B51: Falta segregación de funciones | C51: Fiscal | D51: Posibilidad de efecto dañoso sobre bienes de uso público | E51: =CONCATENATE(A51,C51,D51) -> Ejecución_administración_de_procesosFiscalPosibilidad de efecto dañoso sobre bienes de uso público | F51: =CONCATENATE(A51,C51) -> Ejecución_administración_de_procesosFiscal | G51: Fiscal | H51: Afectación_Económica | I51: Reputacional | J51: Todos los niveles / De medio a Catastrófico
A52: Ejecución_administración_de_procesos | B52: Falta segregación de funciones | C52: Fiscal | D52: Posibilidad de efecto dañoso sobre bienes de uso fiscal | E52: =CONCATENATE(A52,C52,D52) -> Ejecución_administración_de_procesosFiscalPosibilidad de efecto dañoso sobre bienes de uso fiscal | F52: =CONCATENATE(A52,C52) -> Ejecución_administración_de_procesosFiscal | G52: Fiscal | H52: Afectación_Económica | I52: Reputacional | J52: Todos los niveles / De medio a Catastrófico
A53: Ejecución_administración_de_procesos | B53: Falta segregación de funciones | C53: Fiscal | D53: Posibilidad de efecto dañoso sobre el interes patrimonial | E53: =CONCATENATE(A53,C53,D53) -> Ejecución_administración_de_procesosFiscalPosibilidad de efecto dañoso sobre el interes patrimonial | F53: =CONCATENATE(A53,C53) -> Ejecución_administración_de_procesosFiscal | G53: Fiscal | H53: Afectación_Económica | I53: Reputacional | J53: Todos los niveles / De medio a Catastrófico
A54: Ejecución_administración_de_procesos | B54: Errores de grabación, autorización | C54: Gestión | D54: Posibilidad de afectación económica | E54: =CONCATENATE(A54,C54,D54) -> Ejecución_administración_de_procesosGestiónPosibilidad de afectación económica | F54: =CONCATENATE(A54,C54) -> Ejecución_administración_de_procesosGestión | G54: Gestión | H54: Afectación_Económica | I54: NO_APLICA | J54: Todos los niveles
... A193: Evento_externo | B193: Atentados, vandalismo, orden público | C193: Fiscal | D193: Posibilidad de efecto dañoso sobre el interes patrimonial | E193: =CONCATENATE(A193,C193,D193) -> Evento_externoFiscalPosibilidad de efecto dañoso sobre el interes patrimonial | F193: =CONCATENATE(A193,C193) -> Evento_externoFiscal | G193: Fiscal | H193: Afectación_Económica | I193: Reputacional | J193: Todos los niveles / De medio a Catastrófico

Sheet 11 FORMULAS
A1: Esta hoja se utiliza para realizar cálculos en las demás, en ella no se ingresan datos | E1: NO REQUIERE CLAVE PARA DESBLOQUEAR LAS HOJAS
B2: FACTOR DEL RIESGO | E2: Eficiencia | K2: Atributos formalización del control | P2: Afectación o Desplazamiento en la Matriz | S2: Tratamiento | U2: ¿QUÉ? IMPACTO | W2: Estado
A3: TIPO | B3: TIPO | C3: FACTOR DEL RIESGO | E3: Tipo de control | F3: Peso del Control | H3: Implementación | I3: Peso de la implementación | K3: Documentación | L3: Frecuencia | M3: Evidencia | N3: Ejecuión | P3: Tipo de control | Q3: Afecta | S3: Reducir | U3: Posibilidad de pérdida Económica | W3: Sin Iniciar
A4: A_Ejecución_y_Administración_de_procesos | B4: A_Ejecución_y_Administración_de_procesos | C4: Procesos | E4: Preventivo | F4: 0.25 | H4: Automático | I4: 0.25 | K4: Procedimientos | L4: Siempre que se ejecuta la actividad | M4: Con registro manual | N4: Interna | P4: Preventivo | Q4: Probabilidad | S4: Mitigar | U4: Posibilidad de pérdida Reputacional | W4: En proceso
A5: B_Fraude_Externo | E5: Detectivo | F5: 0.15 | H5: Manual | I5: 0.15 | K5: Sistemas de información | L5: Periódicamente (diario, mensual, bimestral, trimestral, semestral). | M5: Con registro electrónico | N5: Externa | P5: Detectivo | Q5: Probabilidad | S5: Transferir | U5: Posibilidad de pérdida Económica y Reputacional | W5: Cerrado
A6: C_Fraude_Interno | B6: B_Fraude_Externo | C6: Evento_Externo | E6: Correctivo | F6: 0.1 | K6: Otros Esquemas | N6: Mixta | P6: Correctivo | Q6: Impacto | S6: Aceptar | U6: Posibilidad de pérdida Reputacional y Económica
A7: D_Fallas_Tecnológicas | S7: Evitar
A8: E_Relaciones_Laborales | B8: C_Fraude_Interno | C8: Talento_Humano
A9: F_Usuarios_Productos_y_Prácticas_Organizacionales
A10: G_Daños_Activos_Físicos | B10: D_Fallas_Tecnológicas | C10: Tecnologías
B12: E_Relaciones_Laborales | C12: Procesos
A13: TIPOLOGÍA | C13: Evento_Externo
A14: Gestión | C14: Talento_Humano
A15: Fiscal | C15: Tecnologías
A16: Seg. de la Información | C16: Infraestructura
A17: Integridad Pùblica - Corrupción
A18: Integridad Pùblica - LA/FT/FP | B18: F_Usuarios_Productos_y_Prácticas_Organizacionales | C18: Procesos
C19: Evento_Externo
C20: Talento_Humano
C21: Tecnologías
C22: Infraestructura
B24: G_Daños_Activos_Físicos | C24: Infraestructura
C25: Evento_Externo
A31: Gestión | B31: Fiscal | C31: Seguridad_Información | D31: Integridad_Pública_Corrupción | E31: Integridad_Pública_LA_FT_FP | F31: Soborno_entrante | G31: Soborno_saliente
A32: Posibilidad de afectación económica | B32: Posibilidad de efecto dañoso sobre el recurso público | C32: Posibilidad de perdida de integridad | D32: Afectación económica por fraude interno | E32: Contrapartes de la entidad (naturales o jurídicas) | F32: Afectación económica por Soborno Entrante | G32: Afectación económica por Soborno Entrante
A33: Posibilidad de afectación reputacional | B33: Posibilidad de efecto dañoso sobre bienes de uso público | C33: Posibilidad de perdida de confidencialidad | D33: Afectación reputacional por fraude interno | E33: Productos (bienes o servicios) que oferta/requiere | F33: Afectación reputacional por Soborno Entrante | G33: Afectación reputacional por Soborno Entrante
A34: Posibilidad de afectación económica y reputacional | B34: Posibilidad de efecto dañoso sobre bienes de uso fiscal | C34: Posibilidad de perdida de disponibilidad | D34: Afectación económica y reputacional por fraude interno | E34: Canales utilizados para la operación | F34: Afectación económica y reputacional por Soborno Entrante | G34: Afectación económica y reputacional por Soborno Entrante
B35: Posibilidad de efecto dañoso sobre el interes patrimonial | C35: Posibilidad de perdida de disponibilidad y confidencialidad de la información | D35: Afectación económica por soborno entrante o saliente | E35: Jurisdicciones (nacional o territorial)
C36: Posibilidad de perdida de disponibilidad e integridad de la información | D36: Afectación económica y reputacional Soborno soborno entrante o saliente
C37: Posibilidad de perdida de confidencialidad e integridad de la información | D37: Afectación reputacional por soborno entrante o saliente
C38: Posibilidad de perdida de Disponibilidad, confidencialidad e integridad de la información | D38: Afectación económica por conflicto de intereses
D39: Afectación reputacional por conflito de interes
D40: Afectación económica y reputacional conflicto de interes
D41: Afectación económica por acto de corrupción
D42: Afectación reputacional por Acto de corrupción
D43: Afectación económica y reputacional Acto de ciorrupción | H43: FACTOR DE RIESGO | I43: Descripción
A44: Ejecución_administración_de_procesos | B44: Integridad_Pública_LA_FT_FP | C44: Talento_Humano | D44: Tecnología | E44: Infraestructura | F44: Evento_externo | H44: Ejecución_administración_de_procesos | I44: Eventos relacionados con la ejecución de los procesos y procedimientos determinados para la operación de la entidad, uso de sistemas de información, por errores en las actividades que deben realizar los servidores de la organización. Estructura organizacional que afecta la capacidad organizacional
A45: Falta de aplicación de los procedimientos | B45: Contrapartes de la entidad (naturales o jurídicas) | C45: Fraude interno | D45: Daño de equipos | E45: Derrumbes | F45: Fraude Externo | H45: Integridad_Pública_LA_FT_FP | I45: Eventos relacionados con transacciones y Operaciones realizadas por un cliente o usuario, que accede o entrega un bien o servicio a la entidad, a través de los canales dispuestos y en una jurisdicción específica.
A46: Falta segregación de funciones | B46: Productos (bienes o servicios) que oferta/requiere | C46: Soborno entrante | D46: Caída de sistemas de información y aplicaciones | E46: Incendios | F46: Suplantación de identidad | H46: Talento_Humano | I46: Eventos relacionados con las conductas o comportamientos de los empleados que afectan la Integridad Pública
A47: Errores de grabación, autorización | B47: Canales utilizados para la operación | C47: Soborno saliente | D47: Caída de redes | E47: Inundaciones | F47: Asalto a la oficina | H47: Tecnología | I47: Eventos relacionados con la infraestructura tecnológica de la entidad.
A48: Errores en cálculos para pagos internos y externos | B48: Jurisdicciones (nacional o territorial) | C48: Gestión inadecuada de conflicto de Intereses | D48: Errores en hardware o software | E48: Daños a activos fijos | F48: Atentados, vandalismo, orden público | H48: Infraestructura | I48: Eventos relacionados con la infraestructura física de la entidad.
A49: Falta de supervisión o interventoría | C49: Corrupción | D49: Errores en programas | H49: Evento_externo | I49: Eventos por situaciones externas que afectan la entidad.
A50: Alta rotación o insuficiencia de personal | C50: Hurto de activos
A51: Acciones contrarias a las leyes o acuerdos de empleo, salud o seguridad en el trabajo
A52: Acciones contrarias a las leyes o acuerdos contractuales
A53: Falta de capacitación y otros temas relacionados con el personal
A56: Características de Eficiencia | C56: Peso | D56: Factor
A57: Tipo | B57: Preventivo | C57: 0.25 | D57: Probabilidad
B58: Detectivo | C58: 0.15 | D58: Probabilidad
B59: Correctivo | C59: 0.1 | D59: Impacto
A60: *Implementación | B60: Automático | C60: 0.25
A61: *Nota: En implementación no se tienen controles semiautomáticos. | B61: Manual | C61: 0.15
A64: Atributos adicionales del control no tienen valoración pero deben cumplir con todos
A65: Características de Eficiencia | C65: Descripción
A66: Documentación | B66: Procedimientos | C66: Basados en la estructura del Modelo de Operación por procesos, despliegue desde cada proceso, sus procedimientos y esquemas asociados, que se encuentren documentados.
B67: Sistemas de información | C67: Sistemas de información de apoyo a la ejecución del control (si existen).
B68: Otros Esquemas | C68: Políticas de operación, manuales o guías específicas.
A69: Frecuencia | B69: Diario | C69: La oportunidad en que se ejecuta el control debe ayudar a prevenir la mitigación del riesgo o a detectar la materialización del riesgo de manera oportuna.
B70: Mensual
B71: Bimestral
B72: Trimestral
B73: Semestral
A74: Evidencia (Trazabilidad de la ejecución) | B74: Con registro manual | C74: Se deja evidencia o rastro de la ejecución del control.
B75: Con registro electrónico
A76: Ejecución (Fuentes de información internas o externas) | B76: Interna | C76: Formatos o registros internos formales.
B77: Externa | C77: Registros externos confiables (extractos bancarios, confirmaciones de autenticidad de documentos, SECOP, SIIF, SIGEP, bases de datos).
B78: Mixta | C78: Combinación de datos de fuentes internas y externas formales.

Sheet 3 PROBABIL E IMPACTO INHERENTE
B1: =+'2 CONTEXTO E IDENTIFICACIÓN'!A1 -> MAPA DE RIESGOS
C2: =+'2 CONTEXTO E IDENTIFICACIÓN'!A2 -> VERSIÓN: | D2: ='2 CONTEXTO E IDENTIFICACIÓN'!B2 -> 1 | G2: =+'2 CONTEXTO E IDENTIFICACIÓN'!$J$4 -> Elaboración o Actualización: | H2: ='2 CONTEXTO E IDENTIFICACIÓN'!K4 -> 45991
A4: ENTIDAD: | G4: =+'2 CONTEXTO E IDENTIFICACIÓN'!$E$5 -> Vigencia: | H4: ='2 CONTEXTO E IDENTIFICACIÓN'!H5 -> 46023 | I4: Al | J4: ='2 CONTEXTO E IDENTIFICACIÓN'!K5 -> 46387 | P4: =IF(AND('2 CONTEXTO E IDENTIFICACIÓN'!$B$9='H1'!$A$2,'2 CONTEXTO E IDENTIFICACIÓN'!$C$9='H1'!$B$2,'H1'!$Q$2='H1'!$C$2,OR('H1'!$R$2='H1'!$D$2,'H1'!$R$2='H1'!$D$4)),"Afectación_Económica",'H1'!$U$2) -> N/A
A5: PROCESO:
G6: IMPACTO INHERENTE
C7: PROBABILIDAD INHERENTE | G7: Afectación Económica | J7: Reputacional | M7: Resultado | P7: PROBABILIDAD | V7: IMPACTO
A8: No. Riesgo | B8: Riesgo | C8: No. veces que realiza la actividad al año | D8: Frecuencia de la Actividad | E8: % Probabilidad | F8: Nivel Probabilidad | G8: Afectación Económica | H8: % | I8: Nivel | J8: Reputacional | K8: % | L8: Nivel | M8: Porcentaje de Impacto | N8: Nivel de Impacto | P8: Nivel | Q8: Frecuencia de la Actividad | R8: Mínimo | S8: Máximo | T8: Probabilidad | V8: Nivel | W8: % Impacto | X8: Afectación_Económica | Y8: Reputacional
A9: ='2 CONTEXTO E IDENTIFICACIÓN'!A9 -> R1 | B9: =+'2 CONTEXTO E IDENTIFICACIÓN'!K9 -> Posibilidad de perdida de Disponibilidad, confidencialidad e integridad de la información por fallas en el sistema debido a deficiencias en la infraestructura tecnológica, ausencia o insuficiencia de mantenimiento preventivo y correctivo | C9: 800 | D9: =+IF(C9="","",IF(C9<=$S$9,$Q$9,IF(C9<=$S$10,$Q$10,IF(C9<=$S$11,$Q$11,IF(C9<=$S$12,$Q$12,IF(C9>=$R$13,$Q$13,"")))))) -> La actividad que conlleva el riesgo se ejecuta mínimo 500 veces al año y máximo 5.000 veces por año | E9: =+IF(D9="","",IF(D9=$Q$9,$T$9,IF(D9=$Q$10,$T$10,IF(D9=$Q$11,$T$11,IF(D9=$Q$12,$T$12,IF(D9=$Q$13,$T$13)))))) -> 0.8 | F9: =+IF(D9="","",IF(D9=$Q$9,$P$9,IF(D9=$Q$10,$P$10,IF(D9=$Q$11,$P$11,IF(D9=$Q$12,$P$12,IF(D9=$Q$13,$P$13)))))) -> Alta | G9: Entre 10 y 50 SMLMV | H9: =+IF(G9="","",IF(G9="N/A","",IF(OR(G9=$X$9,G9=$Y$9),$W$9,IF(OR(G9=$X$10,G9=$Y$10),$W$10,IF(OR(G9=$X$11,G9=$Y$11),$W$11,IF(OR(G9=$X$12,G9=$Y$12),$W$12,IF(OR(G9=$X$13,G9=$Y$13),$W$13))))))) -> 0.4 | I9: =+IF(G9="","",IF(G9="N/A","",IF(OR(G9=$X$9,G9=$Y$9),$V$9,IF(OR(G9=$X$10,G9=$Y$10),$V$10,IF(OR(G9=$X$11,G9=$Y$11),$V$11,IF(OR(G9=$X$12,G9=$Y$12),$V$12,IF(OR(G9=$X$13,G9=$Y$13),$V$13))))))) -> Menor | J9: El riesgo afecta la imagen de la entidad internamente, de conocimiento general nivel interno, de junta directiva y accionistas y/o de proveedores. | K9: =+IF(J9="","",IF(J9="N/A","",IF(OR(J9=$X$9,J9=$Y$9),$W$9,IF(OR(J9=$X$10,J9=$Y$10),$W$10,IF(OR(J9=$X$11,J9=$Y$11),$W$11,IF(OR(J9=$X$12,J9=$Y$12),$W$12,IF(OR(J9=$X$13,J9=$Y$13),$W$13))))))) -> 0.4 | L9: =+IF(J9="","",IF(J9="N/A","",IF(OR(J9=$X$9,J9=$Y$9),$V$9,IF(OR(J9=$X$10,J9=$Y$10),$V$10,IF(OR(J9=$X$11,J9=$Y$11),$V$11,IF(OR(J9=$X$12,J9=$Y$12),$V$12,IF(OR(J9=$X$13,J9=$Y$13),$V$13))))))) -> Menor | M9: =+IF(H9="",K9,IF(K9="",H9,IF(H9>K9,H9,K9))) -> 0.4 | N9: =+IF(M9="","",IF(M9=$W$9,$V$9,IF(M9=$W$10,$V$10,IF(M9=$W$11,$V$11,IF(M9=$W$12,$V$12,IF(M9=$W$13,$V$13)))))) -> Menor | P9: Muy Baja | Q9: La actividad que conlleva el riesgo se ejecuta como máximos 2 veces por año | R9: 0 | S9: 2 | T9: 0.2 | V9: Leve | W9: 0.2 | X9: Menor a 10 SMLMV | Y9: El riesgo afecta la imagen de algún área de la organización.
A10: ='2 CONTEXTO E IDENTIFICACIÓN'!A10 -> R2 | B10: =+'2 CONTEXTO E IDENTIFICACIÓN'!K10 -> Posibilidad de perdida de Disponibilidad, confidencialidad e integridad de la información por accesos no autorizados, hackeos o fallas en el servicio debido a controles de seguridad y autenticación de usuarios, falta de actualización o monitoreo de la plataforma | C10: 2000 | D10: =+IF(C10="","",IF(C10<=$S$9,$Q$9,IF(C10<=$S$10,$Q$10,IF(C10<=$S$11,$Q$11,IF(C10<=$S$12,$Q$12,IF(C10>=$R$13,$Q$13,"")))))) -> La actividad que conlleva el riesgo se ejecuta mínimo 500 veces al año y máximo 5.000 veces por año | E10: =+IF(D10="","",IF(D10=$Q$9,$T$9,IF(D10=$Q$10,$T$10,IF(D10=$Q$11,$T$11,IF(D10=$Q$12,$T$12,IF(D10=$Q$13,$T$13)))))) -> 0.8 | F10: =+IF(D10="","",IF(D10=$Q$9,$P$9,IF(D10=$Q$10,$P$10,IF(D10=$Q$11,$P$11,IF(D10=$Q$12,$P$12,IF(D10=$Q$13,$P$13)))))) -> Alta | G10: Entre 10 y 50 SMLMV | H10: =+IF(G10="","",IF(G10="N/A","",IF(OR(G10=$X$9,G10=$Y$9),$W$9,IF(OR(G10=$X$10,G10=$Y$10),$W$10,IF(OR(G10=$X$11,G10=$Y$11),$W$11,IF(OR(G10=$X$12,G10=$Y$12),$W$12,IF(OR(G10=$X$13,G10=$Y$13),$W$13))))))) -> 0.4 | I10: =+IF(G10="","",IF(G10="N/A","",IF(OR(G10=$X$9,G10=$Y$9),$V$9,IF(OR(G10=$X$10,G10=$Y$10),$V$10,IF(OR(G10=$X$11,G10=$Y$11),$V$11,IF(OR(G10=$X$12,G10=$Y$12),$V$12,IF(OR(G10=$X$13,G10=$Y$13),$V$13))))))) -> Menor | J10: El riesgo afecta la imagen de la entidad con efecto publicitario sostenido a nivel de sector administrativo, nivel departamental o municipal. | K10: =+IF(J10="","",IF(J10="N/A","",IF(OR(J10=$X$9,J10=$Y$9),$W$9,IF(OR(J10=$X$10,J10=$Y$10),$W$10,IF(OR(J10=$X$11,J10=$Y$11),$W$11,IF(OR(J10=$X$12,J10=$Y$12),$W$12,IF(OR(J10=$X$13,J10=$Y$13),$W$13))))))) -> 0.8 | L10: =+IF(J10="","",IF(J10="N/A","",IF(OR(J10=$X$9,J10=$Y$9),$V$9,IF(OR(J10=$X$10,J10=$Y$10),$V$10,IF(OR(J10=$X$11,J10=$Y$11),$V$11,IF(OR(J10=$X$12,J10=$Y$12),$V$12,IF(OR(J10=$X$13,J10=$Y$13),$V$13))))))) -> Mayor | M10: =+IF(H10="",K10,IF(K10="",H10,IF(H10>K10,H10,K10))) -> 0.8 | N10: =+IF(M10="","",IF(M10=$W$9,$V$9,IF(M10=$W$10,$V$10,IF(M10=$W$11,$V$11,IF(M10=$W$12,$V$12,IF(M10=$W$13,$V$13)))))) -> Mayor | P10: Baja | Q10: La actividad que conlleva el riesgo se ejecuta de 3 a 24 veces por año | R10: 3 | S10: 24 | T10: 0.4 | V10: Menor | W10: 0.4 | X10: Entre 10 y 50 SMLMV | Y10: El riesgo afecta la imagen de la entidad internamente, de conocimiento general nivel interno, de junta directiva y accionistas y/o de proveedores.
A11: ='2 CONTEXTO E IDENTIFICACIÓN'!A11 -> R3 | B11: =+'2 CONTEXTO E IDENTIFICACIÓN'!K11 -> Posibilidad de perdida de Disponibilidad, confidencialidad e integridad de la información por eliminación accidental de archivos, fallas en el sistema o accesos no autorizados a causa de deficiencias en copias de seguridad, controles de accesos o ausencia de politicas de preservación digital | C11: 2000 | D11: =+IF(C11="","",IF(C11<=$S$9,$Q$9,IF(C11<=$S$10,$Q$10,IF(C11<=$S$11,$Q$11,IF(C11<=$S$12,$Q$12,IF(C11>=$R$13,$Q$13,"")))))) -> La actividad que conlleva el riesgo se ejecuta mínimo 500 veces al año y máximo 5.000 veces por año | E11: =+IF(D11="","",IF(D11=$Q$9,$T$9,IF(D11=$Q$10,$T$10,IF(D11=$Q$11,$T$11,IF(D11=$Q$12,$T$12,IF(D11=$Q$13,$T$13)))))) -> 0.8 | F11: =+IF(D11="","",IF(D11=$Q$9,$P$9,IF(D11=$Q$10,$P$10,IF(D11=$Q$11,$P$11,IF(D11=$Q$12,$P$12,IF(D11=$Q$13,$P$13)))))) -> Alta | G11: Entre 50 y 100 SMLMV | H11: =+IF(G11="","",IF(G11="N/A","",IF(OR(G11=$X$9,G11=$Y$9),$W$9,IF(OR(G11=$X$10,G11=$Y$10),$W$10,IF(OR(G11=$X$11,G11=$Y$11),$W$11,IF(OR(G11=$X$12,G11=$Y$12),$W$12,IF(OR(G11=$X$13,G11=$Y$13),$W$13))))))) -> 0.6 | I11: =+IF(G11="","",IF(G11="N/A","",IF(OR(G11=$X$9,G11=$Y$9),$V$9,IF(OR(G11=$X$10,G11=$Y$10),$V$10,IF(OR(G11=$X$11,G11=$Y$11),$V$11,IF(OR(G11=$X$12,G11=$Y$12),$V$12,IF(OR(G11=$X$13,G11=$Y$13),$V$13))))))) -> Moderado | J11: El riesgo afecta la imagen de la entidad con efecto publicitario sostenido a nivel de sector administrativo, nivel departamental o municipal. | K11: =+IF(J11="","",IF(J11="N/A","",IF(OR(J11=$X$9,J11=$Y$9),$W$9,IF(OR(J11=$X$10,J11=$Y$10),$W$10,IF(OR(J11=$X$11,J11=$Y$11),$W$11,IF(OR(J11=$X$12,J11=$Y$12),$W$12,IF(OR(J11=$X$13,J11=$Y$13),$W$13))))))) -> 0.8 | L11: =+IF(J11="","",IF(J11="N/A","",IF(OR(J11=$X$9,J11=$Y$9),$V$9,IF(OR(J11=$X$10,J11=$Y$10),$V$10,IF(OR(J11=$X$11,J11=$Y$11),$V$11,IF(OR(J11=$X$12,J11=$Y$12),$V$12,IF(OR(J11=$X$13,J11=$Y$13),$V$13))))))) -> Mayor | M11: =+IF(H11="",K11,IF(K11="",H11,IF(H11>K11,H11,K11))) -> 0.8 | N11: =+IF(M11="","",IF(M11=$W$9,$V$9,IF(M11=$W$10,$V$10,IF(M11=$W$11,$V$11,IF(M11=$W$12,$V$12,IF(M11=$W$13,$V$13)))))) -> Mayor | P11: Media | Q11: La actividad que conlleva el riesgo se ejecuta de 24 a 500 veces por año | R11: 25 | S11: 500 | T11: 0.6 | V11: Moderado | W11: 0.6 | X11: Entre 50 y 100 SMLMV | Y11: El riesgo afecta la imagen de la entidad con algunos usuarios de relevancia frente al logro de los objetivos.
A12: ='2 CONTEXTO E IDENTIFICACIÓN'!A12 -> R4 | B12: =+'2 CONTEXTO E IDENTIFICACIÓN'!K12 -> Posibilidad de perdida de Disponibilidad, confidencialidad e integridad de la información por fallas tecnológicas y manipulación indebida de la información o interrupciones del servicio debido a falta de actualización tecnólogica, vulnerabilidades en la administración de la plataforma o controles de seguridad avanzados | C12: 800 | D12: =+IF(C12="","",IF(C12<=$S$9,$Q$9,IF(C12<=$S$10,$Q$10,IF(C12<=$S$11,$Q$11,IF(C12<=$S$12,$Q$12,IF(C12>=$R$13,$Q$13,"")))))) -> La actividad que conlleva el riesgo se ejecuta mínimo 500 veces al año y máximo 5.000 veces por año | E12: =+IF(D12="","",IF(D12=$Q$9,$T$9,IF(D12=$Q$10,$T$10,IF(D12=$Q$11,$T$11,IF(D12=$Q$12,$T$12,IF(D12=$Q$13,$T$13)))))) -> 0.8 | F12: =+IF(D12="","",IF(D12=$Q$9,$P$9,IF(D12=$Q$10,$P$10,IF(D12=$Q$11,$P$11,IF(D12=$Q$12,$P$12,IF(D12=$Q$13,$P$13)))))) -> Alta | G12: Entre 10 y 50 SMLMV | H12: =+IF(G12="","",IF(G12="N/A","",IF(OR(G12=$X$9,G12=$Y$9),$W$9,IF(OR(G12=$X$10,G12=$Y$10),$W$10,IF(OR(G12=$X$11,G12=$Y$11),$W$11,IF(OR(G12=$X$12,G12=$Y$12),$W$12,IF(OR(G12=$X$13,G12=$Y$13),$W$13))))))) -> 0.4 | I12: =+IF(G12="","",IF(G12="N/A","",IF(OR(G12=$X$9,G12=$Y$9),$V$9,IF(OR(G12=$X$10,G12=$Y$10),$V$10,IF(OR(G12=$X$11,G12=$Y$11),$V$11,IF(OR(G12=$X$12,G12=$Y$12),$V$12,IF(OR(G12=$X$13,G12=$Y$13),$V$13))))))) -> Menor | J12: El riesgo afecta la imagen de la entidad internamente, de conocimiento general nivel interno, de junta directiva y accionistas y/o de proveedores. | K12: =+IF(J12="","",IF(J12="N/A","",IF(OR(J12=$X$9,J12=$Y$9),$W$9,IF(OR(J12=$X$10,J12=$Y$10),$W$10,IF(OR(J12=$X$11,J12=$Y$11),$W$11,IF(OR(J12=$X$12,J12=$Y$12),$W$12,IF(OR(J12=$X$13,J12=$Y$13),$W$13))))))) -> 0.4 | L12: =+IF(J12="","",IF(J12="N/A","",IF(OR(J12=$X$9,J12=$Y$9),$V$9,IF(OR(J12=$X$10,J12=$Y$10),$V$10,IF(OR(J12=$X$11,J12=$Y$11),$V$11,IF(OR(J12=$X$12,J12=$Y$12),$V$12,IF(OR(J12=$X$13,J12=$Y$13),$V$13))))))) -> Menor | M12: =+IF(H12="",K12,IF(K12="",H12,IF(H12>K12,H12,K12))) -> 0.4 | N12: =+IF(M12="","",IF(M12=$W$9,$V$9,IF(M12=$W$10,$V$10,IF(M12=$W$11,$V$11,IF(M12=$W$12,$V$12,IF(M12=$W$13,$V$13)))))) -> Menor | P12: Alta | Q12: La actividad que conlleva el riesgo se ejecuta mínimo 500 veces al año y máximo 5.000 veces por año | R12: 501 | S12: 5000 | T12: 0.8 | V12: Mayor | W12: 0.8 | X12: Entre 100 y 500 SMLMV | Y12: El riesgo afecta la imagen de la entidad con efecto publicitario sostenido a nivel de sector administrativo, nivel departamental o municipal.
A13: ='2 CONTEXTO E IDENTIFICACIÓN'!A13 -> R5 | B13: =+'2 CONTEXTO E IDENTIFICACIÓN'!K13 -> Posibilidad de perdida de disponibilidad e integridad de la información por ataques cibernéticos, modificaciones no autorizadas o fallas del servidor debido a ausencia de monitoreo permanente y mantenimiento de la plataforma o deficiencias en la implementación de controles de seguridad | C13: 500 | D13: =+IF(C13="","",IF(C13<=$S$9,$Q$9,IF(C13<=$S$10,$Q$10,IF(C13<=$S$11,$Q$11,IF(C13<=$S$12,$Q$12,IF(C13>=$R$13,$Q$13,"")))))) -> La actividad que conlleva el riesgo se ejecuta de 24 a 500 veces por año | E13: =+IF(D13="","",IF(D13=$Q$9,$T$9,IF(D13=$Q$10,$T$10,IF(D13=$Q$11,$T$11,IF(D13=$Q$12,$T$12,IF(D13=$Q$13,$T$13)))))) -> 0.6 | F13: =+IF(D13="","",IF(D13=$Q$9,$P$9,IF(D13=$Q$10,$P$10,IF(D13=$Q$11,$P$11,IF(D13=$Q$12,$P$12,IF(D13=$Q$13,$P$13)))))) -> Media | G13: Menor a 10 SMLMV | H13: =+IF(G13="","",IF(G13="N/A","",IF(OR(G13=$X$9,G13=$Y$9),$W$9,IF(OR(G13=$X$10,G13=$Y$10),$W$10,IF(OR(G13=$X$11,G13=$Y$11),$W$11,IF(OR(G13=$X$12,G13=$Y$12),$W$12,IF(OR(G13=$X$13,G13=$Y$13),$W$13))))))) -> 0.2 | I13: =+IF(G13="","",IF(G13="N/A","",IF(OR(G13=$X$9,G13=$Y$9),$V$9,IF(OR(G13=$X$10,G13=$Y$10),$V$10,IF(OR(G13=$X$11,G13=$Y$11),$V$11,IF(OR(G13=$X$12,G13=$Y$12),$V$12,IF(OR(G13=$X$13,G13=$Y$13),$V$13))))))) -> Leve | J13: El riesgo afecta la imagen de la entidad con algunos usuarios de relevancia frente al logro de los objetivos. | K13: =+IF(J13="","",IF(J13="N/A","",IF(OR(J13=$X$9,J13=$Y$9),$W$9,IF(OR(J13=$X$10,J13=$Y$10),$W$10,IF(OR(J13=$X$11,J13=$Y$11),$W$11,IF(OR(J13=$X$12,J13=$Y$12),$W$12,IF(OR(J13=$X$13,J13=$Y$13),$W$13))))))) -> 0.6 | L13: =+IF(J13="","",IF(J13="N/A","",IF(OR(J13=$X$9,J13=$Y$9),$V$9,IF(OR(J13=$X$10,J13=$Y$10),$V$10,IF(OR(J13=$X$11,J13=$Y$11),$V$11,IF(OR(J13=$X$12,J13=$Y$12),$V$12,IF(OR(J13=$X$13,J13=$Y$13),$V$13))))))) -> Moderado | M13: =+IF(H13="",K13,IF(K13="",H13,IF(H13>K13,H13,K13))) -> 0.6 | N13: =+IF(M13="","",IF(M13=$W$9,$V$9,IF(M13=$W$10,$V$10,IF(M13=$W$11,$V$11,IF(M13=$W$12,$V$12,IF(M13=$W$13,$V$13)))))) -> Moderado | P13: Muy Alta | Q13: La actividad que conlleva el riesgo se ejecuta más de 5.000 veces por año | R13: 5001 | T13: 1 | V13: Catastrófico | W13: 1 | X13: Mayor a 500 SMLMV | Y13: El riesgo afecta la imagen de la entidad a nivel nacional, con efecto publicitario sostenido a nivel país
A14: ='2 CONTEXTO E IDENTIFICACIÓN'!A14 -> R6 | B14: =+'2 CONTEXTO E IDENTIFICACIÓN'!K14 | D14: =+IF(C14="","",IF(C14<=$S$9,$Q$9,IF(C14<=$S$10,$Q$10,IF(C14<=$S$11,$Q$11,IF(C14<=$S$12,$Q$12,IF(C14>=$R$13,$Q$13,"")))))) | E14: =+IF(D14="","",IF(D14=$Q$9,$T$9,IF(D14=$Q$10,$T$10,IF(D14=$Q$11,$T$11,IF(D14=$Q$12,$T$12,IF(D14=$Q$13,$T$13)))))) | F14: =+IF(D14="","",IF(D14=$Q$9,$P$9,IF(D14=$Q$10,$P$10,IF(D14=$Q$11,$P$11,IF(D14=$Q$12,$P$12,IF(D14=$Q$13,$P$13)))))) | H14: =+IF(G14="","",IF(G14="N/A","",IF(OR(G14=$X$9,G14=$Y$9),$W$9,IF(OR(G14=$X$10,G14=$Y$10),$W$10,IF(OR(G14=$X$11,G14=$Y$11),$W$11,IF(OR(G14=$X$12,G14=$Y$12),$W$12,IF(OR(G14=$X$13,G14=$Y$13),$W$13))))))) | I14: =+IF(G14="","",IF(G14="N/A","",IF(OR(G14=$X$9,G14=$Y$9),$V$9,IF(OR(G14=$X$10,G14=$Y$10),$V$10,IF(OR(G14=$X$11,G14=$Y$11),$V$11,IF(OR(G14=$X$12,G14=$Y$12),$V$12,IF(OR(G14=$X$13,G14=$Y$13),$V$13))))))) | K14: =+IF(J14="","",IF(J14="N/A","",IF(OR(J14=$X$9,J14=$Y$9),$W$9,IF(OR(J14=$X$10,J14=$Y$10),$W$10,IF(OR(J14=$X$11,J14=$Y$11),$W$11,IF(OR(J14=$X$12,J14=$Y$12),$W$12,IF(OR(J14=$X$13,J14=$Y$13),$W$13))))))) | L14: =+IF(J14="","",IF(J14="N/A","",IF(OR(J14=$X$9,J14=$Y$9),$V$9,IF(OR(J14=$X$10,J14=$Y$10),$V$10,IF(OR(J14=$X$11,J14=$Y$11),$V$11,IF(OR(J14=$X$12,J14=$Y$12),$V$12,IF(OR(J14=$X$13,J14=$Y$13),$V$13))))))) | M14: =+IF(H14="",K14,IF(K14="",H14,IF(H14>K14,H14,K14))) | N14: =+IF(M14="","",IF(M14=$W$9,$V$9,IF(M14=$W$10,$V$10,IF(M14=$W$11,$V$11,IF(M14=$W$12,$V$12,IF(M14=$W$13,$V$13)))))) | X14: N/A | Y14: N/A
A15: ='2 CONTEXTO E IDENTIFICACIÓN'!A15 -> R7 | B15: =+'2 CONTEXTO E IDENTIFICACIÓN'!K15 | D15: =+IF(C15="","",IF(C15<=$S$9,$Q$9,IF(C15<=$S$10,$Q$10,IF(C15<=$S$11,$Q$11,IF(C15<=$S$12,$Q$12,IF(C15>=$R$13,$Q$13,"")))))) | E15: =+IF(D15="","",IF(D15=$Q$9,$T$9,IF(D15=$Q$10,$T$10,IF(D15=$Q$11,$T$11,IF(D15=$Q$12,$T$12,IF(D15=$Q$13,$T$13)))))) | F15: =+IF(D15="","",IF(D15=$Q$9,$P$9,IF(D15=$Q$10,$P$10,IF(D15=$Q$11,$P$11,IF(D15=$Q$12,$P$12,IF(D15=$Q$13,$P$13)))))) | H15: =+IF(G15="","",IF(G15="N/A","",IF(OR(G15=$X$9,G15=$Y$9),$W$9,IF(OR(G15=$X$10,G15=$Y$10),$W$10,IF(OR(G15=$X$11,G15=$Y$11),$W$11,IF(OR(G15=$X$12,G15=$Y$12),$W$12,IF(OR(G15=$X$13,G15=$Y$13),$W$13))))))) | I15: =+IF(G15="","",IF(G15="N/A","",IF(OR(G15=$X$9,G15=$Y$9),$V$9,IF(OR(G15=$X$10,G15=$Y$10),$V$10,IF(OR(G15=$X$11,G15=$Y$11),$V$11,IF(OR(G15=$X$12,G15=$Y$12),$V$12,IF(OR(G15=$X$13,G15=$Y$13),$V$13))))))) | K15: =+IF(J15="","",IF(J15="N/A","",IF(OR(J15=$X$9,J15=$Y$9),$W$9,IF(OR(J15=$X$10,J15=$Y$10),$W$10,IF(OR(J15=$X$11,J15=$Y$11),$W$11,IF(OR(J15=$X$12,J15=$Y$12),$W$12,IF(OR(J15=$X$13,J15=$Y$13),$W$13))))))) | L15: =+IF(J15="","",IF(J15="N/A","",IF(OR(J15=$X$9,J15=$Y$9),$V$9,IF(OR(J15=$X$10,J15=$Y$10),$V$10,IF(OR(J15=$X$11,J15=$Y$11),$V$11,IF(OR(J15=$X$12,J15=$Y$12),$V$12,IF(OR(J15=$X$13,J15=$Y$13),$V$13))))))) | M15: =+IF(H15="",K15,IF(K15="",H15,IF(H15>K15,H15,K15))) | N15: =+IF(M15="","",IF(M15=$W$9,$V$9,IF(M15=$W$10,$V$10,IF(M15=$W$11,$V$11,IF(M15=$W$12,$V$12,IF(M15=$W$13,$V$13))))))
A16: ='2 CONTEXTO E IDENTIFICACIÓN'!A16 -> R8 | B16: =+'2 CONTEXTO E IDENTIFICACIÓN'!K16 | D16: =+IF(C16="","",IF(C16<=$S$9,$Q$9,IF(C16<=$S$10,$Q$10,IF(C16<=$S$11,$Q$11,IF(C16<=$S$12,$Q$12,IF(C16>=$R$13,$Q$13,"")))))) | E16: =+IF(D16="","",IF(D16=$Q$9,$T$9,IF(D16=$Q$10,$T$10,IF(D16=$Q$11,$T$11,IF(D16=$Q$12,$T$12,IF(D16=$Q$13,$T$13)))))) | F16: =+IF(D16="","",IF(D16=$Q$9,$P$9,IF(D16=$Q$10,$P$10,IF(D16=$Q$11,$P$11,IF(D16=$Q$12,$P$12,IF(D16=$Q$13,$P$13)))))) | H16: =+IF(G16="","",IF(G16="N/A","",IF(OR(G16=$X$9,G16=$Y$9),$W$9,IF(OR(G16=$X$10,G16=$Y$10),$W$10,IF(OR(G16=$X$11,G16=$Y$11),$W$11,IF(OR(G16=$X$12,G16=$Y$12),$W$12,IF(OR(G16=$X$13,G16=$Y$13),$W$13))))))) | I16: =+IF(G16="","",IF(G16="N/A","",IF(OR(G16=$X$9,G16=$Y$9),$V$9,IF(OR(G16=$X$10,G16=$Y$10),$V$10,IF(OR(G16=$X$11,G16=$Y$11),$V$11,IF(OR(G16=$X$12,G16=$Y$12),$V$12,IF(OR(G16=$X$13,G16=$Y$13),$V$13))))))) | K16: =+IF(J16="","",IF(J16="N/A","",IF(OR(J16=$X$9,J16=$Y$9),$W$9,IF(OR(J16=$X$10,J16=$Y$10),$W$10,IF(OR(J16=$X$11,J16=$Y$11),$W$11,IF(OR(J16=$X$12,J16=$Y$12),$W$12,IF(OR(J16=$X$13,J16=$Y$13),$W$13))))))) | L16: =+IF(J16="","",IF(J16="N/A","",IF(OR(J16=$X$9,J16=$Y$9),$V$9,IF(OR(J16=$X$10,J16=$Y$10),$V$10,IF(OR(J16=$X$11,J16=$Y$11),$V$11,IF(OR(J16=$X$12,J16=$Y$12),$V$12,IF(OR(J16=$X$13,J16=$Y$13),$V$13))))))) | M16: =+IF(H16="",K16,IF(K16="",H16,IF(H16>K16,H16,K16))) | N16: =+IF(M16="","",IF(M16=$W$9,$V$9,IF(M16=$W$10,$V$10,IF(M16=$W$11,$V$11,IF(M16=$W$12,$V$12,IF(M16=$W$13,$V$13))))))
A17: ='2 CONTEXTO E IDENTIFICACIÓN'!A17 -> R9 | B17: =+'2 CONTEXTO E IDENTIFICACIÓN'!K17 | D17: =+IF(C17="","",IF(C17<=$S$9,$Q$9,IF(C17<=$S$10,$Q$10,IF(C17<=$S$11,$Q$11,IF(C17<=$S$12,$Q$12,IF(C17>=$R$13,$Q$13,"")))))) | E17: =+IF(D17="","",IF(D17=$Q$9,$T$9,IF(D17=$Q$10,$T$10,IF(D17=$Q$11,$T$11,IF(D17=$Q$12,$T$12,IF(D17=$Q$13,$T$13)))))) | F17: =+IF(D17="","",IF(D17=$Q$9,$P$9,IF(D17=$Q$10,$P$10,IF(D17=$Q$11,$P$11,IF(D17=$Q$12,$P$12,IF(D17=$Q$13,$P$13)))))) | H17: =+IF(G17="","",IF(G17="N/A","",IF(OR(G17=$X$9,G17=$Y$9),$W$9,IF(OR(G17=$X$10,G17=$Y$10),$W$10,IF(OR(G17=$X$11,G17=$Y$11),$W$11,IF(OR(G17=$X$12,G17=$Y$12),$W$12,IF(OR(G17=$X$13,G17=$Y$13),$W$13))))))) | I17: =+IF(G17="","",IF(G17="N/A","",IF(OR(G17=$X$9,G17=$Y$9),$V$9,IF(OR(G17=$X$10,G17=$Y$10),$V$10,IF(OR(G17=$X$11,G17=$Y$11),$V$11,IF(OR(G17=$X$12,G17=$Y$12),$V$12,IF(OR(G17=$X$13,G17=$Y$13),$V$13))))))) | K17: =+IF(J17="","",IF(J17="N/A","",IF(OR(J17=$X$9,J17=$Y$9),$W$9,IF(OR(J17=$X$10,J17=$Y$10),$W$10,IF(OR(J17=$X$11,J17=$Y$11),$W$11,IF(OR(J17=$X$12,J17=$Y$12),$W$12,IF(OR(J17=$X$13,J17=$Y$13),$W$13))))))) | L17: =+IF(J17="","",IF(J17="N/A","",IF(OR(J17=$X$9,J17=$Y$9),$V$9,IF(OR(J17=$X$10,J17=$Y$10),$V$10,IF(OR(J17=$X$11,J17=$Y$11),$V$11,IF(OR(J17=$X$12,J17=$Y$12),$V$12,IF(OR(J17=$X$13,J17=$Y$13),$V$13))))))) | M17: =+IF(H17="",K17,IF(K17="",H17,IF(H17>K17,H17,K17))) | N17: =+IF(M17="","",IF(M17=$W$9,$V$9,IF(M17=$W$10,$V$10,IF(M17=$W$11,$V$11,IF(M17=$W$12,$V$12,IF(M17=$W$13,$V$13))))))
A18: ='2 CONTEXTO E IDENTIFICACIÓN'!A18 -> R10 | B18: =+'2 CONTEXTO E IDENTIFICACIÓN'!K18 | D18: =+IF(C18="","",IF(C18<=$S$9,$Q$9,IF(C18<=$S$10,$Q$10,IF(C18<=$S$11,$Q$11,IF(C18<=$S$12,$Q$12,IF(C18>=$R$13,$Q$13,"")))))) | E18: =+IF(D18="","",IF(D18=$Q$9,$T$9,IF(D18=$Q$10,$T$10,IF(D18=$Q$11,$T$11,IF(D18=$Q$12,$T$12,IF(D18=$Q$13,$T$13)))))) | F18: =+IF(D18="","",IF(D18=$Q$9,$P$9,IF(D18=$Q$10,$P$10,IF(D18=$Q$11,$P$11,IF(D18=$Q$12,$P$12,IF(D18=$Q$13,$P$13)))))) | H18: =+IF(G18="","",IF(G18="N/A","",IF(OR(G18=$X$9,G18=$Y$9),$W$9,IF(OR(G18=$X$10,G18=$Y$10),$W$10,IF(OR(G18=$X$11,G18=$Y$11),$W$11,IF(OR(G18=$X$12,G18=$Y$12),$W$12,IF(OR(G18=$X$13,G18=$Y$13),$W$13))))))) | I18: =+IF(G18="","",IF(G18="N/A","",IF(OR(G18=$X$9,G18=$Y$9),$V$9,IF(OR(G18=$X$10,G18=$Y$10),$V$10,IF(OR(G18=$X$11,G18=$Y$11),$V$11,IF(OR(G18=$X$12,G18=$Y$12),$V$12,IF(OR(G18=$X$13,G18=$Y$13),$V$13))))))) | K18: =+IF(J18="","",IF(J18="N/A","",IF(OR(J18=$X$9,J18=$Y$9),$W$9,IF(OR(J18=$X$10,J18=$Y$10),$W$10,IF(OR(J18=$X$11,J18=$Y$11),$W$11,IF(OR(J18=$X$12,J18=$Y$12),$W$12,IF(OR(J18=$X$13,J18=$Y$13),$W$13))))))) | L18: =+IF(J18="","",IF(J18="N/A","",IF(OR(J18=$X$9,J18=$Y$9),$V$9,IF(OR(J18=$X$10,J18=$Y$10),$V$10,IF(OR(J18=$X$11,J18=$Y$11),$V$11,IF(OR(J18=$X$12,J18=$Y$12),$V$12,IF(OR(J18=$X$13,J18=$Y$13),$V$13))))))) | M18: =+IF(H18="",K18,IF(K18="",H18,IF(H18>K18,H18,K18))) | N18: =+IF(M18="","",IF(M18=$W$9,$V$9,IF(M18=$W$10,$V$10,IF(M18=$W$11,$V$11,IF(M18=$W$12,$V$12,IF(M18=$W$13,$V$13))))))
A19: ='2 CONTEXTO E IDENTIFICACIÓN'!A19 -> R11 | B19: =+'2 CONTEXTO E IDENTIFICACIÓN'!K19 | D19: =+IF(C19="","",IF(C19<=$S$9,$Q$9,IF(C19<=$S$10,$Q$10,IF(C19<=$S$11,$Q$11,IF(C19<=$S$12,$Q$12,IF(C19>=$R$13,$Q$13,"")))))) | E19: =+IF(D19="","",IF(D19=$Q$9,$T$9,IF(D19=$Q$10,$T$10,IF(D19=$Q$11,$T$11,IF(D19=$Q$12,$T$12,IF(D19=$Q$13,$T$13)))))) | F19: =+IF(D19="","",IF(D19=$Q$9,$P$9,IF(D19=$Q$10,$P$10,IF(D19=$Q$11,$P$11,IF(D19=$Q$12,$P$12,IF(D19=$Q$13,$P$13)))))) | H19: =+IF(G19="","",IF(G19="N/A","",IF(OR(G19=$X$9,G19=$Y$9),$W$9,IF(OR(G19=$X$10,G19=$Y$10),$W$10,IF(OR(G19=$X$11,G19=$Y$11),$W$11,IF(OR(G19=$X$12,G19=$Y$12),$W$12,IF(OR(G19=$X$13,G19=$Y$13),$W$13))))))) | I19: =+IF(G19="","",IF(G19="N/A","",IF(OR(G19=$X$9,G19=$Y$9),$V$9,IF(OR(G19=$X$10,G19=$Y$10),$V$10,IF(OR(G19=$X$11,G19=$Y$11),$V$11,IF(OR(G19=$X$12,G19=$Y$12),$V$12,IF(OR(G19=$X$13,G19=$Y$13),$V$13))))))) | K19: =+IF(J19="","",IF(J19="N/A","",IF(OR(J19=$X$9,J19=$Y$9),$W$9,IF(OR(J19=$X$10,J19=$Y$10),$W$10,IF(OR(J19=$X$11,J19=$Y$11),$W$11,IF(OR(J19=$X$12,J19=$Y$12),$W$12,IF(OR(J19=$X$13,J19=$Y$13),$W$13))))))) | L19: =+IF(J19="","",IF(J19="N/A","",IF(OR(J19=$X$9,J19=$Y$9),$V$9,IF(OR(J19=$X$10,J19=$Y$10),$V$10,IF(OR(J19=$X$11,J19=$Y$11),$V$11,IF(OR(J19=$X$12,J19=$Y$12),$V$12,IF(OR(J19=$X$13,J19=$Y$13),$V$13))))))) | M19: =+IF(H19="",K19,IF(K19="",H19,IF(H19>K19,H19,K19))) | N19: =+IF(M19="","",IF(M19=$W$9,$V$9,IF(M19=$W$10,$V$10,IF(M19=$W$11,$V$11,IF(M19=$W$12,$V$12,IF(M19=$W$13,$V$13))))))
A20: ='2 CONTEXTO E IDENTIFICACIÓN'!A20 -> R12 | B20: =+'2 CONTEXTO E IDENTIFICACIÓN'!K20 | D20: =+IF(C20="","",IF(C20<=$S$9,$Q$9,IF(C20<=$S$10,$Q$10,IF(C20<=$S$11,$Q$11,IF(C20<=$S$12,$Q$12,IF(C20>=$R$13,$Q$13,"")))))) | E20: =+IF(D20="","",IF(D20=$Q$9,$T$9,IF(D20=$Q$10,$T$10,IF(D20=$Q$11,$T$11,IF(D20=$Q$12,$T$12,IF(D20=$Q$13,$T$13)))))) | F20: =+IF(D20="","",IF(D20=$Q$9,$P$9,IF(D20=$Q$10,$P$10,IF(D20=$Q$11,$P$11,IF(D20=$Q$12,$P$12,IF(D20=$Q$13,$P$13)))))) | H20: =+IF(G20="","",IF(G20="N/A","",IF(OR(G20=$X$9,G20=$Y$9),$W$9,IF(OR(G20=$X$10,G20=$Y$10),$W$10,IF(OR(G20=$X$11,G20=$Y$11),$W$11,IF(OR(G20=$X$12,G20=$Y$12),$W$12,IF(OR(G20=$X$13,G20=$Y$13),$W$13))))))) | I20: =+IF(G20="","",IF(G20="N/A","",IF(OR(G20=$X$9,G20=$Y$9),$V$9,IF(OR(G20=$X$10,G20=$Y$10),$V$10,IF(OR(G20=$X$11,G20=$Y$11),$V$11,IF(OR(G20=$X$12,G20=$Y$12),$V$12,IF(OR(G20=$X$13,G20=$Y$13),$V$13))))))) | K20: =+IF(J20="","",IF(J20="N/A","",IF(OR(J20=$X$9,J20=$Y$9),$W$9,IF(OR(J20=$X$10,J20=$Y$10),$W$10,IF(OR(J20=$X$11,J20=$Y$11),$W$11,IF(OR(J20=$X$12,J20=$Y$12),$W$12,IF(OR(J20=$X$13,J20=$Y$13),$W$13))))))) | L20: =+IF(J20="","",IF(J20="N/A","",IF(OR(J20=$X$9,J20=$Y$9),$V$9,IF(OR(J20=$X$10,J20=$Y$10),$V$10,IF(OR(J20=$X$11,J20=$Y$11),$V$11,IF(OR(J20=$X$12,J20=$Y$12),$V$12,IF(OR(J20=$X$13,J20=$Y$13),$V$13))))))) | M20: =+IF(H20="",K20,IF(K20="",H20,IF(H20>K20,H20,K20))) | N20: =+IF(M20="","",IF(M20=$W$9,$V$9,IF(M20=$W$10,$V$10,IF(M20=$W$11,$V$11,IF(M20=$W$12,$V$12,IF(M20=$W$13,$V$13))))))
A21: ='2 CONTEXTO E IDENTIFICACIÓN'!A21 -> R13 | B21: =+'2 CONTEXTO E IDENTIFICACIÓN'!K21 | D21: =+IF(C21="","",IF(C21<=$S$9,$Q$9,IF(C21<=$S$10,$Q$10,IF(C21<=$S$11,$Q$11,IF(C21<=$S$12,$Q$12,IF(C21>=$R$13,$Q$13,"")))))) | E21: =+IF(D21="","",IF(D21=$Q$9,$T$9,IF(D21=$Q$10,$T$10,IF(D21=$Q$11,$T$11,IF(D21=$Q$12,$T$12,IF(D21=$Q$13,$T$13)))))) | F21: =+IF(D21="","",IF(D21=$Q$9,$P$9,IF(D21=$Q$10,$P$10,IF(D21=$Q$11,$P$11,IF(D21=$Q$12,$P$12,IF(D21=$Q$13,$P$13)))))) | H21: =+IF(G21="","",IF(G21="N/A","",IF(OR(G21=$X$9,G21=$Y$9),$W$9,IF(OR(G21=$X$10,G21=$Y$10),$W$10,IF(OR(G21=$X$11,G21=$Y$11),$W$11,IF(OR(G21=$X$12,G21=$Y$12),$W$12,IF(OR(G21=$X$13,G21=$Y$13),$W$13))))))) | I21: =+IF(G21="","",IF(G21="N/A","",IF(OR(G21=$X$9,G21=$Y$9),$V$9,IF(OR(G21=$X$10,G21=$Y$10),$V$10,IF(OR(G21=$X$11,G21=$Y$11),$V$11,IF(OR(G21=$X$12,G21=$Y$12),$V$12,IF(OR(G21=$X$13,G21=$Y$13),$V$13))))))) | K21: =+IF(J21="","",IF(J21="N/A","",IF(OR(J21=$X$9,J21=$Y$9),$W$9,IF(OR(J21=$X$10,J21=$Y$10),$W$10,IF(OR(J21=$X$11,J21=$Y$11),$W$11,IF(OR(J21=$X$12,J21=$Y$12),$W$12,IF(OR(J21=$X$13,J21=$Y$13),$W$13))))))) | L21: =+IF(J21="","",IF(J21="N/A","",IF(OR(J21=$X$9,J21=$Y$9),$V$9,IF(OR(J21=$X$10,J21=$Y$10),$V$10,IF(OR(J21=$X$11,J21=$Y$11),$V$11,IF(OR(J21=$X$12,J21=$Y$12),$V$12,IF(OR(J21=$X$13,J21=$Y$13),$V$13))))))) | M21: =+IF(H21="",K21,IF(K21="",H21,IF(H21>K21,H21,K21))) | N21: =+IF(M21="","",IF(M21=$W$9,$V$9,IF(M21=$W$10,$V$10,IF(M21=$W$11,$V$11,IF(M21=$W$12,$V$12,IF(M21=$W$13,$V$13))))))
A22: ='2 CONTEXTO E IDENTIFICACIÓN'!A22 -> R14 | B22: =+'2 CONTEXTO E IDENTIFICACIÓN'!K22 | D22: =+IF(C22="","",IF(C22<=$S$9,$Q$9,IF(C22<=$S$10,$Q$10,IF(C22<=$S$11,$Q$11,IF(C22<=$S$12,$Q$12,IF(C22>=$R$13,$Q$13,"")))))) | E22: =+IF(D22="","",IF(D22=$Q$9,$T$9,IF(D22=$Q$10,$T$10,IF(D22=$Q$11,$T$11,IF(D22=$Q$12,$T$12,IF(D22=$Q$13,$T$13)))))) | F22: =+IF(D22="","",IF(D22=$Q$9,$P$9,IF(D22=$Q$10,$P$10,IF(D22=$Q$11,$P$11,IF(D22=$Q$12,$P$12,IF(D22=$Q$13,$P$13)))))) | H22: =+IF(G22="","",IF(G22="N/A","",IF(OR(G22=$X$9,G22=$Y$9),$W$9,IF(OR(G22=$X$10,G22=$Y$10),$W$10,IF(OR(G22=$X$11,G22=$Y$11),$W$11,IF(OR(G22=$X$12,G22=$Y$12),$W$12,IF(OR(G22=$X$13,G22=$Y$13),$W$13))))))) | I22: =+IF(G22="","",IF(G22="N/A","",IF(OR(G22=$X$9,G22=$Y$9),$V$9,IF(OR(G22=$X$10,G22=$Y$10),$V$10,IF(OR(G22=$X$11,G22=$Y$11),$V$11,IF(OR(G22=$X$12,G22=$Y$12),$V$12,IF(OR(G22=$X$13,G22=$Y$13),$V$13))))))) | K22: =+IF(J22="","",IF(J22="N/A","",IF(OR(J22=$X$9,J22=$Y$9),$W$9,IF(OR(J22=$X$10,J22=$Y$10),$W$10,IF(OR(J22=$X$11,J22=$Y$11),$W$11,IF(OR(J22=$X$12,J22=$Y$12),$W$12,IF(OR(J22=$X$13,J22=$Y$13),$W$13))))))) | L22: =+IF(J22="","",IF(J22="N/A","",IF(OR(J22=$X$9,J22=$Y$9),$V$9,IF(OR(J22=$X$10,J22=$Y$10),$V$10,IF(OR(J22=$X$11,J22=$Y$11),$V$11,IF(OR(J22=$X$12,J22=$Y$12),$V$12,IF(OR(J22=$X$13,J22=$Y$13),$V$13))))))) | M22: =+IF(H22="",K22,IF(K22="",H22,IF(H22>K22,H22,K22))) | N22: =+IF(M22="","",IF(M22=$W$9,$V$9,IF(M22=$W$10,$V$10,IF(M22=$W$11,$V$11,IF(M22=$W$12,$V$12,IF(M22=$W$13,$V$13))))))
A23: ='2 CONTEXTO E IDENTIFICACIÓN'!A23 -> R15 | B23: =+'2 CONTEXTO E IDENTIFICACIÓN'!K23 | D23: =+IF(C23="","",IF(C23<=$S$9,$Q$9,IF(C23<=$S$10,$Q$10,IF(C23<=$S$11,$Q$11,IF(C23<=$S$12,$Q$12,IF(C23>=$R$13,$Q$13,"")))))) | E23: =+IF(D23="","",IF(D23=$Q$9,$T$9,IF(D23=$Q$10,$T$10,IF(D23=$Q$11,$T$11,IF(D23=$Q$12,$T$12,IF(D23=$Q$13,$T$13)))))) | F23: =+IF(D23="","",IF(D23=$Q$9,$P$9,IF(D23=$Q$10,$P$10,IF(D23=$Q$11,$P$11,IF(D23=$Q$12,$P$12,IF(D23=$Q$13,$P$13)))))) | H23: =+IF(G23="","",IF(G23="N/A","",IF(OR(G23=$X$9,G23=$Y$9),$W$9,IF(OR(G23=$X$10,G23=$Y$10),$W$10,IF(OR(G23=$X$11,G23=$Y$11),$W$11,IF(OR(G23=$X$12,G23=$Y$12),$W$12,IF(OR(G23=$X$13,G23=$Y$13),$W$13))))))) | I23: =+IF(G23="","",IF(G23="N/A","",IF(OR(G23=$X$9,G23=$Y$9),$V$9,IF(OR(G23=$X$10,G23=$Y$10),$V$10,IF(OR(G23=$X$11,G23=$Y$11),$V$11,IF(OR(G23=$X$12,G23=$Y$12),$V$12,IF(OR(G23=$X$13,G23=$Y$13),$V$13))))))) | K23: =+IF(J23="","",IF(J23="N/A","",IF(OR(J23=$X$9,J23=$Y$9),$W$9,IF(OR(J23=$X$10,J23=$Y$10),$W$10,IF(OR(J23=$X$11,J23=$Y$11),$W$11,IF(OR(J23=$X$12,J23=$Y$12),$W$12,IF(OR(J23=$X$13,J23=$Y$13),$W$13))))))) | L23: =+IF(J23="","",IF(J23="N/A","",IF(OR(J23=$X$9,J23=$Y$9),$V$9,IF(OR(J23=$X$10,J23=$Y$10),$V$10,IF(OR(J23=$X$11,J23=$Y$11),$V$11,IF(OR(J23=$X$12,J23=$Y$12),$V$12,IF(OR(J23=$X$13,J23=$Y$13),$V$13))))))) | M23: =+IF(H23="",K23,IF(K23="",H23,IF(H23>K23,H23,K23))) | N23: =+IF(M23="","",IF(M23=$W$9,$V$9,IF(M23=$W$10,$V$10,IF(M23=$W$11,$V$11,IF(M23=$W$12,$V$12,IF(M23=$W$13,$V$13))))))
A24: ='2 CONTEXTO E IDENTIFICACIÓN'!A24 -> R16 | B24: =+'2 CONTEXTO E IDENTIFICACIÓN'!K24 | D24: =+IF(C24="","",IF(C24<=$S$9,$Q$9,IF(C24<=$S$10,$Q$10,IF(C24<=$S$11,$Q$11,IF(C24<=$S$12,$Q$12,IF(C24>=$R$13,$Q$13,"")))))) | E24: =+IF(D24="","",IF(D24=$Q$9,$T$9,IF(D24=$Q$10,$T$10,IF(D24=$Q$11,$T$11,IF(D24=$Q$12,$T$12,IF(D24=$Q$13,$T$13)))))) | F24: =+IF(D24="","",IF(D24=$Q$9,$P$9,IF(D24=$Q$10,$P$10,IF(D24=$Q$11,$P$11,IF(D24=$Q$12,$P$12,IF(D24=$Q$13,$P$13)))))) | H24: =+IF(G24="","",IF(G24="N/A","",IF(OR(G24=$X$9,G24=$Y$9),$W$9,IF(OR(G24=$X$10,G24=$Y$10),$W$10,IF(OR(G24=$X$11,G24=$Y$11),$W$11,IF(OR(G24=$X$12,G24=$Y$12),$W$12,IF(OR(G24=$X$13,G24=$Y$13),$W$13))))))) | I24: =+IF(G24="","",IF(G24="N/A","",IF(OR(G24=$X$9,G24=$Y$9),$V$9,IF(OR(G24=$X$10,G24=$Y$10),$V$10,IF(OR(G24=$X$11,G24=$Y$11),$V$11,IF(OR(G24=$X$12,G24=$Y$12),$V$12,IF(OR(G24=$X$13,G24=$Y$13),$V$13))))))) | K24: =+IF(J24="","",IF(J24="N/A","",IF(OR(J24=$X$9,J24=$Y$9),$W$9,IF(OR(J24=$X$10,J24=$Y$10),$W$10,IF(OR(J24=$X$11,J24=$Y$11),$W$11,IF(OR(J24=$X$12,J24=$Y$12),$W$12,IF(OR(J24=$X$13,J24=$Y$13),$W$13))))))) | L24: =+IF(J24="","",IF(J24="N/A","",IF(OR(J24=$X$9,J24=$Y$9),$V$9,IF(OR(J24=$X$10,J24=$Y$10),$V$10,IF(OR(J24=$X$11,J24=$Y$11),$V$11,IF(OR(J24=$X$12,J24=$Y$12),$V$12,IF(OR(J24=$X$13,J24=$Y$13),$V$13))))))) | M24: =+IF(H24="",K24,IF(K24="",H24,IF(H24>K24,H24,K24))) | N24: =+IF(M24="","",IF(M24=$W$9,$V$9,IF(M24=$W$10,$V$10,IF(M24=$W$11,$V$11,IF(M24=$W$12,$V$12,IF(M24=$W$13,$V$13))))))
A25: ='2 CONTEXTO E IDENTIFICACIÓN'!A25 -> R17 | B25: =+'2 CONTEXTO E IDENTIFICACIÓN'!K25 | D25: =+IF(C25="","",IF(C25<=$S$9,$Q$9,IF(C25<=$S$10,$Q$10,IF(C25<=$S$11,$Q$11,IF(C25<=$S$12,$Q$12,IF(C25>=$R$13,$Q$13,"")))))) | E25: =+IF(D25="","",IF(D25=$Q$9,$T$9,IF(D25=$Q$10,$T$10,IF(D25=$Q$11,$T$11,IF(D25=$Q$12,$T$12,IF(D25=$Q$13,$T$13)))))) | F25: =+IF(D25="","",IF(D25=$Q$9,$P$9,IF(D25=$Q$10,$P$10,IF(D25=$Q$11,$P$11,IF(D25=$Q$12,$P$12,IF(D25=$Q$13,$P$13)))))) | H25: =+IF(G25="","",IF(G25="N/A","",IF(OR(G25=$X$9,G25=$Y$9),$W$9,IF(OR(G25=$X$10,G25=$Y$10),$W$10,IF(OR(G25=$X$11,G25=$Y$11),$W$11,IF(OR(G25=$X$12,G25=$Y$12),$W$12,IF(OR(G25=$X$13,G25=$Y$13),$W$13))))))) | I25: =+IF(G25="","",IF(G25="N/A","",IF(OR(G25=$X$9,G25=$Y$9),$V$9,IF(OR(G25=$X$10,G25=$Y$10),$V$10,IF(OR(G25=$X$11,G25=$Y$11),$V$11,IF(OR(G25=$X$12,G25=$Y$12),$V$12,IF(OR(G25=$X$13,G25=$Y$13),$V$13))))))) | K25: =+IF(J25="","",IF(J25="N/A","",IF(OR(J25=$X$9,J25=$Y$9),$W$9,IF(OR(J25=$X$10,J25=$Y$10),$W$10,IF(OR(J25=$X$11,J25=$Y$11),$W$11,IF(OR(J25=$X$12,J25=$Y$12),$W$12,IF(OR(J25=$X$13,J25=$Y$13),$W$13))))))) | L25: =+IF(J25="","",IF(J25="N/A","",IF(OR(J25=$X$9,J25=$Y$9),$V$9,IF(OR(J25=$X$10,J25=$Y$10),$V$10,IF(OR(J25=$X$11,J25=$Y$11),$V$11,IF(OR(J25=$X$12,J25=$Y$12),$V$12,IF(OR(J25=$X$13,J25=$Y$13),$V$13))))))) | M25: =+IF(H25="",K25,IF(K25="",H25,IF(H25>K25,H25,K25))) | N25: =+IF(M25="","",IF(M25=$W$9,$V$9,IF(M25=$W$10,$V$10,IF(M25=$W$11,$V$11,IF(M25=$W$12,$V$12,IF(M25=$W$13,$V$13))))))
A26: ='2 CONTEXTO E IDENTIFICACIÓN'!A26 -> R18 | B26: =+'2 CONTEXTO E IDENTIFICACIÓN'!K26 | D26: =+IF(C26="","",IF(C26<=$S$9,$Q$9,IF(C26<=$S$10,$Q$10,IF(C26<=$S$11,$Q$11,IF(C26<=$S$12,$Q$12,IF(C26>=$R$13,$Q$13,"")))))) | E26: =+IF(D26="","",IF(D26=$Q$9,$T$9,IF(D26=$Q$10,$T$10,IF(D26=$Q$11,$T$11,IF(D26=$Q$12,$T$12,IF(D26=$Q$13,$T$13)))))) | F26: =+IF(D26="","",IF(D26=$Q$9,$P$9,IF(D26=$Q$10,$P$10,IF(D26=$Q$11,$P$11,IF(D26=$Q$12,$P$12,IF(D26=$Q$13,$P$13)))))) | H26: =+IF(G26="","",IF(G26="N/A","",IF(OR(G26=$X$9,G26=$Y$9),$W$9,IF(OR(G26=$X$10,G26=$Y$10),$W$10,IF(OR(G26=$X$11,G26=$Y$11),$W$11,IF(OR(G26=$X$12,G26=$Y$12),$W$12,IF(OR(G26=$X$13,G26=$Y$13),$W$13))))))) | I26: =+IF(G26="","",IF(G26="N/A","",IF(OR(G26=$X$9,G26=$Y$9),$V$9,IF(OR(G26=$X$10,G26=$Y$10),$V$10,IF(OR(G26=$X$11,G26=$Y$11),$V$11,IF(OR(G26=$X$12,G26=$Y$12),$V$12,IF(OR(G26=$X$13,G26=$Y$13),$V$13))))))) | K26: =+IF(J26="","",IF(J26="N/A","",IF(OR(J26=$X$9,J26=$Y$9),$W$9,IF(OR(J26=$X$10,J26=$Y$10),$W$10,IF(OR(J26=$X$11,J26=$Y$11),$W$11,IF(OR(J26=$X$12,J26=$Y$12),$W$12,IF(OR(J26=$X$13,J26=$Y$13),$W$13))))))) | L26: =+IF(J26="","",IF(J26="N/A","",IF(OR(J26=$X$9,J26=$Y$9),$V$9,IF(OR(J26=$X$10,J26=$Y$10),$V$10,IF(OR(J26=$X$11,J26=$Y$11),$V$11,IF(OR(J26=$X$12,J26=$Y$12),$V$12,IF(OR(J26=$X$13,J26=$Y$13),$V$13))))))) | M26: =+IF(H26="",K26,IF(K26="",H26,IF(H26>K26,H26,K26))) | N26: =+IF(M26="","",IF(M26=$W$9,$V$9,IF(M26=$W$10,$V$10,IF(M26=$W$11,$V$11,IF(M26=$W$12,$V$12,IF(M26=$W$13,$V$13))))))
... A28: ='2 CONTEXTO E IDENTIFICACIÓN'!A28 -> R20 | B28: =+'2 CONTEXTO E IDENTIFICACIÓN'!K28 | D28: =+IF(C28="","",IF(C28<=$S$9,$Q$9,IF(C28<=$S$10,$Q$10,IF(C28<=$S$11,$Q$11,IF(C28<=$S$12,$Q$12,IF(C28>=$R$13,$Q$13,"")))))) | E28: =+IF(D28="","",IF(D28=$Q$9,$T$9,IF(D28=$Q$10,$T$10,IF(D28=$Q$11,$T$11,IF(D28=$Q$12,$T$12,IF(D28=$Q$13,$T$13)))))) | F28: =+IF(D28="","",IF(D28=$Q$9,$P$9,IF(D28=$Q$10,$P$10,IF(D28=$Q$11,$P$11,IF(D28=$Q$12,$P$12,IF(D28=$Q$13,$P$13)))))) | H28: =+IF(G28="","",IF(G28="N/A","",IF(OR(G28=$X$9,G28=$Y$9),$W$9,IF(OR(G28=$X$10,G28=$Y$10),$W$10,IF(OR(G28=$X$11,G28=$Y$11),$W$11,IF(OR(G28=$X$12,G28=$Y$12),$W$12,IF(OR(G28=$X$13,G28=$Y$13),$W$13))))))) | I28: =+IF(G28="","",IF(G28="N/A","",IF(OR(G28=$X$9,G28=$Y$9),$V$9,IF(OR(G28=$X$10,G28=$Y$10),$V$10,IF(OR(G28=$X$11,G28=$Y$11),$V$11,IF(OR(G28=$X$12,G28=$Y$12),$V$12,IF(OR(G28=$X$13,G28=$Y$13),$V$13))))))) | K28: =+IF(J28="","",IF(J28="N/A","",IF(OR(J28=$X$9,J28=$Y$9),$W$9,IF(OR(J28=$X$10,J28=$Y$10),$W$10,IF(OR(J28=$X$11,J28=$Y$11),$W$11,IF(OR(J28=$X$12,J28=$Y$12),$W$12,IF(OR(J28=$X$13,J28=$Y$13),$W$13))))))) | L28: =+IF(J28="","",IF(J28="N/A","",IF(OR(J28=$X$9,J28=$Y$9),$V$9,IF(OR(J28=$X$10,J28=$Y$10),$V$10,IF(OR(J28=$X$11,J28=$Y$11),$V$11,IF(OR(J28=$X$12,J28=$Y$12),$V$12,IF(OR(J28=$X$13,J28=$Y$13),$V$13))))))) | M28: =+IF(H28="",K28,IF(K28="",H28,IF(H28>K28,H28,K28))) | N28: =+IF(M28="","",IF(M28=$W$9,$V$9,IF(M28=$W$10,$V$10,IF(M28=$W$11,$V$11,IF(M28=$W$12,$V$12,IF(M28=$W$13,$V$13))))))

Sheet 4 MAPA CALOR INHERENTE
B1: =+'2 CONTEXTO E IDENTIFICACIÓN'!A1 -> MAPA DE RIESGOS
C2: =+'2 CONTEXTO E IDENTIFICACIÓN'!A2 -> VERSIÓN: | D2: ='2 CONTEXTO E IDENTIFICACIÓN'!B2 -> 1 | I2: =+'2 CONTEXTO E IDENTIFICACIÓN'!$J$4 -> Elaboración o Actualización: | J2: ='2 CONTEXTO E IDENTIFICACIÓN'!K4 -> 45991
I3: =+'2 CONTEXTO E IDENTIFICACIÓN'!$E$5 -> Vigencia: | J3: ='2 CONTEXTO E IDENTIFICACIÓN'!H5 -> 46023 | K3: Al | L3: ='2 CONTEXTO E IDENTIFICACIÓN'!K5 -> 46387
A4: ENTIDAD: | B4: ='2 CONTEXTO E IDENTIFICACIÓN'!B4 -> 0
A5: PROCESO: | B5: ='2 CONTEXTO E IDENTIFICACIÓN'!F4 -> 0
G6: MAPA DE CALOR RIESGO INHERENTE | R6: Impacto
C7: CALIFICACIÓN RIESGO INHERENTE | I7: Impacto | R7: 0.2 | S7: 0.4 | T7: 0.6 | U7: 0.8 | V7: 1
A8: No. DEL RIESGO | B8: RIESGO | C8: PROBABILIDAD | D8: IMPACTO | E8: SEVERIDAD (NIVEL DE RIESGO) | I8: Leve | J8: Menor | K8: Moderado | L8: Mayor | M8: Catastrófico | R8: Leve | S8: Menor | T8: Moderado | U8: Mayor | V8: Catastrófico
A9: ='2 CONTEXTO E IDENTIFICACIÓN'!A9 -> R1 | B9: =+'2 CONTEXTO E IDENTIFICACIÓN'!K9 -> Posibilidad de perdida de Disponibilidad, confidencialidad e integridad de la información por fallas en el sistema debido a deficiencias en la infraestructura tecnológica, ausencia o insuficiencia de mantenimiento preventivo y correctivo | C9: =+'3 PROBABIL E IMPACTO INHERENTE'!F9 -> Alta | D9: =+'3 PROBABIL E IMPACTO INHERENTE'!N9 -> Menor | E9: =+IF(C9=$Q$9,IF(D9=$R$8,$R$9,IF(D9=$S$8,$S$9,IF(D9=$T$8,$T$9,IF(D9=$U$8,$U$9,IF(D9=$V$8,$V$9))))),IF(C9=$Q$10,IF(D9=$R$8,$R$10,IF(D9=$S$8,$S$10,IF(D9=$T$8,$T$10,IF(D9=$U$8,$U$10,IF(D9=$V$8,$V$10))))),IF(C9=$Q$11,IF(D9=$R$8,$R$11,IF(D9=$S$8,$S$11,IF(D9=$T$8,$T$11,IF(D9=$U$8,$U$11,IF(D9=$V$8,$V$11))))),IF(C9=$Q$12,IF(D9=$R$8,$R$12,IF(D9=$S$8,$S$12,IF(D9=$T$8,$T$12,IF(D9=$U$8,$U$12,IF(D9=$V$8,$V$12))))),IF(C9=$Q$13,IF(D9=$R$8,$R$13,IF(D9=$S$8,$S$13,IF(D9=$T$8,$T$13,IF(D9=$U$8,$U$13,IF(D9=$V$8,$V$13))))),""))))) -> Moderado | G9: Probabilidad | H9: Muy Alta | I9: =+IF(AND(C9=$Q$9,D9=$R$8),A9,"")&" "&IF(AND(C10=$Q$9,D10=$R$8),A10,"")&" "&IF(AND(C11=$Q$9,D11=$R$8),A11,"")&" "&IF(AND(C12=$Q$9,D12=$R$8),A12,"")&" "&IF(AND(C13=$Q$9,D13=$R$8),A13,"")&" "&IF(AND(C14=$Q$9,D14=$R$8),A14,"")&" "&IF(AND(C15=$Q$9,D15=$R$8),A15,"")&" "&IF(AND(C16=$Q$9,D16=$R$8),A16,"")&" "&IF(AND(C17=$Q$9,D17=$R$8),A17,"")&" "&IF(AND(C18=$Q$9,D18=$R$8),A18,"")&" "&IF(AND(C19=$Q$9,D19=$R$8),A19,"")&" "&IF(AND(C20=$Q$9,D20=$R$8),A20,"")&" "&IF(AND(C21=$Q$9,D21=$R$8),A21,"")&" "&IF(AND(C22=$Q$9,D22=$R$8),A22,"")&" "&IF(AND(C23=$Q$9,D23=$R$8),A23,"")&" "&IF(AND(C24=$Q$9,D24=$R$8),A24,"")&" "&IF(AND(C25=$Q$9,D25=$R$8),A25,"")&" "&IF(AND(C26=$Q$9,D26=$R$8),A26,"")&" "&IF(AND(C27=$Q$9,D27=$R$8),A27,"")&" "&IF(AND(C28=$Q$9,D28=$R$8),A28,"") | J9: =+IF(AND(C9=$Q$9,D9=$S$8),A9,"")&" "&IF(AND(C10=$Q$9,D10=$S$8),A10,"")&" "&IF(AND(C11=$Q$9,D11=$S$8),A11,"")&" "&IF(AND(C12=$Q$9,D12=$S$8),A12,"")&" "&IF(AND(C13=$Q$9,D13=$S$8),A13,"")&" "&IF(AND(C14=$Q$9,D14=$S$8),A14,"")&" "&IF(AND(C15=$Q$9,D15=$S$8),A15,"")&" "&IF(AND(C16=$Q$9,D16=$S$8),A16,"")&" "&IF(AND(C17=$Q$9,D17=$S$8),A17,"")&" "&IF(AND(C18=$Q$9,D18=$S$8),A18,"")&" "&IF(AND(C19=$Q$9,D19=$S$8),A19,"")&" "&IF(AND(C20=$Q$9,D20=$S$8),A20,"")&" "&IF(AND(C21=$Q$9,D21=$S$8),A21,"")&" "&IF(AND(C22=$Q$9,D22=$S$8),A22,"")&" "&IF(AND(C23=$Q$9,D23=$S$8),A23,"")&" "&IF(AND(C24=$Q$9,D24=$S$8),A24,"")&" "&IF(AND(C25=$Q$9,D25=$S$8),A25,"")&" "&IF(AND(C26=$Q$9,D26=$S$8),A26,"")&" "&IF(AND(C27=$Q$9,D27=$S$8),A27,"")&" "&IF(AND(C28=$Q$9,D28=$S$8),A28,"") | K9: =+IF(AND(C9=$Q$9,D9=$T$8),A9,"")&" "&IF(AND(C10=$Q$9,D10=$T$8),A10,"")&" "&IF(AND(C11=$Q$9,D11=$T$8),A11,"")&" "&IF(AND(C12=$Q$9,D12=$T$8),A12,"")&" "&IF(AND(C13=$Q$9,D13=$T$8),A13,"")&" "&IF(AND(C14=$Q$9,D14=$T$8),A14,"")&" "&IF(AND(C15=$Q$9,D15=$T$8),A15,"")&" "&IF(AND(C16=$Q$9,D16=$T$8),A16,"")&" "&IF(AND(C17=$Q$9,D17=$T$8),A17,"")&" "&IF(AND(C18=$Q$9,D18=$T$8),A18,"")&" "&IF(AND(C19=$Q$9,D19=$T$8),A19,"")&" "&IF(AND(C20=$Q$9,D20=$T$8),A20,"")&" "&IF(AND(C21=$Q$9,D21=$T$8),A21,"")&" "&IF(AND(C22=$Q$9,D22=$T$8),A22,"")&" "&IF(AND(C23=$Q$9,D23=$T$8),A23,"")&" "&IF(AND(C24=$Q$9,D24=$T$8),A24,"")&" "&IF(AND(C25=$Q$9,D25=$T$8),A25,"")&" "&IF(AND(C26=$Q$9,D26=$T$8),A26,"")&" "&IF(AND(C27=$Q$9,D27=$T$8),A27,"")&" "&IF(AND(C28=$Q$9,D28=$T$8),A28,"") | L9: =+IF(AND(C9=$Q$9,D9=$U$8),A9,"")&" "&IF(AND(C10=$Q$9,D10=$U$8),A10,"")&" "&IF(AND(C11=$Q$9,D11=$U$8),A11,"")&" "&IF(AND(C12=$Q$9,D12=$U$8),A12,"")&" "&IF(AND(C13=$Q$9,D13=$U$8),A13,"")&" "&IF(AND(C14=$Q$9,D14=$U$8),A14,"")&" "&IF(AND(C15=$Q$9,D15=$U$8),A15,"")&" "&IF(AND(C16=$Q$9,D16=$U$8),A16,"")&" "&IF(AND(C17=$Q$9,D17=$U$8),A17,"")&" "&IF(AND(C18=$Q$9,D18=$U$8),A18,"")&" "&IF(AND(C19=$Q$9,D19=$U$8),A19,"")&" "&IF(AND(C20=$Q$9,D20=$U$8),A20,"")&" "&IF(AND(C21=$Q$9,D21=$U$8),A21,"")&" "&IF(AND(C22=$Q$9,D22=$U$8),A22,"")&" "&IF(AND(C23=$Q$9,D23=$U$8),A23,"")&" "&IF(AND(C24=$Q$9,D24=$U$8),A24,"")&" "&IF(AND(C25=$Q$9,D25=$U$8),A25,"")&" "&IF(AND(C26=$Q$9,D26=$U$8),A26,"")&" "&IF(AND(C27=$Q$9,D27=$U$8),A27,"")&" "&IF(AND(C28=$Q$9,D28=$U$8),A28,"") | M9: =+IF(AND(C9=$Q$9,D9=$V$8),A9,"")&" "&IF(AND(C10=$Q$9,D10=$V$8),A10,"")&" "&IF(AND(C11=$Q$9,D11=$V$8),A11,"")&" "&IF(AND(C12=$Q$9,D12=$V$8),A12,"")&" "&IF(AND(C13=$Q$9,D13=$V$8),A13,"")&" "&IF(AND(C14=$Q$9,D14=$V$8),A14,"")&" "&IF(AND(C15=$Q$9,D15=$V$8),A15,"")&" "&IF(AND(C16=$Q$9,D16=$V$8),A16,"")&" "&IF(AND(C17=$Q$9,D17=$V$8),A17,"")&" "&IF(AND(C18=$Q$9,D18=$V$8),A18,"")&" "&IF(AND(C19=$Q$9,D19=$V$8),A19,"")&" "&IF(AND(C20=$Q$9,D20=$V$8),A20,"")&" "&IF(AND(C21=$Q$9,D21=$V$8),A21,"")&" "&IF(AND(C22=$Q$9,D22=$V$8),A22,"")&" "&IF(AND(C23=$Q$9,D23=$V$8),A23,"")&" "&IF(AND(C24=$Q$9,D24=$V$8),A24,"")&" "&IF(AND(C25=$Q$9,D25=$V$8),A25,"")&" "&IF(AND(C26=$Q$9,D26=$V$8),A26,"")&" "&IF(AND(C27=$Q$9,D27=$V$8),A27,"")&" "&IF(AND(C28=$Q$9,D28=$V$8),A28,"") | O9: Probabilidad | P9: 1 | Q9: Muy Alta | R9: Alto | S9: Alto | T9: Alto | U9: Alto | V9: Extremo
A10: ='2 CONTEXTO E IDENTIFICACIÓN'!A10 -> R2 | B10: =+'2 CONTEXTO E IDENTIFICACIÓN'!K10 -> Posibilidad de perdida de Disponibilidad, confidencialidad e integridad de la información por accesos no autorizados, hackeos o fallas en el servicio debido a controles de seguridad y autenticación de usuarios, falta de actualización o monitoreo de la plataforma | C10: =+'3 PROBABIL E IMPACTO INHERENTE'!F10 -> Alta | D10: =+'3 PROBABIL E IMPACTO INHERENTE'!N10 -> Mayor | E10: =+IF(C10=$Q$9,IF(D10=$R$8,$R$9,IF(D10=$S$8,$S$9,IF(D10=$T$8,$T$9,IF(D10=$U$8,$U$9,IF(D10=$V$8,$V$9))))),IF(C10=$Q$10,IF(D10=$R$8,$R$10,IF(D10=$S$8,$S$10,IF(D10=$T$8,$T$10,IF(D10=$U$8,$U$10,IF(D10=$V$8,$V$10))))),IF(C10=$Q$11,IF(D10=$R$8,$R$11,IF(D10=$S$8,$S$11,IF(D10=$T$8,$T$11,IF(D10=$U$8,$U$11,IF(D10=$V$8,$V$11))))),IF(C10=$Q$12,IF(D10=$R$8,$R$12,IF(D10=$S$8,$S$12,IF(D10=$T$8,$T$12,IF(D10=$U$8,$U$12,IF(D10=$V$8,$V$12))))),IF(C10=$Q$13,IF(D10=$R$8,$R$13,IF(D10=$S$8,$S$13,IF(D10=$T$8,$T$13,IF(D10=$U$8,$U$13,IF(D10=$V$8,$V$13))))),""))))) -> Alto | H10: Alta | I10: =+IF(AND(C9=$Q$10,D9=$R$8),A9,"")&" "&IF(AND(C10=$Q$10,D10=$R$8),A10,"")&" "&IF(AND(C11=$Q$10,D11=$R$8),A11,"")&" "&IF(AND(C12=$Q$10,D12=$R$8),A12,"")&" "&IF(AND(C13=$Q$10,D13=$R$8),A13,"")&" "&IF(AND(C14=$Q$10,D14=$R$8),A14,"")&" "&IF(AND(C15=$Q$10,D15=$R$8),A15,"")&" "&IF(AND(C16=$Q$10,D16=$R$8),A16,"")&" "&IF(AND(C17=$Q$10,D17=$R$8),A17,"")&" "&IF(AND(C18=$Q$10,D18=$R$8),A18,"")&" "&IF(AND(C19=$Q$10,D19=$R$8),A19,"")&" "&IF(AND(C20=$Q$10,D20=$R$8),A20,"")&" "&IF(AND(C21=$Q$10,D21=$R$8),A21,"")&" "&IF(AND(C22=$Q$10,D22=$R$8),A22,"")&" "&IF(AND(C23=$Q$10,D23=$R$8),A23,"")&" "&IF(AND(C24=$Q$10,D24=$R$8),A24,"")&" "&IF(AND(C25=$Q$10,D25=$R$8),A25,"")&" "&IF(AND(C26=$Q$10,D26=$R$8),A26,"")&" "&IF(AND(C27=$Q$10,D27=$R$8),A27,"")&" "&IF(AND(C28=$Q$10,D28=$R$8),A28,"") | J10: =+IF(AND(C9=$Q$10,D9=$S$8),A9,"")&" "&IF(AND(C10=$Q$10,D10=$S$8),A10,"")&" "&IF(AND(C11=$Q$10,D11=$S$8),A11,"")&" "&IF(AND(C12=$Q$10,D12=$S$8),A12,"")&" "&IF(AND(C13=$Q$10,D13=$S$8),A13,"")&" "&IF(AND(C14=$Q$10,D14=$S$8),A14,"")&" "&IF(AND(C15=$Q$10,D15=$S$8),A15,"")&" "&IF(AND(C16=$Q$10,D16=$S$8),A16,"")&" "&IF(AND(C17=$Q$10,D17=$S$8),A17,"")&" "&IF(AND(C18=$Q$10,D18=$S$8),A18,"")&" "&IF(AND(C19=$Q$10,D19=$S$8),A19,"")&" "&IF(AND(C20=$Q$10,D20=$S$8),A20,"")&" "&IF(AND(C21=$Q$10,D21=$S$8),A21,"")&" "&IF(AND(C22=$Q$10,D22=$S$8),A22,"")&" "&IF(AND(C23=$Q$10,D23=$S$8),A23,"")&" "&IF(AND(C24=$Q$10,D24=$S$8),A24,"")&" "&IF(AND(C25=$Q$10,D25=$S$8),A25,"")&" "&IF(AND(C26=$Q$10,D26=$S$8),A26,"")&" "&IF(AND(C27=$Q$10,D27=$S$8),A27,"")&" "&IF(AND(C28=$Q$10,D28=$S$8),A28,"") -> R1 R4 | K10: =+IF(AND(C9=$Q$10,D9=$T$8),A9,"")&" "&IF(AND(C10=$Q$10,D10=$T$8),A10,"")&" "&IF(AND(C11=$Q$10,D11=$T$8),A11,"")&" "&IF(AND(C12=$Q$10,D12=$T$8),A12,"")&" "&IF(AND(C13=$Q$10,D13=$T$8),A13,"")&" "&IF(AND(C14=$Q$10,D14=$T$8),A14,"")&" "&IF(AND(C15=$Q$10,D15=$T$8),A15,"")&" "&IF(AND(C16=$Q$10,D16=$T$8),A16,"")&" "&IF(AND(C17=$Q$10,D17=$T$8),A17,"")&" "&IF(AND(C18=$Q$10,D18=$T$8),A18,"")&" "&IF(AND(C19=$Q$10,D19=$T$8),A19,"")&" "&IF(AND(C20=$Q$10,D20=$T$8),A20,"")&" "&IF(AND(C21=$Q$10,D21=$T$8),A21,"")&" "&IF(AND(C22=$Q$10,D22=$T$8),A22,"")&" "&IF(AND(C23=$Q$10,D23=$T$8),A23,"")&" "&IF(AND(C24=$Q$10,D24=$T$8),A24,"")&" "&IF(AND(C25=$Q$10,D25=$T$8),A25,"")&" "&IF(AND(C26=$Q$10,D26=$T$8),A26,"")&" "&IF(AND(C27=$Q$10,D27=$T$8),A27,"")&" "&IF(AND(C28=$Q$10,D28=$T$8),A28,"") | L10: =+IF(AND(C9=$Q$10,D9=$U$8),A9,"")&" "&IF(AND(C10=$Q$10,D10=$U$8),A10,"")&" "&IF(AND(C11=$Q$10,D11=$U$8),A11,"")&" "&IF(AND(C12=$Q$10,D12=$U$8),A12,"")&" "&IF(AND(C13=$Q$10,D13=$U$8),A13,"")&" "&IF(AND(C14=$Q$10,D14=$U$8),A14,"")&" "&IF(AND(C15=$Q$10,D15=$U$8),A15,"")&" "&IF(AND(C16=$Q$10,D16=$U$8),A16,"")&" "&IF(AND(C17=$Q$10,D17=$U$8),A17,"")&" "&IF(AND(C18=$Q$10,D18=$U$8),A18,"")&" "&IF(AND(C19=$Q$10,D19=$U$8),A19,"")&" "&IF(AND(C20=$Q$10,D20=$U$8),A20,"")&" "&IF(AND(C21=$Q$10,D21=$U$8),A21,"")&" "&IF(AND(C22=$Q$10,D22=$U$8),A22,"")&" "&IF(AND(C23=$Q$10,D23=$U$8),A23,"")&" "&IF(AND(C24=$Q$10,D24=$U$8),A24,"")&" "&IF(AND(C25=$Q$10,D25=$U$8),A25,"")&" "&IF(AND(C26=$Q$10,D26=$U$8),A26,"")&" "&IF(AND(C27=$Q$10,D27=$U$8),A27,"")&" "&IF(AND(C28=$Q$10,D28=$U$8),A28,"") -> R2 R3 | M10: =+IF(AND(C9=$Q$10,D9=$V$8),A9,"")&" "&IF(AND(C10=$Q$10,D10=$V$8),A10,"")&" "&IF(AND(C11=$Q$10,D11=$V$8),A11,"")&" "&IF(AND(C12=$Q$10,D12=$V$8),A12,"")&" "&IF(AND(C13=$Q$10,D13=$V$8),A13,"")&" "&IF(AND(C14=$Q$10,D14=$V$8),A14,"")&" "&IF(AND(C15=$Q$10,D15=$V$8),A15,"")&" "&IF(AND(C16=$Q$10,D16=$V$8),A16,"")&" "&IF(AND(C17=$Q$10,D17=$V$8),A17,"")&" "&IF(AND(C18=$Q$10,D18=$V$8),A18,"")&" "&IF(AND(C19=$Q$10,D19=$V$8),A19,"")&" "&IF(AND(C20=$Q$10,D20=$V$8),A20,"")&" "&IF(AND(C21=$Q$10,D21=$V$8),A21,"")&" "&IF(AND(C22=$Q$10,D22=$V$8),A22,"")&" "&IF(AND(C23=$Q$10,D23=$V$8),A23,"")&" "&IF(AND(C24=$Q$10,D24=$V$8),A24,"")&" "&IF(AND(C25=$Q$10,D25=$V$8),A25,"")&" "&IF(AND(C26=$Q$10,D26=$V$8),A26,"")&" "&IF(AND(C27=$Q$10,D27=$V$8),A27,"")&" "&IF(AND(C28=$Q$10,D28=$V$8),A28,"") | P10: 0.8 | Q10: Alta | R10: Moderado | S10: Moderado | T10: Alto | U10: Alto | V10: Extremo
A11: ='2 CONTEXTO E IDENTIFICACIÓN'!A11 -> R3 | B11: =+'2 CONTEXTO E IDENTIFICACIÓN'!K11 -> Posibilidad de perdida de Disponibilidad, confidencialidad e integridad de la información por eliminación accidental de archivos, fallas en el sistema o accesos no autorizados a causa de deficiencias en copias de seguridad, controles de accesos o ausencia de politicas de preservación digital | C11: =+'3 PROBABIL E IMPACTO INHERENTE'!F11 -> Alta | D11: =+'3 PROBABIL E IMPACTO INHERENTE'!N11 -> Mayor | E11: =+IF(C11=$Q$9,IF(D11=$R$8,$R$9,IF(D11=$S$8,$S$9,IF(D11=$T$8,$T$9,IF(D11=$U$8,$U$9,IF(D11=$V$8,$V$9))))),IF(C11=$Q$10,IF(D11=$R$8,$R$10,IF(D11=$S$8,$S$10,IF(D11=$T$8,$T$10,IF(D11=$U$8,$U$10,IF(D11=$V$8,$V$10))))),IF(C11=$Q$11,IF(D11=$R$8,$R$11,IF(D11=$S$8,$S$11,IF(D11=$T$8,$T$11,IF(D11=$U$8,$U$11,IF(D11=$V$8,$V$11))))),IF(C11=$Q$12,IF(D11=$R$8,$R$12,IF(D11=$S$8,$S$12,IF(D11=$T$8,$T$12,IF(D11=$U$8,$U$12,IF(D11=$V$8,$V$12))))),IF(C11=$Q$13,IF(D11=$R$8,$R$13,IF(D11=$S$8,$S$13,IF(D11=$T$8,$T$13,IF(D11=$U$8,$U$13,IF(D11=$V$8,$V$13))))),""))))) -> Alto | H11: Media | I11: =+IF(AND(C9=$Q$11,D9=$R$8),A9,"")&" "&IF(AND(C10=$Q$11,D10=$R$8),A10,"")&" "&IF(AND(C11=$Q$11,D11=$R$8),A11,"")&" "&IF(AND(C12=$Q$11,D12=$R$8),A12,"")&" "&IF(AND(C13=$Q$11,D13=$R$8),A13,"")&" "&IF(AND(C14=$Q$11,D14=$R$8),A14,"")&" "&IF(AND(C15=$Q$11,D15=$R$8),A15,"")&" "&IF(AND(C16=$Q$11,D16=$R$8),A16,"")&" "&IF(AND(C17=$Q$11,D17=$R$8),A17,"")&" "&IF(AND(C18=$Q$11,D18=$R$8),A18,"")&" "&IF(AND(C19=$Q$11,D19=$R$8),A19,"")&" "&IF(AND(C20=$Q$11,D20=$R$8),A20,"")&" "&IF(AND(C21=$Q$11,D21=$R$8),A21,"")&" "&IF(AND(C22=$Q$11,D22=$R$8),A22,"")&" "&IF(AND(C23=$Q$11,D23=$R$8),A23,"")&" "&IF(AND(C24=$Q$11,D24=$R$8),A24,"")&" "&IF(AND(C25=$Q$11,D25=$R$8),A25,"")&" "&IF(AND(C26=$Q$11,D26=$R$8),A26,"")&" "&IF(AND(C27=$Q$11,D27=$R$8),A27,"")&" "&IF(AND(C28=$Q$11,D28=$R$8),A28,"") | J11: =+IF(AND(C9=$Q$11,D9=$S$8),A9,"")&" "&IF(AND(C10=$Q$11,D10=$S$8),A10,"")&" "&IF(AND(C11=$Q$11,D11=$S$8),A11,"")&" "&IF(AND(C12=$Q$11,D12=$S$8),A12,"")&" "&IF(AND(C13=$Q$11,D13=$S$8),A13,"")&" "&IF(AND(C14=$Q$11,D14=$S$8),A14,"")&" "&IF(AND(C15=$Q$11,D15=$S$8),A15,"")&" "&IF(AND(C16=$Q$11,D16=$S$8),A16,"")&" "&IF(AND(C17=$Q$11,D17=$S$8),A17,"")&" "&IF(AND(C18=$Q$11,D18=$S$8),A18,"")&" "&IF(AND(C19=$Q$11,D19=$S$8),A19,"")&" "&IF(AND(C20=$Q$11,D20=$S$8),A20,"")&" "&IF(AND(C21=$Q$11,D21=$S$8),A21,"")&" "&IF(AND(C22=$Q$11,D22=$S$8),A22,"")&" "&IF(AND(C23=$Q$11,D23=$S$8),A23,"")&" "&IF(AND(C24=$Q$11,D24=$S$8),A24,"")&" "&IF(AND(C25=$Q$11,D25=$S$8),A25,"")&" "&IF(AND(C26=$Q$11,D26=$S$8),A26,"")&" "&IF(AND(C27=$Q$11,D27=$S$8),A27,"")&" "&IF(AND(C28=$Q$11,D28=$S$8),A28,"") | K11: =+IF(AND(C9=$Q$11,D9=$T$8),A9,"")&" "&IF(AND(C10=$Q$11,D10=$T$8),A10,"")&" "&IF(AND(C11=$Q$11,D11=$T$8),A11,"")&" "&IF(AND(C12=$Q$11,D12=$T$8),A12,"")&" "&IF(AND(C13=$Q$11,D13=$T$8),A13,"")&" "&IF(AND(C14=$Q$11,D14=$T$8),A14,"")&" "&IF(AND(C15=$Q$11,D15=$T$8),A15,"")&" "&IF(AND(C16=$Q$11,D16=$T$8),A16,"")&" "&IF(AND(C17=$Q$11,D17=$T$8),A17,"")&" "&IF(AND(C18=$Q$11,D18=$T$8),A18,"")&" "&IF(AND(C19=$Q$11,D19=$T$8),A19,"")&" "&IF(AND(C20=$Q$11,D20=$T$8),A20,"")&" "&IF(AND(C21=$Q$11,D21=$T$8),A21,"")&" "&IF(AND(C22=$Q$11,D22=$T$8),A22,"")&" "&IF(AND(C23=$Q$11,D23=$T$8),A23,"")&" "&IF(AND(C24=$Q$11,D24=$T$8),A24,"")&" "&IF(AND(C25=$Q$11,D25=$T$8),A25,"")&" "&IF(AND(C26=$Q$11,D26=$T$8),A26,"")&" "&IF(AND(C27=$Q$11,D27=$T$8),A27,"")&" "&IF(AND(C28=$Q$11,D28=$T$8),A28,"") -> R5 | L11: =+IF(AND(C9=$Q$11,D9=$U$8),A9,"")&" "&IF(AND(C10=$Q$11,D10=$U$8),A10,"")&" "&IF(AND(C11=$Q$11,D11=$U$8),A11,"")&" "&IF(AND(C12=$Q$11,D12=$U$8),A12,"")&" "&IF(AND(C13=$Q$11,D13=$U$8),A13,"")&" "&IF(AND(C14=$Q$11,D14=$U$8),A14,"")&" "&IF(AND(C15=$Q$11,D15=$U$8),A15,"")&" "&IF(AND(C16=$Q$11,D16=$U$8),A16,"")&" "&IF(AND(C17=$Q$11,D17=$U$8),A17,"")&" "&IF(AND(C18=$Q$11,D18=$U$8),A18,"")&" "&IF(AND(C19=$Q$11,D19=$U$8),A19,"")&" "&IF(AND(C20=$Q$11,D20=$U$8),A20,"")&" "&IF(AND(C21=$Q$11,D21=$U$8),A21,"")&" "&IF(AND(C22=$Q$11,D22=$U$8),A22,"")&" "&IF(AND(C23=$Q$11,D23=$U$8),A23,"")&" "&IF(AND(C24=$Q$11,D24=$U$8),A24,"")&" "&IF(AND(C25=$Q$11,D25=$U$8),A25,"")&" "&IF(AND(C26=$Q$11,D26=$U$8),A26,"")&" "&IF(AND(C27=$Q$11,D27=$U$8),A27,"")&" "&IF(AND(C28=$Q$11,D28=$U$8),A28,"") | M11: =+IF(AND(C9=$Q$11,D9=$V$8),A9,"")&" "&IF(AND(C10=$Q$11,D10=$V$8),A10,"")&" "&IF(AND(C11=$Q$11,D11=$V$8),A11,"")&" "&IF(AND(C12=$Q$11,D12=$V$8),A12,"")&" "&IF(AND(C13=$Q$11,D13=$V$8),A13,"")&" "&IF(AND(C14=$Q$11,D14=$V$8),A14,"")&" "&IF(AND(C15=$Q$11,D15=$V$8),A15,"")&" "&IF(AND(C16=$Q$11,D16=$V$8),A16,"")&" "&IF(AND(C17=$Q$11,D17=$V$8),A17,"")&" "&IF(AND(C18=$Q$11,D18=$V$8),A18,"")&" "&IF(AND(C19=$Q$11,D19=$V$8),A19,"")&" "&IF(AND(C20=$Q$11,D20=$V$8),A20,"")&" "&IF(AND(C21=$Q$11,D21=$V$8),A21,"")&" "&IF(AND(C22=$Q$11,D22=$V$8),A22,"")&" "&IF(AND(C23=$Q$11,D23=$V$8),A23,"")&" "&IF(AND(C24=$Q$11,D24=$V$8),A24,"")&" "&IF(AND(C25=$Q$11,D25=$V$8),A25,"")&" "&IF(AND(C26=$Q$11,D26=$V$8),A26,"")&" "&IF(AND(C27=$Q$11,D27=$V$8),A27,"")&" "&IF(AND(C28=$Q$11,D28=$V$8),A28,"") | P11: 0.6 | Q11: Media | R11: Moderado | S11: Moderado | T11: Moderado | U11: Alto | V11: Extremo
A12: ='2 CONTEXTO E IDENTIFICACIÓN'!A12 -> R4 | B12: =+'2 CONTEXTO E IDENTIFICACIÓN'!K12 -> Posibilidad de perdida de Disponibilidad, confidencialidad e integridad de la información por fallas tecnológicas y manipulación indebida de la información o interrupciones del servicio debido a falta de actualización tecnólogica, vulnerabilidades en la administración de la plataforma o controles de seguridad avanzados | C12: =+'3 PROBABIL E IMPACTO INHERENTE'!F12 -> Alta | D12: =+'3 PROBABIL E IMPACTO INHERENTE'!N12 -> Menor | E12: =+IF(C12=$Q$9,IF(D12=$R$8,$R$9,IF(D12=$S$8,$S$9,IF(D12=$T$8,$T$9,IF(D12=$U$8,$U$9,IF(D12=$V$8,$V$9))))),IF(C12=$Q$10,IF(D12=$R$8,$R$10,IF(D12=$S$8,$S$10,IF(D12=$T$8,$T$10,IF(D12=$U$8,$U$10,IF(D12=$V$8,$V$10))))),IF(C12=$Q$11,IF(D12=$R$8,$R$11,IF(D12=$S$8,$S$11,IF(D12=$T$8,$T$11,IF(D12=$U$8,$U$11,IF(D12=$V$8,$V$11))))),IF(C12=$Q$12,IF(D12=$R$8,$R$12,IF(D12=$S$8,$S$12,IF(D12=$T$8,$T$12,IF(D12=$U$8,$U$12,IF(D12=$V$8,$V$12))))),IF(C12=$Q$13,IF(D12=$R$8,$R$13,IF(D12=$S$8,$S$13,IF(D12=$T$8,$T$13,IF(D12=$U$8,$U$13,IF(D12=$V$8,$V$13))))),""))))) -> Moderado | H12: Baja | I12: =+IF(AND(C9=$Q$12,D9=$R$8),A9,"")&" "&IF(AND(C10=$Q$12,D10=$R$8),A10,"")&" "&IF(AND(C11=$Q$12,D11=$R$8),A11,"")&" "&IF(AND(C12=$Q$12,D12=$R$8),A12,"")&" "&IF(AND(C13=$Q$12,D13=$R$8),A13,"")&" "&IF(AND(C14=$Q$12,D14=$R$8),A14,"")&" "&IF(AND(C15=$Q$12,D15=$R$8),A15,"")&" "&IF(AND(C16=$Q$12,D16=$R$8),A16,"")&" "&IF(AND(C17=$Q$12,D17=$R$8),A17,"")&" "&IF(AND(C18=$Q$12,D18=$R$8),A18,"")&" "&IF(AND(C19=$Q$12,D19=$R$8),A19,"")&" "&IF(AND(C20=$Q$12,D20=$R$8),A20,"")&" "&IF(AND(C21=$Q$12,D21=$R$8),A21,"")&" "&IF(AND(C22=$Q$12,D22=$R$8),A22,"")&" "&IF(AND(C23=$Q$12,D23=$R$8),A23,"")&" "&IF(AND(C24=$Q$12,D24=$R$8),A24,"")&" "&IF(AND(C25=$Q$12,D25=$R$8),A25,"")&" "&IF(AND(C26=$Q$12,D26=$R$8),A26,"")&" "&IF(AND(C27=$Q$12,D27=$R$8),A27,"")&" "&IF(AND(C28=$Q$12,D28=$R$8),A28,"") | J12: =+IF(AND(C9=$Q$12,D9=$S$8),A9,"")&" "&IF(AND(C10=$Q$12,D10=$S$8),A10,"")&" "&IF(AND(C11=$Q$12,D11=$S$8),A11,"")&" "&IF(AND(C12=$Q$12,D12=$S$8),A12,"")&" "&IF(AND(C13=$Q$12,D13=$S$8),A13,"")&" "&IF(AND(C14=$Q$12,D14=$S$8),A14,"")&" "&IF(AND(C15=$Q$12,D15=$S$8),A15,"")&" "&IF(AND(C16=$Q$12,D16=$S$8),A16,"")&" "&IF(AND(C17=$Q$12,D17=$S$8),A17,"")&" "&IF(AND(C18=$Q$12,D18=$S$8),A18,"")&" "&IF(AND(C19=$Q$12,D19=$S$8),A19,"")&" "&IF(AND(C20=$Q$12,D20=$S$8),A20,"")&" "&IF(AND(C21=$Q$12,D21=$S$8),A21,"")&" "&IF(AND(C22=$Q$12,D22=$S$8),A22,"")&" "&IF(AND(C23=$Q$12,D23=$S$8),A23,"")&" "&IF(AND(C24=$Q$12,D24=$S$8),A24,"")&" "&IF(AND(C25=$Q$12,D25=$S$8),A25,"")&" "&IF(AND(C26=$Q$12,D26=$S$8),A26,"")&" "&IF(AND(C27=$Q$12,D27=$S$8),A27,"")&" "&IF(AND(C28=$Q$12,D28=$S$8),A28,"") | K12: =+IF(AND(C9=$Q$12,D9=$T$8),A9,"")&" "&IF(AND(C10=$Q$12,D10=$T$8),A10,"")&" "&IF(AND(C11=$Q$12,D11=$T$8),A11,"")&" "&IF(AND(C12=$Q$12,D12=$T$8),A12,"")&" "&IF(AND(C13=$Q$12,D13=$T$8),A13,"")&" "&IF(AND(C14=$Q$12,D14=$T$8),A14,"")&" "&IF(AND(C15=$Q$12,D15=$T$8),A15,"")&" "&IF(AND(C16=$Q$12,D16=$T$8),A16,"")&" "&IF(AND(C17=$Q$12,D17=$T$8),A17,"")&" "&IF(AND(C18=$Q$12,D18=$T$8),A18,"")&" "&IF(AND(C19=$Q$12,D19=$T$8),A19,"")&" "&IF(AND(C20=$Q$12,D20=$T$8),A20,"")&" "&IF(AND(C21=$Q$12,D21=$T$8),A21,"")&" "&IF(AND(C22=$Q$12,D22=$T$8),A22,"")&" "&IF(AND(C23=$Q$12,D23=$T$8),A23,"")&" "&IF(AND(C24=$Q$12,D24=$T$8),A24,"")&" "&IF(AND(C25=$Q$12,D25=$T$8),A25,"")&" "&IF(AND(C26=$Q$12,D26=$T$8),A26,"")&" "&IF(AND(C27=$Q$12,D27=$T$8),A27,"")&" "&IF(AND(C28=$Q$12,D28=$T$8),A28,"") | L12: =+IF(AND(C9=$Q$12,D9=$U$8),A9,"")&" "&IF(AND(C10=$Q$12,D10=$U$8),A10,"")&" "&IF(AND(C11=$Q$12,D11=$U$8),A11,"")&" "&IF(AND(C12=$Q$12,D12=$U$8),A12,"")&" "&IF(AND(C13=$Q$12,D13=$U$8),A13,"")&" "&IF(AND(C14=$Q$12,D14=$U$8),A14,"")&" "&IF(AND(C15=$Q$12,D15=$U$8),A15,"")&" "&IF(AND(C16=$Q$12,D16=$U$8),A16,"")&" "&IF(AND(C17=$Q$12,D17=$U$8),A17,"")&" "&IF(AND(C18=$Q$12,D18=$U$8),A18,"")&" "&IF(AND(C19=$Q$12,D19=$U$8),A19,"")&" "&IF(AND(C20=$Q$12,D20=$U$8),A20,"")&" "&IF(AND(C21=$Q$12,D21=$U$8),A21,"")&" "&IF(AND(C22=$Q$12,D22=$U$8),A22,"")&" "&IF(AND(C23=$Q$12,D23=$U$8),A23,"")&" "&IF(AND(C24=$Q$12,D24=$U$8),A24,"")&" "&IF(AND(C25=$Q$12,D25=$U$8),A25,"")&" "&IF(AND(C26=$Q$12,D26=$U$8),A26,"")&" "&IF(AND(C27=$Q$12,D27=$U$8),A27,"")&" "&IF(AND(C28=$Q$12,D28=$U$8),A28,"") | M12: =+IF(AND(C9=$Q$12,D9=$V$8),A9,"")&" "&IF(AND(C10=$Q$12,D10=$V$8),A10,"")&" "&IF(AND(C11=$Q$12,D11=$V$8),A11,"")&" "&IF(AND(C12=$Q$12,D12=$V$8),A12,"")&" "&IF(AND(C13=$Q$12,D13=$V$8),A13,"")&" "&IF(AND(C14=$Q$12,D14=$V$8),A14,"")&" "&IF(AND(C15=$Q$12,D15=$V$8),A15,"")&" "&IF(AND(C16=$Q$12,D16=$V$8),A16,"")&" "&IF(AND(C17=$Q$12,D17=$V$8),A17,"")&" "&IF(AND(C18=$Q$12,D18=$V$8),A18,"")&" "&IF(AND(C19=$Q$12,D19=$V$8),A19,"")&" "&IF(AND(C20=$Q$12,D20=$V$8),A20,"")&" "&IF(AND(C21=$Q$12,D21=$V$8),A21,"")&" "&IF(AND(C22=$Q$12,D22=$V$8),A22,"")&" "&IF(AND(C23=$Q$12,D23=$V$8),A23,"")&" "&IF(AND(C24=$Q$12,D24=$V$8),A24,"")&" "&IF(AND(C25=$Q$12,D25=$V$8),A25,"")&" "&IF(AND(C26=$Q$12,D26=$V$8),A26,"")&" "&IF(AND(C27=$Q$12,D27=$V$8),A27,"")&" "&IF(AND(C28=$Q$12,D28=$V$8),A28,"") | P12: 0.4 | Q12: Baja | R12: Bajo | S12: Moderado | T12: Moderado | U12: Alto | V12: Extremo
